Workbook

Sheet RESUMO
B2: PEC | G2: Q. PROFISSIONAL | L2: OUTLET
B3: DESCRIÇÃO | C3: VALOR | D3: TOTAL | E3: MESES | G3: DESCRIÇÃO | H3: VALOR | I3: TOTAL | J3: MESES | L3: DESCRIÇÃO | M3: VALOR | N3: TOTAL | O3: MESES
B4: =PEC!B50 -> Marketing | C4: =SUM(D4/E4) -> 0 | D4: =PEC!O50 -> 0 | E4: 11 | G4: ='Q. PROF.'!B50 -> Marketing | H4: =SUM(I4/J4) -> 0 | I4: ='Q. PROF.'!O50 -> 0 | J4: 11 | L4: =OUTLET!B50 -> Marketing | M4: =SUM(N4/O4) -> 46.363636 | N4: =OUTLET!O50 -> 510 | O4: 11
B5: =PEC!B53 -> Despesas com Pessoal | C5: =SUM(D5/E5) -> 12000 | D5: =PEC!O53 -> 144000 | E5: 12 | G5: ='Q. PROF.'!B53 -> Despesas com Pessoal | H5: =SUM(I5/J5) -> 7300 | I5: ='Q. PROF.'!O53 -> 87600 | J5: 12 | L5: =OUTLET!B53 -> Despesas com Pessoal | M5: =SUM(N5/O5) -> 6650 | N5: =OUTLET!O53 -> 79800 | O5: 12
B6: =PEC!B75 -> Despesas Administrativas | C6: =SUM(D6/E6) -> 6720.8333 | D6: =PEC!O75 -> 80650 | E6: 12 | G6: ='Q. PROF.'!B75 -> Despesas Administrativas | H6: =SUM(I6/J6) -> 812.5 | I6: ='Q. PROF.'!O75 -> 9750 | J6: 12 | L6: =OUTLET!B75 -> Despesas Administrativas | M6: =SUM(N6/O6) -> 3537.5 | N6: =OUTLET!O75 -> 42450 | O6: 12
B7: =PEC!B99 -> Despesas Financeiras / Bancos | C7: =SUM(D7/E7) -> 0 | D7: =PEC!O99 -> 0 | E7: 12 | G7: ='Q. PROF.'!B99 -> Despesas Financeiras / Bancos | H7: =SUM(I7/J7) -> 0 | I7: ='Q. PROF.'!O99 -> 0 | J7: 12 | L7: =OUTLET!B99 -> Despesas Financeiras / Bancos | M7: =SUM(N7/O7) -> 50 | N7: =OUTLET!O99 -> 600 | O7: 12
B8: =PEC!B105 -> Impostos e Taxas | C8: =SUM(D8/E8) -> 0 | D8: =PEC!O105 -> 0 | E8: 12 | G8: ='Q. PROF.'!B105 -> Impostos e Taxas | H8: =SUM(I8/J8) -> 0 | I8: ='Q. PROF.'!O105 -> 0 | J8: 12 | L8: =OUTLET!B105 -> Impostos e Taxas | M8: =SUM(N8/O8) -> 0 | N8: =OUTLET!O105 -> 0 | O8: 12
B9: =PEC!B116 -> Investimento | C9: =SUM(D9/E9) -> 1550 | D9: =PEC!O116 -> 18600 | E9: 12 | G9: ='Q. PROF.'!B116 -> Investimento | H9: =SUM(I9/J9) -> 0 | I9: ='Q. PROF.'!O116 -> 0 | J9: 12 | L9: =OUTLET!B116 -> Investimento | M9: =SUM(N9/O9) -> 0 | N9: =OUTLET!O116 -> 0 | O9: 12
B10: =PEC!B126 -> Despesas Com Veículos | C10: =SUM(D10/E10) -> 0 | D10: =PEC!O126 -> 0 | E10: 11 | G10: ='Q. PROF.'!B126 -> Despesas Com Veículos | H10: =SUM(I10/J10) -> 0 | I10: ='Q. PROF.'!O126 -> 0 | J10: 11 | L10: =OUTLET!B126 -> Despesas Com Veículos | M10: =SUM(N10/O10) -> 0 | N10: =OUTLET!O126 -> 0 | O10: 11
B11: =PEC!B130 -> Despesas Com Eventos | C11: =SUM(D11/E11) -> 4163.6364 | D11: =PEC!O130 -> 45800 | E11: 11 | G11: ='Q. PROF.'!B130 -> Despesas Com Eventos | H11: =SUM(I11/J11) -> 0 | I11: ='Q. PROF.'!O130 -> 0 | J11: 11 | L11: =OUTLET!B130 -> Despesas Com Eventos | M11: =SUM(N11/O11) -> 0 | N11: =OUTLET!O130 -> 0 | O11: 11
B12: =PEC!B133 -> Despesas Matérias-Primas | C12: =SUM(D12/E12) -> 0 | D12: =PEC!O133 -> 0 | E12: 12 | G12: ='Q. PROF.'!B133 -> Despesas Matérias-Primas | H12: =SUM(I12/J12) -> 0 | I12: ='Q. PROF.'!O133 -> 0 | J12: 12 | L12: =OUTLET!B133 -> Despesas Matérias-Primas | M12: =SUM(N12/O12) -> 0 | N12: =OUTLET!O133 -> 0 | O12: 12
L13: =OUTLET!B49 -> Compras Mercadorias Revenda | M13: =SUM(N13/O13) -> 800 | N13: =OUTLET!O49 -> 9600 | O13: 12
D15: =SUM(D4:D13) -> 289050 | I15: =SUM(I4:I13) -> 97350 | N15: =SUM(N4:N13) -> 132960
B17: PSICOSSOCIAL | G17: CASA SONHAR | L17: GRIFFTE
B18: DESCRIÇÃO | C18: VALOR | D18: TOTAL | E18: MESES | G18: DESCRIÇÃO | H18: VALOR | I18: TOTAL | J18: MESES | L18: DESCRIÇÃO | M18: VALOR | N18: TOTAL | O18: MESES
B19: =PSICOSSOCIAL!B50 -> Marketing | C19: =SUM(D19/E19) -> 0 | D19: =PSICOSSOCIAL!O50 -> 0 | E19: 11 | G19: ='CASA SONHAR'!B50 -> Marketing | H19: =SUM(I19/J19) -> 72.727273 | I19: ='CASA SONHAR'!O50 -> 800 | J19: 11 | L19: =GRIFFTE!B50 -> Marketing | M19: =SUM(N19/O19) -> 0 | N19: =GRIFFTE!O50 -> 0 | O19: 11
B20: =PSICOSSOCIAL!B53 -> Despesas com Pessoal | C20: =SUM(D20/E20) -> 7291.6667 | D20: =PSICOSSOCIAL!O53 -> 87500 | E20: 12 | G20: ='CASA SONHAR'!B53 -> Despesas com Pessoal | H20: =SUM(I20/J20) -> 19414.667 | I20: ='CASA SONHAR'!O53 -> 232976 | J20: 12 | L20: =GRIFFTE!B53 -> Despesas com Pessoal | M20: =SUM(N20/O20) -> 7800 | N20: =GRIFFTE!O53 -> 93600 | O20: 12
B21: =PSICOSSOCIAL!B75 -> Despesas Administrativas | C21: =SUM(D21/E21) -> 200 | D21: =PSICOSSOCIAL!O75 -> 2400 | E21: 12 | G21: ='CASA SONHAR'!B75 -> Despesas Administrativas | H21: =SUM(I21/J21) -> 7910 | I21: ='CASA SONHAR'!O75 -> 94920 | J21: 12 | L21: =GRIFFTE!B75 -> Despesas Administrativas | M21: =SUM(N21/O21) -> 2525 | N21: =GRIFFTE!O75 -> 30300 | O21: 12
B22: =PSICOSSOCIAL!B99 -> Despesas Financeiras / Bancos | C22: =SUM(D22/E22) -> 0 | D22: =PSICOSSOCIAL!O99 -> 0 | E22: 12 | G22: ='CASA SONHAR'!B99 -> Despesas Financeiras / Bancos | H22: =SUM(I22/J22) -> 0 | I22: ='CASA SONHAR'!O99 -> 0 | J22: 12 | L22: =GRIFFTE!B99 -> Despesas Financeiras / Bancos | M22: =SUM(N22/O22) -> 50 | N22: =GRIFFTE!O99 -> 600 | O22: 12
B23: =PSICOSSOCIAL!B105 -> Impostos e Taxas | C23: =SUM(D23/E23) -> 0 | D23: =PSICOSSOCIAL!O105 -> 0 | E23: 12 | G23: ='CASA SONHAR'!B105 -> Impostos e Taxas | H23: =SUM(I23/J23) -> 0 | I23: ='CASA SONHAR'!O105 -> 0 | J23: 12 | L23: =GRIFFTE!B105 -> Impostos e Taxas | M23: =SUM(N23/O23) -> 0 | N23: =GRIFFTE!O105 -> 0 | O23: 12
B24: =PSICOSSOCIAL!B116 -> Investimento | C24: =SUM(D24/E24) -> 0 | D24: =PSICOSSOCIAL!O116 -> 0 | E24: 12 | G24: ='CASA SONHAR'!B116 -> Investimento | H24: =SUM(I24/J24) -> 1116.6667 | I24: ='CASA SONHAR'!O116 -> 13400 | J24: 12 | L24: =GRIFFTE!B116 -> Investimento | M24: =SUM(N24/O24) -> 0 | N24: =GRIFFTE!O116 -> 0 | O24: 12
B25: =PSICOSSOCIAL!B126 -> Despesas Com Veículos | C25: =SUM(D25/E25) -> 163.63636 | D25: =PSICOSSOCIAL!O126 -> 1800 | E25: 11 | G25: ='CASA SONHAR'!B126 -> Despesas Com Veículos | H25: =SUM(I25/J25) -> 0 | I25: ='CASA SONHAR'!O126 -> 0 | J25: 11 | L25: =GRIFFTE!B126 -> Despesas Com Veículos | M25: =SUM(N25/O25) -> 0 | N25: =GRIFFTE!O126 -> 0 | O25: 11
B26: =PSICOSSOCIAL!B130 -> Despesas Com Eventos | C26: =SUM(D26/E26) -> 109.09091 | D26: =PSICOSSOCIAL!O130 -> 1200 | E26: 11 | G26: ='CASA SONHAR'!B130 -> Despesas Com Eventos | H26: =SUM(I26/J26) -> 1863.6364 | I26: ='CASA SONHAR'!O130 -> 20500 | J26: 11 | L26: =GRIFFTE!B130 -> Despesas Com Eventos | M26: =SUM(N26/O26) -> 0 | N26: =GRIFFTE!O130 -> 0 | O26: 11
B27: =PSICOSSOCIAL!B133 -> Despesas Matérias-Primas | C27: =SUM(D27/E27) -> 0 | D27: =PSICOSSOCIAL!O133 -> 0 | E27: 12 | G27: ='CASA SONHAR'!B133 -> Despesas Matérias-Primas | H27: =SUM(I27/J27) -> 0 | I27: ='CASA SONHAR'!O133 -> 0 | J27: 12 | L27: =GRIFFTE!B133 -> Despesas Matérias-Primas | M27: =SUM(N27/O27) -> 0 | N27: =GRIFFTE!O133 -> 0 | O27: 12
D30: =SUM(D19:D28) -> 92900 | I30: =SUM(I19:I27) -> 362596 | N30: =SUM(N19:N28) -> 124500
B32: MARKETING | G32: ADMINISTRATIVO
B33: DESCRIÇÃO | C33: VALOR | D33: TOTAL | E33: MESES | G33: DESCRIÇÃO | H33: VALOR | I33: TOTAL | J33: MESES
B34: =MARKETING!B50 -> Marketing | C34: =SUM(D34/E34) -> 13000 | D34: =MARKETING!O50 -> 143000 | E34: 11 | G34: =ADM!B50 -> Marketing | H34: =SUM(I34/J34) -> 0 | I34: =ADM!O50 -> 0 | J34: 11
B35: =MARKETING!B53 -> Despesas com Pessoal | C35: =SUM(D35/E35) -> 8808.3333 | D35: =MARKETING!O53 -> 105700 | E35: 12 | G35: =ADM!B53 -> Despesas com Pessoal | H35: =SUM(I35/J35) -> 33050 | I35: =ADM!O53 -> 396600 | J35: 12
B36: =MARKETING!B75 -> Despesas Administrativas | C36: =SUM(D36/E36) -> 3807.1333 | D36: =MARKETING!O75 -> 45685.6 | E36: 12 | G36: =ADM!B75 -> Despesas Administrativas | H36: =SUM(I36/J36) -> 12562.5 | I36: =ADM!O75 -> 150750 | J36: 12
B37: =MARKETING!B99 -> Despesas Financeiras / Bancos | C37: =SUM(D37/E37) -> 0 | D37: =MARKETING!O99 -> 0 | E37: 12 | G37: =ADM!B99 -> Despesas Financeiras / Bancos | H37: =SUM(I37/J37) -> 150 | I37: =ADM!O99 -> 1800 | J37: 12
B38: =MARKETING!B105 -> Impostos e Taxas | C38: =SUM(D38/E38) -> 0 | D38: =MARKETING!O105 -> 0 | E38: 12 | G38: =ADM!B105 -> Impostos e Taxas | H38: =SUM(I38/J38) -> 275 | I38: =ADM!O105 -> 3300 | J38: 12
B39: =MARKETING!B116 -> Investimento | C39: =SUM(D39/E39) -> 1458.3333 | D39: =MARKETING!O116 -> 17500 | E39: 12 | G39: =ADM!B116 -> Investimento | H39: =SUM(I39/J39) -> 750 | I39: =ADM!O116 -> 9000 | J39: 12
B40: =MARKETING!B126 -> Despesas Com Veículos | C40: =SUM(D40/E40) -> 0 | D40: =MARKETING!O126 -> 0 | E40: 11 | G40: =ADM!B125 -> Devolução Entradas | H40: =SUM(I40/J40) -> 1463.6364 | I40: =ADM!O126 -> 16100 | J40: 11
B41: =MARKETING!B130 -> Despesas Com Eventos | C41: =SUM(D41/E41) -> 10063.636 | D41: =MARKETING!O130 -> 110700 | E41: 11 | G41: =ADM!B129 -> Manutenções Veículos | H41: =SUM(I41/J41) -> 0 | I41: =ADM!O130 -> 0 | J41: 11
B42: =MARKETING!B133 -> Despesas Matérias-Primas | C42: =SUM(D42/E42) -> 0 | D42: =MARKETING!O133 -> 0 | E42: 12 | G42: =ADM!B132 -> Crowdfunding/Excurções/eventos | H42: =SUM(I42/J42) -> 0 | I42: =ADM!O133 -> 0 | J42: 12
B43: =MARKETING!B49 -> Compras Mercadorias Revenda | C43: =SUM(D43/E43) -> 2387.5 | D43: =MARKETING!O48 -> 28650 | E43: 12
D45: =SUM(D34:D43) -> 451235.6 | I45: =SUM(I34:I43) -> 577550
B47: RECEITA | G47: CUSTO
B48: =GERAL!B22 -> Doações | C48: =GERAL!O22 -> 76500 | G48: PEC | H48: =D15 -> 289050
B49: =GERAL!B33 -> Editais/Projetos | C49: =GERAL!O33 -> 413000 | G49: Q. PROFISSIONAL | H49: =I15 -> 97350
B50: =GERAL!B37 -> Negócios Sociais | C50: =GERAL!O37 -> 347600 | G50: PSICOSSOCIAL | H50: =D30 -> 92900
B51: =GERAL!B40 -> Eventos | C51: =GERAL!O40 -> 55085 | G51: CASA SONHAR | H51: =I30 -> 362596
B52: =GERAL!B43 -> Aplicações | C52: =GERAL!O43 -> 60000 | G52: OUTLET | H52: =N15 -> 132960
G53: GRIFFTE | H53: =N30 -> 124500
G54: MARKETING | H54: =D45 -> 451235.6
B55: JANTAR O GRITO 2025 | C55: 1500000 | G55: ADMINISTRATIVO | H55: =I45 -> 577550
C58: =SUM(C48:C56) -> 2532585 | H58: =SUM(H48:H56) -> 2128141.6

Sheet GERAL
C1: INSTITUTO DE CAPACITACAO E ACAO SOCIAL O GRITO - PLANEJAMENTO 2025 - GERAL
A2: Emitido por RICARDO em 07/03/2024 | C2: =C47/O$47 -> 0.069748292 | D2: =D47/$O$47 -> 0.10924297 | E2: =E47/$O$47 -> 0.077005152 | F2: =F47/$O$47 -> 0.078055797 | G2: =G47/$O$47 -> 0.072448887 | H2: =H47/$O$47 -> 0.089515807 | I2: =I47/$O$47 -> 0.091464529 | J2: =J47/$O$47 -> 0.078489232 | K2: =K47/$O$47 -> 0.071367035 | ... N2: =N47/$O$47 -> 0.10139456
B3: CATEGORIA | C3: JANEIRO | D3: FEVEREIRO | E3: MARÇO | F3: ABRIL | G3: MAIO | H3: JUNHO | I3: JULHO | J3: AGOSTO | K3: SETEMBRO | L3: OUTUBRO | M3: NOVEMBRO | N3: DEZEMBRO | O3: TOTAL
B5: SALDO ACUMULADO | C5: =C6 -> 63350 | D5: =C5+D6 -> -56700.36 | E5: =D5+E6 -> -172478.72 | F5: =E5+F6 -> -293187.08 | G5: =F5+G6 -> -397825.44 | H5: =G5+H6 -> -394378.8 | I5: =H5+I6 -> -559617.16 | J5: =I5+J6 -> -687435.52 | K5: =J5+K6 -> -893253.88 | ... N5: =M5+N6 -> -1650756.6
B6: SALDO MÊS | C6: =SUM(C8-C47) -> 63350 | D6: =SUM(D8-D47) -> -120050.36 | E6: =SUM(E8-E47) -> -115778.36 | F6: =SUM(F8-F47) -> -120708.36 | G6: =SUM(G8-G47) -> -104638.36 | H6: =SUM(H8-H47) -> 3446.64 | I6: =SUM(I8-I47) -> -165238.36 | J6: =SUM(J8-J47) -> -127818.36 | ... N6: =SUM(N8-N47) -> -292416 | O6: =SUM(C6:N6) -> -1650756.6
B8: RECEITAS | C8: =SUM(C9,C16,C22,C28,C33,C37,C40,C43) -> 264500 | D8: =SUM(D9,D16,D22,D28,D33,D37,D40,D43) -> 195000 | E8: =SUM(E9,E16,E22,E28,E33,E37,E40,E43) -> 106300 | F8: =SUM(F9,F16,F22,F28,F33,F37,F40,F43) -> 104400 | G8: =SUM(G9,G16,G22,G28,G33,G37,G40,G43) -> 104300 | H8: =SUM(H9,H16,H22,H28,H33,H37,H40,H43) -> 261605 | I8: =SUM(I9,I16,I22,I28,I33,I37,I40,I43) -> 98540 | J8: =SUM(J9,J16,J22,J28,J33,J37,J40,J43) -> 98540 | ... N8: =SUM(N9,N16,N22,N28,N33,N37,N40,N43) -> 98540 | O8: =SUM(C8:N8) -> 1233185
B9: Devoluções | C9: =SUM(C10:C15) -> 0 | D9: =SUM(D10:D15) -> 0 | E9: =SUM(E10:E15) -> 0 | F9: =SUM(F10:F15) -> 0 | G9: =SUM(G10:G15) -> 0 | H9: =SUM(H10:H15) -> 0 | I9: =SUM(I10:I15) -> 0 | J9: =SUM(J10:J15) -> 0 | ... N9: =SUM(N10:N15) -> 0 | O9: =SUM(C9:N9) -> 0
B10: Devoluções Compra Mercadoria Revenda | C10: 0 | D10: 0 | E10: 0 | F10: 0 | G10: 0 | H10: 0 | I10: 0 | J10: 0 | K10: 0 | L10: 0 | M10: 0 | N10: 0 | O10: =SUM(C10:N10) -> 0
B11: Devoluções de Compra Material Consumo | C11: 0 | D11: 0 | E11: 0 | F11: 0 | G11: 0 | H11: 0 | I11: 0 | J11: 0 | K11: 0 | L11: 0 | M11: 0 | N11: 0 | O11: =SUM(C11:N11) -> 0
B12: Devoluções de Compra de Matéria Prima | C12: 0 | D12: 0 | E12: 0 | F12: 0 | G12: 0 | H12: 0 | I12: 0 | J12: 0 | K12: 0 | L12: 0 | M12: 0 | N12: 0 | O12: =SUM(C12:N12) -> 0
B13: Devoluções de Compra de Ativo | C13: 0 | D13: 0 | E13: 0 | F13: 0 | G13: 0 | H13: 0 | I13: 0 | J13: 0 | K13: 0 | L13: 0 | M13: 0 | N13: 0 | O13: =SUM(C13:N13) -> 0
B14: Devoluções de Compra de Serviços | C14: 0 | D14: 0 | E14: 0 | F14: 0 | G14: 0 | H14: 0 | I14: 0 | J14: 0 | K14: 0 | L14: 0 | M14: 0 | N14: 0 | O14: =SUM(C14:N14) -> 0
B15: Devolução de Doações | C15: 0 | D15: 0 | E15: 0 | F15: 0 | G15: 0 | H15: 0 | I15: 0 | J15: 0 | K15: 0 | L15: 0 | M15: 0 | N15: 0 | O15: =SUM(C15:N15) -> 0
B16: Outras Entradas | C16: =SUM(C17:C21) -> 0 | D16: =SUM(D17:D21) -> 0 | E16: =SUM(E17:E21) -> 0 | F16: =SUM(F17:F21) -> 0 | G16: =SUM(G17:G21) -> 0 | H16: =SUM(H17:H21) -> 0 | I16: =SUM(I17:I21) -> 0 | J16: =SUM(J17:J21) -> 0 | ... N16: =SUM(N17:N21) -> 0 | O16: =SUM(C16:N16) -> 0
B17: Empréstimos Bancários | C17: 0 | D17: 0 | E17: 0 | F17: 0 | G17: 0 | H17: 0 | I17: 0 | J17: 0 | K17: 0 | L17: 0 | M17: 0 | N17: 0 | O17: =SUM(C17:N17) -> 0
B18: Aumento de Capital | C18: 0 | D18: 0 | E18: 0 | F18: 0 | G18: 0 | H18: 0 | I18: 0 | J18: 0 | K18: 0 | L18: 0 | M18: 0 | N18: 0 | O18: =SUM(C18:N18) -> 0
B19: Venda de Ativos | C19: 0 | D19: 0 | E19: 0 | F19: 0 | G19: 0 | H19: 0 | I19: 0 | J19: 0 | K19: 0 | L19: 0 | M19: 0 | N19: 0 | O19: =SUM(C19:N19) -> 0
B20: AJUSTE DE CAIXA | C20: 0 | D20: 0 | E20: 0 | F20: 0 | G20: 0 | H20: 0 | I20: 0 | J20: 0 | K20: 0 | L20: 0 | M20: 0 | N20: 0 | O20: =SUM(C20:N20) -> 0
B21: Prêmios de Seguros / Sinistros | C21: 0 | D21: 0 | E21: 0 | F21: 0 | G21: 0 | H21: 0 | I21: 0 | J21: 0 | K21: 0 | L21: 0 | M21: 0 | N21: 0 | O21: =SUM(C21:N21) -> 0
B22: Doações | C22: =SUM(C23:C27) -> 5500 | D22: =SUM(D23:D27) -> 7000 | E22: =SUM(E23:E27) -> 5500 | F22: =SUM(F23:F27) -> 5500 | G22: =SUM(G23:G27) -> 5500 | H22: =SUM(H23:H27) -> 14500 | I22: =SUM(I23:I27) -> 5500 | J22: =SUM(J23:J27) -> 5500 | ... N22: =SUM(N23:N27) -> 5500 | O22: =SUM(C22:N22) -> 76500
B23: Doações Recorrentes | C23: =SUM(ADM!C23,MARKETING!C23,COMERCIAL!C23,OPERAÇÕES!C23,'FAVELA 3D'!C23) -> 2500 | D23: =SUM(ADM!D23,MARKETING!D23,COMERCIAL!D23,OPERAÇÕES!D23,'FAVELA 3D'!D23) -> 2500 | E23: =SUM(ADM!E23,MARKETING!E23,COMERCIAL!E23,OPERAÇÕES!E23,'FAVELA 3D'!E23) -> 2500 | F23: =SUM(ADM!F23,MARKETING!F23,COMERCIAL!F23,OPERAÇÕES!F23,'FAVELA 3D'!F23) -> 2500 | G23: =SUM(ADM!G23,MARKETING!G23,COMERCIAL!G23,OPERAÇÕES!G23,'FAVELA 3D'!G23) -> 2500 | H23: =SUM(ADM!H23,MARKETING!H23,COMERCIAL!H23,OPERAÇÕES!H23,'FAVELA 3D'!H23) -> 2500 | I23: =SUM(ADM!I23,MARKETING!I23,COMERCIAL!I23,OPERAÇÕES!I23,'FAVELA 3D'!I23) -> 2500 | J23: =SUM(ADM!J23,MARKETING!J23,COMERCIAL!J23,OPERAÇÕES!J23,'FAVELA 3D'!J23) -> 2500 | ... N23: =SUM(ADM!N23,MARKETING!N23,COMERCIAL!N23,OPERAÇÕES!N23,'FAVELA 3D'!N23) -> 2500 | O23: =SUM(C23:N23) -> 30000
B24: Doações Pontuais PF | C24: =SUM(ADM!C24,MARKETING!C24,COMERCIAL!C24,OPERAÇÕES!C24,'FAVELA 3D'!C24) -> 0 | D24: =SUM(ADM!D24,MARKETING!D24,COMERCIAL!D24,OPERAÇÕES!D24,'FAVELA 3D'!D24) -> 1500 | E24: =SUM(ADM!E24,MARKETING!E24,COMERCIAL!E24,OPERAÇÕES!E24,'FAVELA 3D'!E24) -> 0 | F24: =SUM(ADM!F24,MARKETING!F24,COMERCIAL!F24,OPERAÇÕES!F24,'FAVELA 3D'!F24) -> 0 | G24: =SUM(ADM!G24,MARKETING!G24,COMERCIAL!G24,OPERAÇÕES!G24,'FAVELA 3D'!G24) -> 0 | H24: =SUM(ADM!H24,MARKETING!H24,COMERCIAL!H24,OPERAÇÕES!H24,'FAVELA 3D'!H24) -> 9000 | I24: =SUM(ADM!I24,MARKETING!I24,COMERCIAL!I24,OPERAÇÕES!I24,'FAVELA 3D'!I24) -> 0 | J24: =SUM(ADM!J24,MARKETING!J24,COMERCIAL!J24,OPERAÇÕES!J24,'FAVELA 3D'!J24) -> 0 | ... N24: =SUM(ADM!N24,MARKETING!N24,COMERCIAL!N24,OPERAÇÕES!N24,'FAVELA 3D'!N24) -> 0 | O24: =SUM(C24:N24) -> 10500
B25: Doações Pontuais PJ | C25: =SUM(ADM!C25,MARKETING!C25,COMERCIAL!C25,OPERAÇÕES!C25,'FAVELA 3D'!C25) -> 0 | D25: =SUM(ADM!D25,MARKETING!D25,COMERCIAL!D25,OPERAÇÕES!D25,'FAVELA 3D'!D25) -> 0 | E25: =SUM(ADM!E25,MARKETING!E25,COMERCIAL!E25,OPERAÇÕES!E25,'FAVELA 3D'!E25) -> 0 | F25: =SUM(ADM!F25,MARKETING!F25,COMERCIAL!F25,OPERAÇÕES!F25,'FAVELA 3D'!F25) -> 0 | G25: =SUM(ADM!G25,MARKETING!G25,COMERCIAL!G25,OPERAÇÕES!G25,'FAVELA 3D'!G25) -> 0 | H25: =SUM(ADM!H25,MARKETING!H25,COMERCIAL!H25,OPERAÇÕES!H25,'FAVELA 3D'!H25) -> 0 | I25: =SUM(ADM!I25,MARKETING!I25,COMERCIAL!I25,OPERAÇÕES!I25,'FAVELA 3D'!I25) -> 0 | J25: =SUM(ADM!J25,MARKETING!J25,COMERCIAL!J25,OPERAÇÕES!J25,'FAVELA 3D'!J25) -> 0 | ... N25: =SUM(ADM!N25,MARKETING!N25,COMERCIAL!N25,OPERAÇÕES!N25,'FAVELA 3D'!N25) -> 0 | O25: =SUM(C25:N25) -> 0
B26: Sócio Doador | C26: =SUM(ADM!C26,MARKETING!C26,COMERCIAL!C26,OPERAÇÕES!C26,'FAVELA 3D'!C26) -> 3000 | D26: =SUM(ADM!D26,MARKETING!D26,COMERCIAL!D26,OPERAÇÕES!D26,'FAVELA 3D'!D26) -> 3000 | E26: =SUM(ADM!E26,MARKETING!E26,COMERCIAL!E26,OPERAÇÕES!E26,'FAVELA 3D'!E26) -> 3000 | F26: =SUM(ADM!F26,MARKETING!F26,COMERCIAL!F26,OPERAÇÕES!F26,'FAVELA 3D'!F26) -> 3000 | G26: =SUM(ADM!G26,MARKETING!G26,COMERCIAL!G26,OPERAÇÕES!G26,'FAVELA 3D'!G26) -> 3000 | H26: =SUM(ADM!H26,MARKETING!H26,COMERCIAL!H26,OPERAÇÕES!H26,'FAVELA 3D'!H26) -> 3000 | I26: =SUM(ADM!I26,MARKETING!I26,COMERCIAL!I26,OPERAÇÕES!I26,'FAVELA 3D'!I26) -> 3000 | J26: =SUM(ADM!J26,MARKETING!J26,COMERCIAL!J26,OPERAÇÕES!J26,'FAVELA 3D'!J26) -> 3000 | ... N26: =SUM(ADM!N26,MARKETING!N26,COMERCIAL!N26,OPERAÇÕES!N26,'FAVELA 3D'!N26) -> 3000 | O26: =SUM(C26:N26) -> 36000
B27: Patrocínios | C27: =SUM(ADM!C27,MARKETING!C27,COMERCIAL!C27,OPERAÇÕES!C27,'FAVELA 3D'!C27) -> 0 | D27: =SUM(ADM!D27,MARKETING!D27,COMERCIAL!D27,OPERAÇÕES!D27,'FAVELA 3D'!D27) -> 0 | E27: =SUM(ADM!E27,MARKETING!E27,COMERCIAL!E27,OPERAÇÕES!E27,'FAVELA 3D'!E27) -> 0 | F27: =SUM(ADM!F27,MARKETING!F27,COMERCIAL!F27,OPERAÇÕES!F27,'FAVELA 3D'!F27) -> 0 | G27: =SUM(ADM!G27,MARKETING!G27,COMERCIAL!G27,OPERAÇÕES!G27,'FAVELA 3D'!G27) -> 0 | H27: =SUM(ADM!H27,MARKETING!H27,COMERCIAL!H27,OPERAÇÕES!H27,'FAVELA 3D'!H27) -> 0 | I27: =SUM(ADM!I27,MARKETING!I27,COMERCIAL!I27,OPERAÇÕES!I27,'FAVELA 3D'!I27) -> 0 | J27: =SUM(ADM!J27,MARKETING!J27,COMERCIAL!J27,OPERAÇÕES!J27,'FAVELA 3D'!J27) -> 0 | ... N27: =SUM(ADM!N27,MARKETING!N27,COMERCIAL!N27,OPERAÇÕES!N27,'FAVELA 3D'!N27) -> 0 | O27: =SUM(C27:N27) -> 0
B28: Gerando Falcões | C28: =SUM(C29:C32) -> 53500 | D28: =SUM(D29:D32) -> 53500 | E28: =SUM(E29:E32) -> 53500 | F28: =SUM(F29:F32) -> 53500 | G28: =SUM(G29:G32) -> 53500 | H28: =SUM(H29:H32) -> 53500 | I28: =SUM(I29:I32) -> 53500 | J28: =SUM(J29:J32) -> 53500 | ... N28: =SUM(N29:N32) -> 53500 | O28: =SUM(C28:N28) -> 642000
B29: Aporte | C29: =SUM(ADM!C29,MARKETING!C29,COMERCIAL!C29,OPERAÇÕES!C29,'FAVELA 3D'!C29) -> 53500 | D29: =SUM(ADM!D29,MARKETING!D29,COMERCIAL!D29,OPERAÇÕES!D29,'FAVELA 3D'!D29) -> 53500 | E29: =SUM(ADM!E29,MARKETING!E29,COMERCIAL!E29,OPERAÇÕES!E29,'FAVELA 3D'!E29) -> 53500 | F29: =SUM(ADM!F29,MARKETING!F29,COMERCIAL!F29,OPERAÇÕES!F29,'FAVELA 3D'!F29) -> 53500 | G29: =SUM(ADM!G29,MARKETING!G29,COMERCIAL!G29,OPERAÇÕES!G29,'FAVELA 3D'!G29) -> 53500 | H29: =SUM(ADM!H29,MARKETING!H29,COMERCIAL!H29,OPERAÇÕES!H29,'FAVELA 3D'!H29) -> 53500 | I29: =SUM(ADM!I29,MARKETING!I29,COMERCIAL!I29,OPERAÇÕES!I29,'FAVELA 3D'!I29) -> 53500 | J29: =SUM(ADM!J29,MARKETING!J29,COMERCIAL!J29,OPERAÇÕES!J29,'FAVELA 3D'!J29) -> 53500 | ... N29: =SUM(ADM!N29,MARKETING!N29,COMERCIAL!N29,OPERAÇÕES!N29,'FAVELA 3D'!N29) -> 53500 | O29: =SUM(C29:N29) -> 642000
B30: Falcons Univercity | C30: =SUM(ADM!C30,MARKETING!C30,COMERCIAL!C30,OPERAÇÕES!C30,'FAVELA 3D'!C30) -> 0 | D30: =SUM(ADM!D30,MARKETING!D30,COMERCIAL!D30,OPERAÇÕES!D30,'FAVELA 3D'!D30) -> 0 | E30: =SUM(ADM!E30,MARKETING!E30,COMERCIAL!E30,OPERAÇÕES!E30,'FAVELA 3D'!E30) -> 0 | F30: =SUM(ADM!F30,MARKETING!F30,COMERCIAL!F30,OPERAÇÕES!F30,'FAVELA 3D'!F30) -> 0 | G30: =SUM(ADM!G30,MARKETING!G30,COMERCIAL!G30,OPERAÇÕES!G30,'FAVELA 3D'!G30) -> 0 | H30: =SUM(ADM!H30,MARKETING!H30,COMERCIAL!H30,OPERAÇÕES!H30,'FAVELA 3D'!H30) -> 0 | I30: =SUM(ADM!I30,MARKETING!I30,COMERCIAL!I30,OPERAÇÕES!I30,'FAVELA 3D'!I30) -> 0 | J30: =SUM(ADM!J30,MARKETING!J30,COMERCIAL!J30,OPERAÇÕES!J30,'FAVELA 3D'!J30) -> 0 | ... N30: =SUM(ADM!N30,MARKETING!N30,COMERCIAL!N30,OPERAÇÕES!N30,'FAVELA 3D'!N30) -> 0 | O30: =SUM(C30:N30) -> 0
B31: Regional GF | C31: =SUM(ADM!C31,MARKETING!C31,COMERCIAL!C31,OPERAÇÕES!C31,'FAVELA 3D'!C31) -> 0 | D31: =SUM(ADM!D31,MARKETING!D31,COMERCIAL!D31,OPERAÇÕES!D31,'FAVELA 3D'!D31) -> 0 | E31: =SUM(ADM!E31,MARKETING!E31,COMERCIAL!E31,OPERAÇÕES!E31,'FAVELA 3D'!E31) -> 0 | F31: =SUM(ADM!F31,MARKETING!F31,COMERCIAL!F31,OPERAÇÕES!F31,'FAVELA 3D'!F31) -> 0 | G31: =SUM(ADM!G31,MARKETING!G31,COMERCIAL!G31,OPERAÇÕES!G31,'FAVELA 3D'!G31) -> 0 | H31: =SUM(ADM!H31,MARKETING!H31,COMERCIAL!H31,OPERAÇÕES!H31,'FAVELA 3D'!H31) -> 0 | I31: =SUM(ADM!I31,MARKETING!I31,COMERCIAL!I31,OPERAÇÕES!I31,'FAVELA 3D'!I31) -> 0 | J31: =SUM(ADM!J31,MARKETING!J31,COMERCIAL!J31,OPERAÇÕES!J31,'FAVELA 3D'!J31) -> 0 | ... N31: =SUM(ADM!N31,MARKETING!N31,COMERCIAL!N31,OPERAÇÕES!N31,'FAVELA 3D'!N31) -> 0 | O31: =SUM(C31:N31) -> 0
B32: Favela 3D | C32: =SUM(ADM!C32,MARKETING!C32,COMERCIAL!C32,OPERAÇÕES!C32,'FAVELA 3D'!C32) -> 0 | D32: =SUM(ADM!D32,MARKETING!D32,COMERCIAL!D32,OPERAÇÕES!D32,'FAVELA 3D'!D32) -> 0 | E32: =SUM(ADM!E32,MARKETING!E32,COMERCIAL!E32,OPERAÇÕES!E32,'FAVELA 3D'!E32) -> 0 | F32: =SUM(ADM!F32,MARKETING!F32,COMERCIAL!F32,OPERAÇÕES!F32,'FAVELA 3D'!F32) -> 0 | G32: =SUM(ADM!G32,MARKETING!G32,COMERCIAL!G32,OPERAÇÕES!G32,'FAVELA 3D'!G32) -> 0 | H32: =SUM(ADM!H32,MARKETING!H32,COMERCIAL!H32,OPERAÇÕES!H32,'FAVELA 3D'!H32) -> 0 | I32: =SUM(ADM!I32,MARKETING!I32,COMERCIAL!I32,OPERAÇÕES!I32,'FAVELA 3D'!I32) -> 0 | J32: =SUM(ADM!J32,MARKETING!J32,COMERCIAL!J32,OPERAÇÕES!J32,'FAVELA 3D'!J32) -> 0 | ... N32: =SUM(ADM!N32,MARKETING!N32,COMERCIAL!N32,OPERAÇÕES!N32,'FAVELA 3D'!N32) -> 0 | O32: =SUM(C32:N32) -> 0
B33: Editais/Projetos | C33: =SUM(C34:C36) -> 174000 | D33: =SUM(D34:D36) -> 90000 | E33: =SUM(E34:E36) -> 0 | F33: =SUM(F34:F36) -> 0 | G33: =SUM(G34:G36) -> 0 | H33: =SUM(H34:H36) -> 149000 | I33: =SUM(I34:I36) -> 0 | J33: =SUM(J34:J36) -> 0 | ... N33: =SUM(N34:N36) -> 0 | O33: =SUM(C33:N33) -> 413000
B34: Ecogaiola | C34: =SUM(ADM!C34,MARKETING!C34,COMERCIAL!C34,OPERAÇÕES!C34,'FAVELA 3D'!C34) -> 0 | D34: =SUM(ADM!D34,MARKETING!D34,COMERCIAL!D34,OPERAÇÕES!D34,'FAVELA 3D'!D34) -> 0 | E34: =SUM(ADM!E34,MARKETING!E34,COMERCIAL!E34,OPERAÇÕES!E34,'FAVELA 3D'!E34) -> 0 | F34: =SUM(ADM!F34,MARKETING!F34,COMERCIAL!F34,OPERAÇÕES!F34,'FAVELA 3D'!F34) -> 0 | G34: =SUM(ADM!G34,MARKETING!G34,COMERCIAL!G34,OPERAÇÕES!G34,'FAVELA 3D'!G34) -> 0 | H34: =SUM(ADM!H34,MARKETING!H34,COMERCIAL!H34,OPERAÇÕES!H34,'FAVELA 3D'!H34) -> 0 | I34: =SUM(ADM!I34,MARKETING!I34,COMERCIAL!I34,OPERAÇÕES!I34,'FAVELA 3D'!I34) -> 0 | J34: =SUM(ADM!J34,MARKETING!J34,COMERCIAL!J34,OPERAÇÕES!J34,'FAVELA 3D'!J34) -> 0 | ... N34: =SUM(ADM!N34,MARKETING!N34,COMERCIAL!N34,OPERAÇÕES!N34,'FAVELA 3D'!N34) -> 0 | O34: =SUM(C34:N34) -> 0
B35: Prog. Hab. Polaris | C35: =SUM(ADM!C35,MARKETING!C35,COMERCIAL!C35,OPERAÇÕES!C35,'FAVELA 3D'!C35) -> 0 | D35: =SUM(ADM!D35,MARKETING!D35,COMERCIAL!D35,OPERAÇÕES!D35,'FAVELA 3D'!D35) -> 0 | E35: =SUM(ADM!E35,MARKETING!E35,COMERCIAL!E35,OPERAÇÕES!E35,'FAVELA 3D'!E35) -> 0 | F35: =SUM(ADM!F35,MARKETING!F35,COMERCIAL!F35,OPERAÇÕES!F35,'FAVELA 3D'!F35) -> 0 | G35: =SUM(ADM!G35,MARKETING!G35,COMERCIAL!G35,OPERAÇÕES!G35,'FAVELA 3D'!G35) -> 0 | H35: =SUM(ADM!H35,MARKETING!H35,COMERCIAL!H35,OPERAÇÕES!H35,'FAVELA 3D'!H35) -> 0 | I35: =SUM(ADM!I35,MARKETING!I35,COMERCIAL!I35,OPERAÇÕES!I35,'FAVELA 3D'!I35) -> 0 | J35: =SUM(ADM!J35,MARKETING!J35,COMERCIAL!J35,OPERAÇÕES!J35,'FAVELA 3D'!J35) -> 0 | ... N35: =SUM(ADM!N35,MARKETING!N35,COMERCIAL!N35,OPERAÇÕES!N35,'FAVELA 3D'!N35) -> 0 | O35: =SUM(C35:N35) -> 0
B36: Lei De Incentivo | C36: =SUM(ADM!C36,MARKETING!C36,COMERCIAL!C36,OPERAÇÕES!C36,'FAVELA 3D'!C36) -> 174000 | D36: =SUM(ADM!D36,MARKETING!D36,COMERCIAL!D36,OPERAÇÕES!D36,'FAVELA 3D'!D36) -> 90000 | E36: =SUM(ADM!E36,MARKETING!E36,COMERCIAL!E36,OPERAÇÕES!E36,'FAVELA 3D'!E36) -> 0 | F36: =SUM(ADM!F36,MARKETING!F36,COMERCIAL!F36,OPERAÇÕES!F36,'FAVELA 3D'!F36) -> 0 | G36: =SUM(ADM!G36,MARKETING!G36,COMERCIAL!G36,OPERAÇÕES!G36,'FAVELA 3D'!G36) -> 0 | H36: =SUM(ADM!H36,MARKETING!H36,COMERCIAL!H36,OPERAÇÕES!H36,'FAVELA 3D'!H36) -> 149000 | I36: =SUM(ADM!I36,MARKETING!I36,COMERCIAL!I36,OPERAÇÕES!I36,'FAVELA 3D'!I36) -> 0 | J36: =SUM(ADM!J36,MARKETING!J36,COMERCIAL!J36,OPERAÇÕES!J36,'FAVELA 3D'!J36) -> 0 | ... N36: =SUM(ADM!N36,MARKETING!N36,COMERCIAL!N36,OPERAÇÕES!N36,'FAVELA 3D'!N36) -> 0 | O36: =SUM(C36:N36) -> 413000
B37: Negócios Sociais | C37: =SUM(C38:C39) -> 16500 | D37: =SUM(D38:D39) -> 29500 | E37: =SUM(E38:E39) -> 34400 | F37: =SUM(F38:F39) -> 34400 | G37: =SUM(G38:G39) -> 34400 | H37: =SUM(H38:H39) -> 34400 | I37: =SUM(I38:I39) -> 29500 | J37: =SUM(J38:J39) -> 29500 | ... N37: =SUM(N38:N39) -> 16500 | O37: =SUM(C37:N37) -> 347600
B38: Vendas Outlet | C38: =SUM(ADM!C38,MARKETING!C38,COMERCIAL!C38,OPERAÇÕES!C38,'FAVELA 3D'!C38) -> 16500 | D38: =SUM(ADM!D38,MARKETING!D38,COMERCIAL!D38,OPERAÇÕES!D38,'FAVELA 3D'!D38) -> 16500 | E38: =SUM(ADM!E38,MARKETING!E38,COMERCIAL!E38,OPERAÇÕES!E38,'FAVELA 3D'!E38) -> 21400 | F38: =SUM(ADM!F38,MARKETING!F38,COMERCIAL!F38,OPERAÇÕES!F38,'FAVELA 3D'!F38) -> 21400 | G38: =SUM(ADM!G38,MARKETING!G38,COMERCIAL!G38,OPERAÇÕES!G38,'FAVELA 3D'!G38) -> 21400 | H38: =SUM(ADM!H38,MARKETING!H38,COMERCIAL!H38,OPERAÇÕES!H38,'FAVELA 3D'!H38) -> 21400 | I38: =SUM(ADM!I38,MARKETING!I38,COMERCIAL!I38,OPERAÇÕES!I38,'FAVELA 3D'!I38) -> 16500 | J38: =SUM(ADM!J38,MARKETING!J38,COMERCIAL!J38,OPERAÇÕES!J38,'FAVELA 3D'!J38) -> 16500 | ... N38: =SUM(ADM!N38,MARKETING!N38,COMERCIAL!N38,OPERAÇÕES!N38,'FAVELA 3D'!N38) -> 16500 | O38: =SUM(C38:N38) -> 217600
B39: Vendas Griffte | C39: =SUM(ADM!C39,MARKETING!C39,COMERCIAL!C39,OPERAÇÕES!C39,'FAVELA 3D'!C39) -> 0 | D39: =SUM(ADM!D39,MARKETING!D39,COMERCIAL!D39,OPERAÇÕES!D39,'FAVELA 3D'!D39) -> 13000 | E39: =SUM(ADM!E39,MARKETING!E39,COMERCIAL!E39,OPERAÇÕES!E39,'FAVELA 3D'!E39) -> 13000 | F39: =SUM(ADM!F39,MARKETING!F39,COMERCIAL!F39,OPERAÇÕES!F39,'FAVELA 3D'!F39) -> 13000 | G39: =SUM(ADM!G39,MARKETING!G39,COMERCIAL!G39,OPERAÇÕES!G39,'FAVELA 3D'!G39) -> 13000 | H39: =SUM(ADM!H39,MARKETING!H39,COMERCIAL!H39,OPERAÇÕES!H39,'FAVELA 3D'!H39) -> 13000 | I39: =SUM(ADM!I39,MARKETING!I39,COMERCIAL!I39,OPERAÇÕES!I39,'FAVELA 3D'!I39) -> 13000 | J39: =SUM(ADM!J39,MARKETING!J39,COMERCIAL!J39,OPERAÇÕES!J39,'FAVELA 3D'!J39) -> 13000 | ... N39: =SUM(ADM!N39,MARKETING!N39,COMERCIAL!N39,OPERAÇÕES!N39,'FAVELA 3D'!N39) -> 0 | O39: =SUM(C39:N39) -> 130000
B40: Eventos | C40: =SUM(C41:C42) -> 10000 | D40: =SUM(D41:D42) -> 10000 | E40: =SUM(E41:E42) -> 7900 | F40: =SUM(F41:F42) -> 6000 | G40: =SUM(G41:G42) -> 5900 | H40: =SUM(H41:H42) -> 5205 | I40: =SUM(I41:I42) -> 5040 | J40: =SUM(J41:J42) -> 5040 | ... N40: =SUM(N41:N42) -> 0 | O40: =SUM(C40:N40) -> 55085
B41: Clube Do Grito | C41: =SUM(ADM!C41,MARKETING!C41,COMERCIAL!C41,OPERAÇÕES!C41,'FAVELA 3D'!C41) -> 10000 | D41: =SUM(ADM!D41,MARKETING!D41,COMERCIAL!D41,OPERAÇÕES!D41,'FAVELA 3D'!D41) -> 10000 | E41: =SUM(ADM!E41,MARKETING!E41,COMERCIAL!E41,OPERAÇÕES!E41,'FAVELA 3D'!E41) -> 7900 | F41: =SUM(ADM!F41,MARKETING!F41,COMERCIAL!F41,OPERAÇÕES!F41,'FAVELA 3D'!F41) -> 6000 | G41: =SUM(ADM!G41,MARKETING!G41,COMERCIAL!G41,OPERAÇÕES!G41,'FAVELA 3D'!G41) -> 5900 | H41: =SUM(ADM!H41,MARKETING!H41,COMERCIAL!H41,OPERAÇÕES!H41,'FAVELA 3D'!H41) -> 5205 | I41: =SUM(ADM!I41,MARKETING!I41,COMERCIAL!I41,OPERAÇÕES!I41,'FAVELA 3D'!I41) -> 5040 | J41: =SUM(ADM!J41,MARKETING!J41,COMERCIAL!J41,OPERAÇÕES!J41,'FAVELA 3D'!J41) -> 5040 | ... N41: =SUM(ADM!N41,MARKETING!N41,COMERCIAL!N41,OPERAÇÕES!N41,'FAVELA 3D'!N41) -> 10000 | O41: =SUM(C41:N41) -> 55085
B42: Crowdfunding | C42: =SUM(ADM!C42,MARKETING!C42,COMERCIAL!C42,OPERAÇÕES!C42,'FAVELA 3D'!C42) -> 0 | D42: =SUM(ADM!D42,MARKETING!D42,COMERCIAL!D42,OPERAÇÕES!D42,'FAVELA 3D'!D42) -> 0 | E42: =SUM(ADM!E42,MARKETING!E42,COMERCIAL!E42,OPERAÇÕES!E42,'FAVELA 3D'!E42) -> 0 | F42: =SUM(ADM!F42,MARKETING!F42,COMERCIAL!F42,OPERAÇÕES!F42,'FAVELA 3D'!F42) -> 0 | G42: =SUM(ADM!G42,MARKETING!G42,COMERCIAL!G42,OPERAÇÕES!G42,'FAVELA 3D'!G42) -> 0 | H42: =SUM(ADM!H42,MARKETING!H42,COMERCIAL!H42,OPERAÇÕES!H42,'FAVELA 3D'!H42) -> 0 | I42: =SUM(ADM!I42,MARKETING!I42,COMERCIAL!I42,OPERAÇÕES!I42,'FAVELA 3D'!I42) -> 0 | J42: =SUM(ADM!J42,MARKETING!J42,COMERCIAL!J42,OPERAÇÕES!J42,'FAVELA 3D'!J42) -> 0 | ... N42: =SUM(ADM!N42,MARKETING!N42,COMERCIAL!N42,OPERAÇÕES!N42,'FAVELA 3D'!N42) -> 0 | O42: =SUM(C42:N42) -> 0
B43: Aplicações | C43: =SUM(C44:C46) -> 5000 | D43: =SUM(D44:D46) -> 5000 | E43: =SUM(E44:E46) -> 5000 | F43: =SUM(F44:F46) -> 5000 | G43: =SUM(G44:G46) -> 5000 | H43: =SUM(H44:H46) -> 5000 | I43: =SUM(I44:I46) -> 5000 | J43: =SUM(J44:J46) -> 5000 | ... N43: =SUM(N44:N46) -> 5000 | O43: =SUM(C43:N43) -> 60000
B44: Resgate Aplicações (Clube do Grito 2024) | C44: =SUM(ADM!C44,MARKETING!C44,COMERCIAL!C44,OPERAÇÕES!C44,'FAVELA 3D'!C44) -> 0 | D44: =SUM(ADM!D44,MARKETING!D44,COMERCIAL!D44,OPERAÇÕES!D44,'FAVELA 3D'!D44) -> 0 | E44: =SUM(ADM!E44,MARKETING!E44,COMERCIAL!E44,OPERAÇÕES!E44,'FAVELA 3D'!E44) -> 0 | F44: =SUM(ADM!F44,MARKETING!F44,COMERCIAL!F44,OPERAÇÕES!F44,'FAVELA 3D'!F44) -> 0 | G44: =SUM(ADM!G44,MARKETING!G44,COMERCIAL!G44,OPERAÇÕES!G44,'FAVELA 3D'!G44) -> 0 | H44: =SUM(ADM!H44,MARKETING!H44,COMERCIAL!H44,OPERAÇÕES!H44,'FAVELA 3D'!H44) -> 0 | I44: =SUM(ADM!I44,MARKETING!I44,COMERCIAL!I44,OPERAÇÕES!I44,'FAVELA 3D'!I44) -> 0 | J44: =SUM(ADM!J44,MARKETING!J44,COMERCIAL!J44,OPERAÇÕES!J44,'FAVELA 3D'!J44) -> 0 | ... N44: =SUM(ADM!N44,MARKETING!N44,COMERCIAL!N44,OPERAÇÕES!N44,'FAVELA 3D'!N44) -> 0 | O44: =SUM(C44:N44) -> 0
B45: Rendimentos Aplicações | C45: =SUM(ADM!C45,MARKETING!C45,COMERCIAL!C45,OPERAÇÕES!C45,'FAVELA 3D'!C45) -> 5000 | D45: =SUM(ADM!D45,MARKETING!D45,COMERCIAL!D45,OPERAÇÕES!D45,'FAVELA 3D'!D45) -> 5000 | E45: =SUM(ADM!E45,MARKETING!E45,COMERCIAL!E45,OPERAÇÕES!E45,'FAVELA 3D'!E45) -> 5000 | F45: =SUM(ADM!F45,MARKETING!F45,COMERCIAL!F45,OPERAÇÕES!F45,'FAVELA 3D'!F45) -> 5000 | G45: =SUM(ADM!G45,MARKETING!G45,COMERCIAL!G45,OPERAÇÕES!G45,'FAVELA 3D'!G45) -> 5000 | H45: =SUM(ADM!H45,MARKETING!H45,COMERCIAL!H45,OPERAÇÕES!H45,'FAVELA 3D'!H45) -> 5000 | I45: =SUM(ADM!I45,MARKETING!I45,COMERCIAL!I45,OPERAÇÕES!I45,'FAVELA 3D'!I45) -> 5000 | J45: =SUM(ADM!J45,MARKETING!J45,COMERCIAL!J45,OPERAÇÕES!J45,'FAVELA 3D'!J45) -> 5000 | ... N45: =SUM(ADM!N45,MARKETING!N45,COMERCIAL!N45,OPERAÇÕES!N45,'FAVELA 3D'!N45) -> 5000 | O45: =SUM(C45:N45) -> 60000
C46: =SUM(ADM!C46,MARKETING!C46,COMERCIAL!C46,OPERAÇÕES!C46,'FAVELA 3D'!C46) -> 0 | D46: =SUM(ADM!D46,MARKETING!D46,COMERCIAL!D46,OPERAÇÕES!D46,'FAVELA 3D'!D46) -> 0 | E46: =SUM(ADM!E46,MARKETING!E46,COMERCIAL!E46,OPERAÇÕES!E46,'FAVELA 3D'!E46) -> 0 | F46: =SUM(ADM!F46,MARKETING!F46,COMERCIAL!F46,OPERAÇÕES!F46,'FAVELA 3D'!F46) -> 0 | G46: =SUM(ADM!G46,MARKETING!G46,COMERCIAL!G46,OPERAÇÕES!G46,'FAVELA 3D'!G46) -> 0 | H46: =SUM(ADM!H46,MARKETING!H46,COMERCIAL!H46,OPERAÇÕES!H46,'FAVELA 3D'!H46) -> 0 | I46: =SUM(ADM!I46,MARKETING!I46,COMERCIAL!I46,OPERAÇÕES!I46,'FAVELA 3D'!I46) -> 0 | J46: =SUM(ADM!J46,MARKETING!J46,COMERCIAL!J46,OPERAÇÕES!J46,'FAVELA 3D'!J46) -> 0 | ... N46: =SUM(ADM!N46,MARKETING!N46,COMERCIAL!N46,OPERAÇÕES!N46,'FAVELA 3D'!N46) -> 0 | O46: =SUM(C46:N46) -> 0
B47: DESPESAS | C47: =SUM(C48,C50,C53,C75,C99,C105,C116,C120,C123,C126,C130,C133) -> 201150 | D47: =SUM(D48,D50,D53,D75,D99,D105,D116,D120,D123,D126,D130,D133) -> 315050.36 | E47: =SUM(E48,E50,E53,E75,E99,E105,E116,E120,E123,E126,E130,E133) -> 222078.36 | F47: =SUM(F48,F50,F53,F75,F99,F105,F116,F120,F123,F126,F130,F133) -> 225108.36 | G47: =SUM(G48,G50,G53,G75,G99,G105,G116,G120,G123,G126,G130,G133) -> 208938.36 | H47: =SUM(H48,H50,H53,H75,H99,H105,H116,H120,H123,H126,H130,H133) -> 258158.36 | I47: =SUM(I48,I50,I53,I75,I99,I105,I116,I120,I123,I126,I130,I133) -> 263778.36 | J47: =SUM(J48,J50,J53,J75,J99,J105,J116,J120,J123,J126,J130,J133) -> 226358.36 | ... N47: =SUM(N48,N50,N53,N75,N99,N105,N116,N120,N123,N126,N130,N133) -> 292416 | O47: =SUM(C47:N47) -> 2883941.6
B48: Despesas Diretas | C48: =SUM(C49) -> 800 | D48: =SUM(D49) -> 800 | E48: =SUM(E49) -> 15450 | F48: =SUM(F49) -> 14800 | G48: =SUM(G49) -> 800 | H48: =SUM(H49) -> 800 | I48: =SUM(I49) -> 800 | J48: =SUM(J49) -> 800 | ... N48: =SUM(N49) -> 800 | O48: =SUM(C48:N48) -> 38250
B49: Compras Mercadorias Revenda | C49: =SUM(ADM!C49,MARKETING!C49,COMERCIAL!C49,OPERAÇÕES!C49,'FAVELA 3D'!C49) -> 800 | D49: =SUM(ADM!D49,MARKETING!D49,COMERCIAL!D49,OPERAÇÕES!D49,'FAVELA 3D'!D49) -> 800 | E49: =SUM(ADM!E49,MARKETING!E49,COMERCIAL!E49,OPERAÇÕES!E49,'FAVELA 3D'!E49) -> 15450 | F49: =SUM(ADM!F49,MARKETING!F49,COMERCIAL!F49,OPERAÇÕES!F49,'FAVELA 3D'!F49) -> 14800 | G49: =SUM(ADM!G49,MARKETING!G49,COMERCIAL!G49,OPERAÇÕES!G49,'FAVELA 3D'!G49) -> 800 | H49: =SUM(ADM!H49,MARKETING!H49,COMERCIAL!H49,OPERAÇÕES!H49,'FAVELA 3D'!H49) -> 800 | I49: =SUM(ADM!I49,MARKETING!I49,COMERCIAL!I49,OPERAÇÕES!I49,'FAVELA 3D'!I49) -> 800 | J49: =SUM(ADM!J49,MARKETING!J49,COMERCIAL!J49,OPERAÇÕES!J49,'FAVELA 3D'!J49) -> 800 | ... N49: =SUM(ADM!N49,MARKETING!N49,COMERCIAL!N49,OPERAÇÕES!N49,'FAVELA 3D'!N49) -> 800 | O49: =SUM(C49:N49) -> 38250
B50: Marketing | C50: =SUM(C51:C52) -> 0 | D50: =SUM(D51:D52) -> 20200 | E50: =SUM(E51:E52) -> 600 | F50: =SUM(F51:F52) -> 500 | G50: =SUM(G51:G52) -> 760 | H50: =SUM(H51:H52) -> 40550 | I50: =SUM(I51:I52) -> 40500 | J50: =SUM(J51:J52) -> 700 | ... N50: =SUM(N51:N52) -> 40700 | O50: =SUM(C50:N50) -> 146310
B51: Divulgação | C51: =SUM(ADM!C51,MARKETING!C51,COMERCIAL!C51,OPERAÇÕES!C51,'FAVELA 3D'!C51) -> 0 | D51: =SUM(ADM!D51,MARKETING!D51,COMERCIAL!D51,OPERAÇÕES!D51,'FAVELA 3D'!D51) -> 20200 | E51: =SUM(ADM!E51,MARKETING!E51,COMERCIAL!E51,OPERAÇÕES!E51,'FAVELA 3D'!E51) -> 600 | F51: =SUM(ADM!F51,MARKETING!F51,COMERCIAL!F51,OPERAÇÕES!F51,'FAVELA 3D'!F51) -> 500 | G51: =SUM(ADM!G51,MARKETING!G51,COMERCIAL!G51,OPERAÇÕES!G51,'FAVELA 3D'!G51) -> 760 | H51: =SUM(ADM!H51,MARKETING!H51,COMERCIAL!H51,OPERAÇÕES!H51,'FAVELA 3D'!H51) -> 40550 | I51: =SUM(ADM!I51,MARKETING!I51,COMERCIAL!I51,OPERAÇÕES!I51,'FAVELA 3D'!I51) -> 40500 | J51: =SUM(ADM!J51,MARKETING!J51,COMERCIAL!J51,OPERAÇÕES!J51,'FAVELA 3D'!J51) -> 700 | ... N51: =SUM(ADM!N51,MARKETING!N51,COMERCIAL!N51,OPERAÇÕES!N51,'FAVELA 3D'!N51) -> 40700 | O51: =SUM(C51:N51) -> 146310
B52: Vestuários | C52: =SUM(ADM!C52,MARKETING!C52,COMERCIAL!C52,OPERAÇÕES!C52,'FAVELA 3D'!C52) -> 0 | D52: =SUM(ADM!D52,MARKETING!D52,COMERCIAL!D52,OPERAÇÕES!D52,'FAVELA 3D'!D52) -> 0 | E52: =SUM(ADM!E52,MARKETING!E52,COMERCIAL!E52,OPERAÇÕES!E52,'FAVELA 3D'!E52) -> 0 | F52: =SUM(ADM!F52,MARKETING!F52,COMERCIAL!F52,OPERAÇÕES!F52,'FAVELA 3D'!F52) -> 0 | G52: =SUM(ADM!G52,MARKETING!G52,COMERCIAL!G52,OPERAÇÕES!G52,'FAVELA 3D'!G52) -> 0 | H52: =SUM(ADM!H52,MARKETING!H52,COMERCIAL!H52,OPERAÇÕES!H52,'FAVELA 3D'!H52) -> 0 | I52: =SUM(ADM!I52,MARKETING!I52,COMERCIAL!I52,OPERAÇÕES!I52,'FAVELA 3D'!I52) -> 0 | J52: =SUM(ADM!J52,MARKETING!J52,COMERCIAL!J52,OPERAÇÕES!J52,'FAVELA 3D'!J52) -> 0 | ... N52: =SUM(ADM!N52,MARKETING!N52,COMERCIAL!N52,OPERAÇÕES!N52,'FAVELA 3D'!N52) -> 0 | O52: =SUM(C52:N52) -> 0
B53: Despesas com Pessoal | C53: =SUM(C54:C74) -> 155250 | D53: =SUM(D54:D74) -> 163546 | E53: =SUM(E54:E74) -> 163546 | F53: =SUM(F54:F74) -> 163546 | G53: =SUM(G54:G74) -> 163546 | H53: =SUM(H54:H74) -> 163546 | I53: =SUM(I54:I74) -> 166046 | J53: =SUM(J54:J74) -> 163546 | ... N53: =SUM(N54:N74) -> 175566 | O53: =SUM(C53:N53) -> 1968776
B54: Comissões | C54: =SUM(ADM!C54,MARKETING!C54,COMERCIAL!C54,OPERAÇÕES!C54,'FAVELA 3D'!C54) -> 0 | D54: =SUM(ADM!D54,MARKETING!D54,COMERCIAL!D54,OPERAÇÕES!D54,'FAVELA 3D'!D54) -> 0 | E54: =SUM(ADM!E54,MARKETING!E54,COMERCIAL!E54,OPERAÇÕES!E54,'FAVELA 3D'!E54) -> 0 | F54: =SUM(ADM!F54,MARKETING!F54,COMERCIAL!F54,OPERAÇÕES!F54,'FAVELA 3D'!F54) -> 0 | G54: =SUM(ADM!G54,MARKETING!G54,COMERCIAL!G54,OPERAÇÕES!G54,'FAVELA 3D'!G54) -> 0 | H54: =SUM(ADM!H54,MARKETING!H54,COMERCIAL!H54,OPERAÇÕES!H54,'FAVELA 3D'!H54) -> 0 | I54: =SUM(ADM!I54,MARKETING!I54,COMERCIAL!I54,OPERAÇÕES!I54,'FAVELA 3D'!I54) -> 0 | J54: =SUM(ADM!J54,MARKETING!J54,COMERCIAL!J54,OPERAÇÕES!J54,'FAVELA 3D'!J54) -> 0 | ... N54: =SUM(ADM!N54,MARKETING!N54,COMERCIAL!N54,OPERAÇÕES!N54,'FAVELA 3D'!N54) -> 0 | O54: =SUM(C54:N54) -> 0
B55: Férias | C55: =SUM(ADM!C55,MARKETING!C55,COMERCIAL!C55,OPERAÇÕES!C55,'FAVELA 3D'!C55) -> 0 | D55: =SUM(ADM!D55,MARKETING!D55,COMERCIAL!D55,OPERAÇÕES!D55,'FAVELA 3D'!D55) -> 0 | E55: =SUM(ADM!E55,MARKETING!E55,COMERCIAL!E55,OPERAÇÕES!E55,'FAVELA 3D'!E55) -> 0 | F55: =SUM(ADM!F55,MARKETING!F55,COMERCIAL!F55,OPERAÇÕES!F55,'FAVELA 3D'!F55) -> 0 | G55: =SUM(ADM!G55,MARKETING!G55,COMERCIAL!G55,OPERAÇÕES!G55,'FAVELA 3D'!G55) -> 0 | H55: =SUM(ADM!H55,MARKETING!H55,COMERCIAL!H55,OPERAÇÕES!H55,'FAVELA 3D'!H55) -> 0 | I55: =SUM(ADM!I55,MARKETING!I55,COMERCIAL!I55,OPERAÇÕES!I55,'FAVELA 3D'!I55) -> 0 | J55: =SUM(ADM!J55,MARKETING!J55,COMERCIAL!J55,OPERAÇÕES!J55,'FAVELA 3D'!J55) -> 0 | ... N55: =SUM(ADM!N55,MARKETING!N55,COMERCIAL!N55,OPERAÇÕES!N55,'FAVELA 3D'!N55) -> 0 | O55: =SUM(C55:N55) -> 0
B56: Rescisões | C56: =SUM(ADM!C56,MARKETING!C56,COMERCIAL!C56,OPERAÇÕES!C56,'FAVELA 3D'!C56) -> 0 | D56: =SUM(ADM!D56,MARKETING!D56,COMERCIAL!D56,OPERAÇÕES!D56,'FAVELA 3D'!D56) -> 0 | E56: =SUM(ADM!E56,MARKETING!E56,COMERCIAL!E56,OPERAÇÕES!E56,'FAVELA 3D'!E56) -> 0 | F56: =SUM(ADM!F56,MARKETING!F56,COMERCIAL!F56,OPERAÇÕES!F56,'FAVELA 3D'!F56) -> 0 | G56: =SUM(ADM!G56,MARKETING!G56,COMERCIAL!G56,OPERAÇÕES!G56,'FAVELA 3D'!G56) -> 0 | H56: =SUM(ADM!H56,MARKETING!H56,COMERCIAL!H56,OPERAÇÕES!H56,'FAVELA 3D'!H56) -> 0 | I56: =SUM(ADM!I56,MARKETING!I56,COMERCIAL!I56,OPERAÇÕES!I56,'FAVELA 3D'!I56) -> 0 | J56: =SUM(ADM!J56,MARKETING!J56,COMERCIAL!J56,OPERAÇÕES!J56,'FAVELA 3D'!J56) -> 0 | ... N56: =SUM(ADM!N56,MARKETING!N56,COMERCIAL!N56,OPERAÇÕES!N56,'FAVELA 3D'!N56) -> 0 | O56: =SUM(C56:N56) -> 0
B57: 13º Salário | C57: =SUM(ADM!C57,MARKETING!C57,COMERCIAL!C57,OPERAÇÕES!C57,'FAVELA 3D'!C57) -> 0 | D57: =SUM(ADM!D57,MARKETING!D57,COMERCIAL!D57,OPERAÇÕES!D57,'FAVELA 3D'!D57) -> 0 | E57: =SUM(ADM!E57,MARKETING!E57,COMERCIAL!E57,OPERAÇÕES!E57,'FAVELA 3D'!E57) -> 0 | F57: =SUM(ADM!F57,MARKETING!F57,COMERCIAL!F57,OPERAÇÕES!F57,'FAVELA 3D'!F57) -> 0 | G57: =SUM(ADM!G57,MARKETING!G57,COMERCIAL!G57,OPERAÇÕES!G57,'FAVELA 3D'!G57) -> 0 | H57: =SUM(ADM!H57,MARKETING!H57,COMERCIAL!H57,OPERAÇÕES!H57,'FAVELA 3D'!H57) -> 0 | I57: =SUM(ADM!I57,MARKETING!I57,COMERCIAL!I57,OPERAÇÕES!I57,'FAVELA 3D'!I57) -> 0 | J57: =SUM(ADM!J57,MARKETING!J57,COMERCIAL!J57,OPERAÇÕES!J57,'FAVELA 3D'!J57) -> 0 | ... N57: =SUM(ADM!N57,MARKETING!N57,COMERCIAL!N57,OPERAÇÕES!N57,'FAVELA 3D'!N57) -> 0 | O57: =SUM(C57:N57) -> 0
B58: INSS | C58: =SUM(ADM!C58,MARKETING!C58,COMERCIAL!C58,OPERAÇÕES!C58,'FAVELA 3D'!C58) -> 3000 | D58: =SUM(ADM!D58,MARKETING!D58,COMERCIAL!D58,OPERAÇÕES!D58,'FAVELA 3D'!D58) -> 3000 | E58: =SUM(ADM!E58,MARKETING!E58,COMERCIAL!E58,OPERAÇÕES!E58,'FAVELA 3D'!E58) -> 3000 | F58: =SUM(ADM!F58,MARKETING!F58,COMERCIAL!F58,OPERAÇÕES!F58,'FAVELA 3D'!F58) -> 3000 | G58: =SUM(ADM!G58,MARKETING!G58,COMERCIAL!G58,OPERAÇÕES!G58,'FAVELA 3D'!G58) -> 3000 | H58: =SUM(ADM!H58,MARKETING!H58,COMERCIAL!H58,OPERAÇÕES!H58,'FAVELA 3D'!H58) -> 3000 | I58: =SUM(ADM!I58,MARKETING!I58,COMERCIAL!I58,OPERAÇÕES!I58,'FAVELA 3D'!I58) -> 3000 | J58: =SUM(ADM!J58,MARKETING!J58,COMERCIAL!J58,OPERAÇÕES!J58,'FAVELA 3D'!J58) -> 3000 | ... N58: =SUM(ADM!N58,MARKETING!N58,COMERCIAL!N58,OPERAÇÕES!N58,'FAVELA 3D'!N58) -> 3000 | O58: =SUM(C58:N58) -> 36000
B59: FGTS | C59: =SUM(ADM!C59,MARKETING!C59,COMERCIAL!C59,OPERAÇÕES!C59,'FAVELA 3D'!C59) -> 800 | D59: =SUM(ADM!D59,MARKETING!D59,COMERCIAL!D59,OPERAÇÕES!D59,'FAVELA 3D'!D59) -> 800 | E59: =SUM(ADM!E59,MARKETING!E59,COMERCIAL!E59,OPERAÇÕES!E59,'FAVELA 3D'!E59) -> 800 | F59: =SUM(ADM!F59,MARKETING!F59,COMERCIAL!F59,OPERAÇÕES!F59,'FAVELA 3D'!F59) -> 800 | G59: =SUM(ADM!G59,MARKETING!G59,COMERCIAL!G59,OPERAÇÕES!G59,'FAVELA 3D'!G59) -> 800 | H59: =SUM(ADM!H59,MARKETING!H59,COMERCIAL!H59,OPERAÇÕES!H59,'FAVELA 3D'!H59) -> 800 | I59: =SUM(ADM!I59,MARKETING!I59,COMERCIAL!I59,OPERAÇÕES!I59,'FAVELA 3D'!I59) -> 800 | J59: =SUM(ADM!J59,MARKETING!J59,COMERCIAL!J59,OPERAÇÕES!J59,'FAVELA 3D'!J59) -> 800 | ... N59: =SUM(ADM!N59,MARKETING!N59,COMERCIAL!N59,OPERAÇÕES!N59,'FAVELA 3D'!N59) -> 800 | O59: =SUM(C59:N59) -> 9600
B60: IRRF | C60: =SUM(ADM!C60,MARKETING!C60,COMERCIAL!C60,OPERAÇÕES!C60,'FAVELA 3D'!C60) -> 0 | D60: =SUM(ADM!D60,MARKETING!D60,COMERCIAL!D60,OPERAÇÕES!D60,'FAVELA 3D'!D60) -> 0 | E60: =SUM(ADM!E60,MARKETING!E60,COMERCIAL!E60,OPERAÇÕES!E60,'FAVELA 3D'!E60) -> 0 | F60: =SUM(ADM!F60,MARKETING!F60,COMERCIAL!F60,OPERAÇÕES!F60,'FAVELA 3D'!F60) -> 0 | G60: =SUM(ADM!G60,MARKETING!G60,COMERCIAL!G60,OPERAÇÕES!G60,'FAVELA 3D'!G60) -> 0 | H60: =SUM(ADM!H60,MARKETING!H60,COMERCIAL!H60,OPERAÇÕES!H60,'FAVELA 3D'!H60) -> 0 | I60: =SUM(ADM!I60,MARKETING!I60,COMERCIAL!I60,OPERAÇÕES!I60,'FAVELA 3D'!I60) -> 0 | J60: =SUM(ADM!J60,MARKETING!J60,COMERCIAL!J60,OPERAÇÕES!J60,'FAVELA 3D'!J60) -> 0 | ... N60: =SUM(ADM!N60,MARKETING!N60,COMERCIAL!N60,OPERAÇÕES!N60,'FAVELA 3D'!N60) -> 0 | O60: =SUM(C60:N60) -> 0
B61: Exames | C61: =SUM(ADM!C61,MARKETING!C61,COMERCIAL!C61,OPERAÇÕES!C61,'FAVELA 3D'!C61) -> 0 | D61: =SUM(ADM!D61,MARKETING!D61,COMERCIAL!D61,OPERAÇÕES!D61,'FAVELA 3D'!D61) -> 0 | E61: =SUM(ADM!E61,MARKETING!E61,COMERCIAL!E61,OPERAÇÕES!E61,'FAVELA 3D'!E61) -> 0 | F61: =SUM(ADM!F61,MARKETING!F61,COMERCIAL!F61,OPERAÇÕES!F61,'FAVELA 3D'!F61) -> 0 | G61: =SUM(ADM!G61,MARKETING!G61,COMERCIAL!G61,OPERAÇÕES!G61,'FAVELA 3D'!G61) -> 0 | H61: =SUM(ADM!H61,MARKETING!H61,COMERCIAL!H61,OPERAÇÕES!H61,'FAVELA 3D'!H61) -> 0 | I61: =SUM(ADM!I61,MARKETING!I61,COMERCIAL!I61,OPERAÇÕES!I61,'FAVELA 3D'!I61) -> 0 | J61: =SUM(ADM!J61,MARKETING!J61,COMERCIAL!J61,OPERAÇÕES!J61,'FAVELA 3D'!J61) -> 0 | ... N61: =SUM(ADM!N61,MARKETING!N61,COMERCIAL!N61,OPERAÇÕES!N61,'FAVELA 3D'!N61) -> 0 | O61: =SUM(C61:N61) -> 0
B62: Assistência Médica | C62: =SUM(ADM!C62,MARKETING!C62,COMERCIAL!C62,OPERAÇÕES!C62,'FAVELA 3D'!C62) -> 0 | D62: =SUM(ADM!D62,MARKETING!D62,COMERCIAL!D62,OPERAÇÕES!D62,'FAVELA 3D'!D62) -> 0 | E62: =SUM(ADM!E62,MARKETING!E62,COMERCIAL!E62,OPERAÇÕES!E62,'FAVELA 3D'!E62) -> 0 | F62: =SUM(ADM!F62,MARKETING!F62,COMERCIAL!F62,OPERAÇÕES!F62,'FAVELA 3D'!F62) -> 0 | G62: =SUM(ADM!G62,MARKETING!G62,COMERCIAL!G62,OPERAÇÕES!G62,'FAVELA 3D'!G62) -> 0 | H62: =SUM(ADM!H62,MARKETING!H62,COMERCIAL!H62,OPERAÇÕES!H62,'FAVELA 3D'!H62) -> 0 | I62: =SUM(ADM!I62,MARKETING!I62,COMERCIAL!I62,OPERAÇÕES!I62,'FAVELA 3D'!I62) -> 0 | J62: =SUM(ADM!J62,MARKETING!J62,COMERCIAL!J62,OPERAÇÕES!J62,'FAVELA 3D'!J62) -> 0 | ... N62: =SUM(ADM!N62,MARKETING!N62,COMERCIAL!N62,OPERAÇÕES!N62,'FAVELA 3D'!N62) -> 0 | O62: =SUM(C62:N62) -> 0
B63: Vale Transporte | C63: =SUM(ADM!C63,MARKETING!C63,COMERCIAL!C63,OPERAÇÕES!C63,'FAVELA 3D'!C63) -> 1200 | D63: =SUM(ADM!D63,MARKETING!D63,COMERCIAL!D63,OPERAÇÕES!D63,'FAVELA 3D'!D63) -> 1200 | E63: =SUM(ADM!E63,MARKETING!E63,COMERCIAL!E63,OPERAÇÕES!E63,'FAVELA 3D'!E63) -> 1200 | F63: =SUM(ADM!F63,MARKETING!F63,COMERCIAL!F63,OPERAÇÕES!F63,'FAVELA 3D'!F63) -> 1200 | G63: =SUM(ADM!G63,MARKETING!G63,COMERCIAL!G63,OPERAÇÕES!G63,'FAVELA 3D'!G63) -> 1200 | H63: =SUM(ADM!H63,MARKETING!H63,COMERCIAL!H63,OPERAÇÕES!H63,'FAVELA 3D'!H63) -> 1200 | I63: =SUM(ADM!I63,MARKETING!I63,COMERCIAL!I63,OPERAÇÕES!I63,'FAVELA 3D'!I63) -> 1200 | J63: =SUM(ADM!J63,MARKETING!J63,COMERCIAL!J63,OPERAÇÕES!J63,'FAVELA 3D'!J63) -> 1200 | ... N63: =SUM(ADM!N63,MARKETING!N63,COMERCIAL!N63,OPERAÇÕES!N63,'FAVELA 3D'!N63) -> 1200 | O63: =SUM(C63:N63) -> 14400
B64: Vale Refeição | C64: =SUM(ADM!C64,MARKETING!C64,COMERCIAL!C64,OPERAÇÕES!C64,'FAVELA 3D'!C64) -> 4650 | D64: =SUM(ADM!D64,MARKETING!D64,COMERCIAL!D64,OPERAÇÕES!D64,'FAVELA 3D'!D64) -> 4650 | E64: =SUM(ADM!E64,MARKETING!E64,COMERCIAL!E64,OPERAÇÕES!E64,'FAVELA 3D'!E64) -> 4650 | F64: =SUM(ADM!F64,MARKETING!F64,COMERCIAL!F64,OPERAÇÕES!F64,'FAVELA 3D'!F64) -> 4650 | G64: =SUM(ADM!G64,MARKETING!G64,COMERCIAL!G64,OPERAÇÕES!G64,'FAVELA 3D'!G64) -> 4650 | H64: =SUM(ADM!H64,MARKETING!H64,COMERCIAL!H64,OPERAÇÕES!H64,'FAVELA 3D'!H64) -> 4650 | I64: =SUM(ADM!I64,MARKETING!I64,COMERCIAL!I64,OPERAÇÕES!I64,'FAVELA 3D'!I64) -> 4650 | J64: =SUM(ADM!J64,MARKETING!J64,COMERCIAL!J64,OPERAÇÕES!J64,'FAVELA 3D'!J64) -> 4650 | ... N64: =SUM(ADM!N64,MARKETING!N64,COMERCIAL!N64,OPERAÇÕES!N64,'FAVELA 3D'!N64) -> 4650 | O64: =SUM(C64:N64) -> 55800
B65: Seguro de Vida | C65: =SUM(ADM!C65,MARKETING!C65,COMERCIAL!C65,OPERAÇÕES!C65,'FAVELA 3D'!C65) -> 50 | D65: =SUM(ADM!D65,MARKETING!D65,COMERCIAL!D65,OPERAÇÕES!D65,'FAVELA 3D'!D65) -> 50 | E65: =SUM(ADM!E65,MARKETING!E65,COMERCIAL!E65,OPERAÇÕES!E65,'FAVELA 3D'!E65) -> 50 | F65: =SUM(ADM!F65,MARKETING!F65,COMERCIAL!F65,OPERAÇÕES!F65,'FAVELA 3D'!F65) -> 50 | G65: =SUM(ADM!G65,MARKETING!G65,COMERCIAL!G65,OPERAÇÕES!G65,'FAVELA 3D'!G65) -> 50 | H65: =SUM(ADM!H65,MARKETING!H65,COMERCIAL!H65,OPERAÇÕES!H65,'FAVELA 3D'!H65) -> 50 | I65: =SUM(ADM!I65,MARKETING!I65,COMERCIAL!I65,OPERAÇÕES!I65,'FAVELA 3D'!I65) -> 50 | J65: =SUM(ADM!J65,MARKETING!J65,COMERCIAL!J65,OPERAÇÕES!J65,'FAVELA 3D'!J65) -> 50 | ... N65: =SUM(ADM!N65,MARKETING!N65,COMERCIAL!N65,OPERAÇÕES!N65,'FAVELA 3D'!N65) -> 50 | O65: =SUM(C65:N65) -> 600
... B74: Ajuda de Custo | C74: =SUM(ADM!C74,MARKETING!C74,COMERCIAL!C74,OPERAÇÕES!C74,'FAVELA 3D'!C74) -> 0 | D74: =SUM(ADM!D74,MARKETING!D74,COMERCIAL!D74,OPERAÇÕES!D74,'FAVELA 3D'!D74) -> 100 | E74: =SUM(ADM!E74,MARKETING!E74,COMERCIAL!E74,OPERAÇÕES!E74,'FAVELA 3D'!E74) -> 100 | F74: =SUM(ADM!F74,MARKETING!F74,COMERCIAL!F74,OPERAÇÕES!F74,'FAVELA 3D'!F74) -> 100 | G74: =SUM(ADM!G74,MARKETING!G74,COMERCIAL!G74,OPERAÇÕES!G74,'FAVELA 3D'!G74) -> 100 | H74: =SUM(ADM!H74,MARKETING!H74,COMERCIAL!H74,OPERAÇÕES!H74,'FAVELA 3D'!H74) -> 100 | I74: =SUM(ADM!I74,MARKETING!I74,COMERCIAL!I74,OPERAÇÕES!I74,'FAVELA 3D'!I74) -> 100 | J74: =SUM(ADM!J74,MARKETING!J74,COMERCIAL!J74,OPERAÇÕES!J74,'FAVELA 3D'!J74) -> 100 | ... N74: =SUM(ADM!N74,MARKETING!N74,COMERCIAL!N74,OPERAÇÕES!N74,'FAVELA 3D'!N74) -> 100 | O74: =SUM(C74:N74) -> 1100
B75: Despesas Administrativas | C75: =SUM(C76:C98) -> 41900 | D75: =SUM(D76:D98) -> 59754.36 | E75: =SUM(E76:E98) -> 33982.36 | F75: =SUM(F76:F98) -> 37112.36 | G75: =SUM(G76:G98) -> 34532.36 | H75: =SUM(H76:H98) -> 35012.36 | I75: =SUM(I76:I98) -> 37132.36 | J75: =SUM(J76:J98) -> 51762.36 | ... N75: =SUM(N76:N98) -> 30800 | O75: =SUM(C75:N75) -> 469705.6
B76: Aluguel Espaços | C76: =SUM(ADM!C76,MARKETING!C76,COMERCIAL!C76,OPERAÇÕES!C76,'FAVELA 3D'!C76) -> 6275 | D76: =SUM(ADM!D76,MARKETING!D76,COMERCIAL!D76,OPERAÇÕES!D76,'FAVELA 3D'!D76) -> 6575 | E76: =SUM(ADM!E76,MARKETING!E76,COMERCIAL!E76,OPERAÇÕES!E76,'FAVELA 3D'!E76) -> 6775 | F76: =SUM(ADM!F76,MARKETING!F76,COMERCIAL!F76,OPERAÇÕES!F76,'FAVELA 3D'!F76) -> 6775 | G76: =SUM(ADM!G76,MARKETING!G76,COMERCIAL!G76,OPERAÇÕES!G76,'FAVELA 3D'!G76) -> 6775 | H76: =SUM(ADM!H76,MARKETING!H76,COMERCIAL!H76,OPERAÇÕES!H76,'FAVELA 3D'!H76) -> 6775 | I76: =SUM(ADM!I76,MARKETING!I76,COMERCIAL!I76,OPERAÇÕES!I76,'FAVELA 3D'!I76) -> 6775 | J76: =SUM(ADM!J76,MARKETING!J76,COMERCIAL!J76,OPERAÇÕES!J76,'FAVELA 3D'!J76) -> 7125 | ... N76: =SUM(ADM!N76,MARKETING!N76,COMERCIAL!N76,OPERAÇÕES!N76,'FAVELA 3D'!N76) -> 7125 | O76: =SUM(C76:N76) -> 82350
B77: Aluguel/Locações Outros | C77: =SUM(ADM!C77,MARKETING!C77,COMERCIAL!C77,OPERAÇÕES!C77,'FAVELA 3D'!C77) -> 0 | D77: =SUM(ADM!D77,MARKETING!D77,COMERCIAL!D77,OPERAÇÕES!D77,'FAVELA 3D'!D77) -> 2250 | E77: =SUM(ADM!E77,MARKETING!E77,COMERCIAL!E77,OPERAÇÕES!E77,'FAVELA 3D'!E77) -> 2250 | F77: =SUM(ADM!F77,MARKETING!F77,COMERCIAL!F77,OPERAÇÕES!F77,'FAVELA 3D'!F77) -> 2250 | G77: =SUM(ADM!G77,MARKETING!G77,COMERCIAL!G77,OPERAÇÕES!G77,'FAVELA 3D'!G77) -> 2250 | H77: =SUM(ADM!H77,MARKETING!H77,COMERCIAL!H77,OPERAÇÕES!H77,'FAVELA 3D'!H77) -> 2250 | I77: =SUM(ADM!I77,MARKETING!I77,COMERCIAL!I77,OPERAÇÕES!I77,'FAVELA 3D'!I77) -> 2250 | J77: =SUM(ADM!J77,MARKETING!J77,COMERCIAL!J77,OPERAÇÕES!J77,'FAVELA 3D'!J77) -> 2250 | ... N77: =SUM(ADM!N77,MARKETING!N77,COMERCIAL!N77,OPERAÇÕES!N77,'FAVELA 3D'!N77) -> 2250 | O77: =SUM(C77:N77) -> 24750
B78: ÁGUA | C78: =SUM(ADM!C78,MARKETING!C78,COMERCIAL!C78,OPERAÇÕES!C78,'FAVELA 3D'!C78) -> 950 | D78: =SUM(ADM!D78,MARKETING!D78,COMERCIAL!D78,OPERAÇÕES!D78,'FAVELA 3D'!D78) -> 950 | E78: =SUM(ADM!E78,MARKETING!E78,COMERCIAL!E78,OPERAÇÕES!E78,'FAVELA 3D'!E78) -> 950 | F78: =SUM(ADM!F78,MARKETING!F78,COMERCIAL!F78,OPERAÇÕES!F78,'FAVELA 3D'!F78) -> 950 | G78: =SUM(ADM!G78,MARKETING!G78,COMERCIAL!G78,OPERAÇÕES!G78,'FAVELA 3D'!G78) -> 950 | H78: =SUM(ADM!H78,MARKETING!H78,COMERCIAL!H78,OPERAÇÕES!H78,'FAVELA 3D'!H78) -> 950 | I78: =SUM(ADM!I78,MARKETING!I78,COMERCIAL!I78,OPERAÇÕES!I78,'FAVELA 3D'!I78) -> 950 | J78: =SUM(ADM!J78,MARKETING!J78,COMERCIAL!J78,OPERAÇÕES!J78,'FAVELA 3D'!J78) -> 950 | ... N78: =SUM(ADM!N78,MARKETING!N78,COMERCIAL!N78,OPERAÇÕES!N78,'FAVELA 3D'!N78) -> 950 | O78: =SUM(C78:N78) -> 11400
B79: Energia Elétrica | C79: =SUM(ADM!C79,MARKETING!C79,COMERCIAL!C79,OPERAÇÕES!C79,'FAVELA 3D'!C79) -> 2450 | D79: =SUM(ADM!D79,MARKETING!D79,COMERCIAL!D79,OPERAÇÕES!D79,'FAVELA 3D'!D79) -> 2650 | E79: =SUM(ADM!E79,MARKETING!E79,COMERCIAL!E79,OPERAÇÕES!E79,'FAVELA 3D'!E79) -> 2650 | F79: =SUM(ADM!F79,MARKETING!F79,COMERCIAL!F79,OPERAÇÕES!F79,'FAVELA 3D'!F79) -> 2650 | G79: =SUM(ADM!G79,MARKETING!G79,COMERCIAL!G79,OPERAÇÕES!G79,'FAVELA 3D'!G79) -> 2650 | H79: =SUM(ADM!H79,MARKETING!H79,COMERCIAL!H79,OPERAÇÕES!H79,'FAVELA 3D'!H79) -> 2650 | I79: =SUM(ADM!I79,MARKETING!I79,COMERCIAL!I79,OPERAÇÕES!I79,'FAVELA 3D'!I79) -> 2650 | J79: =SUM(ADM!J79,MARKETING!J79,COMERCIAL!J79,OPERAÇÕES!J79,'FAVELA 3D'!J79) -> 2650 | ... N79: =SUM(ADM!N79,MARKETING!N79,COMERCIAL!N79,OPERAÇÕES!N79,'FAVELA 3D'!N79) -> 2650 | O79: =SUM(C79:N79) -> 31600
B80: TELEFONIA/INTERNET | C80: =SUM(ADM!C80,MARKETING!C80,COMERCIAL!C80,OPERAÇÕES!C80,'FAVELA 3D'!C80) -> 1545 | D80: =SUM(ADM!D80,MARKETING!D80,COMERCIAL!D80,OPERAÇÕES!D80,'FAVELA 3D'!D80) -> 1545 | E80: =SUM(ADM!E80,MARKETING!E80,COMERCIAL!E80,OPERAÇÕES!E80,'FAVELA 3D'!E80) -> 1545 | F80: =SUM(ADM!F80,MARKETING!F80,COMERCIAL!F80,OPERAÇÕES!F80,'FAVELA 3D'!F80) -> 1545 | G80: =SUM(ADM!G80,MARKETING!G80,COMERCIAL!G80,OPERAÇÕES!G80,'FAVELA 3D'!G80) -> 1545 | H80: =SUM(ADM!H80,MARKETING!H80,COMERCIAL!H80,OPERAÇÕES!H80,'FAVELA 3D'!H80) -> 1545 | I80: =SUM(ADM!I80,MARKETING!I80,COMERCIAL!I80,OPERAÇÕES!I80,'FAVELA 3D'!I80) -> 1545 | J80: =SUM(ADM!J80,MARKETING!J80,COMERCIAL!J80,OPERAÇÕES!J80,'FAVELA 3D'!J80) -> 1545 | ... N80: =SUM(ADM!N80,MARKETING!N80,COMERCIAL!N80,OPERAÇÕES!N80,'FAVELA 3D'!N80) -> 1545 | O80: =SUM(C80:N80) -> 18540
B81: Material de Escritório | C81: =SUM(ADM!C81,MARKETING!C81,COMERCIAL!C81,OPERAÇÕES!C81,'FAVELA 3D'!C81) -> 800 | D81: =SUM(ADM!D81,MARKETING!D81,COMERCIAL!D81,OPERAÇÕES!D81,'FAVELA 3D'!D81) -> 850 | E81: =SUM(ADM!E81,MARKETING!E81,COMERCIAL!E81,OPERAÇÕES!E81,'FAVELA 3D'!E81) -> 200 | F81: =SUM(ADM!F81,MARKETING!F81,COMERCIAL!F81,OPERAÇÕES!F81,'FAVELA 3D'!F81) -> 1300 | G81: =SUM(ADM!G81,MARKETING!G81,COMERCIAL!G81,OPERAÇÕES!G81,'FAVELA 3D'!G81) -> 200 | H81: =SUM(ADM!H81,MARKETING!H81,COMERCIAL!H81,OPERAÇÕES!H81,'FAVELA 3D'!H81) -> 200 | I81: =SUM(ADM!I81,MARKETING!I81,COMERCIAL!I81,OPERAÇÕES!I81,'FAVELA 3D'!I81) -> 1300 | J81: =SUM(ADM!J81,MARKETING!J81,COMERCIAL!J81,OPERAÇÕES!J81,'FAVELA 3D'!J81) -> 400 | ... N81: =SUM(ADM!N81,MARKETING!N81,COMERCIAL!N81,OPERAÇÕES!N81,'FAVELA 3D'!N81) -> 200 | O81: =SUM(C81:N81) -> 7150
B82: Gás | C82: =SUM(ADM!C82,MARKETING!C82,COMERCIAL!C82,OPERAÇÕES!C82,'FAVELA 3D'!C82) -> 120 | D82: =SUM(ADM!D82,MARKETING!D82,COMERCIAL!D82,OPERAÇÕES!D82,'FAVELA 3D'!D82) -> 120 | E82: =SUM(ADM!E82,MARKETING!E82,COMERCIAL!E82,OPERAÇÕES!E82,'FAVELA 3D'!E82) -> 240 | F82: =SUM(ADM!F82,MARKETING!F82,COMERCIAL!F82,OPERAÇÕES!F82,'FAVELA 3D'!F82) -> 120 | G82: =SUM(ADM!G82,MARKETING!G82,COMERCIAL!G82,OPERAÇÕES!G82,'FAVELA 3D'!G82) -> 240 | H82: =SUM(ADM!H82,MARKETING!H82,COMERCIAL!H82,OPERAÇÕES!H82,'FAVELA 3D'!H82) -> 120 | I82: =SUM(ADM!I82,MARKETING!I82,COMERCIAL!I82,OPERAÇÕES!I82,'FAVELA 3D'!I82) -> 240 | J82: =SUM(ADM!J82,MARKETING!J82,COMERCIAL!J82,OPERAÇÕES!J82,'FAVELA 3D'!J82) -> 120 | ... N82: =SUM(ADM!N82,MARKETING!N82,COMERCIAL!N82,OPERAÇÕES!N82,'FAVELA 3D'!N82) -> 120 | O82: =SUM(C82:N82) -> 2040
B83: Seguros | C83: =SUM(ADM!C83,MARKETING!C83,COMERCIAL!C83,OPERAÇÕES!C83,'FAVELA 3D'!C83) -> 2500 | D83: =SUM(ADM!D83,MARKETING!D83,COMERCIAL!D83,OPERAÇÕES!D83,'FAVELA 3D'!D83) -> 0 | E83: =SUM(ADM!E83,MARKETING!E83,COMERCIAL!E83,OPERAÇÕES!E83,'FAVELA 3D'!E83) -> 0 | F83: =SUM(ADM!F83,MARKETING!F83,COMERCIAL!F83,OPERAÇÕES!F83,'FAVELA 3D'!F83) -> 0 | G83: =SUM(ADM!G83,MARKETING!G83,COMERCIAL!G83,OPERAÇÕES!G83,'FAVELA 3D'!G83) -> 0 | H83: =SUM(ADM!H83,MARKETING!H83,COMERCIAL!H83,OPERAÇÕES!H83,'FAVELA 3D'!H83) -> 0 | I83: =SUM(ADM!I83,MARKETING!I83,COMERCIAL!I83,OPERAÇÕES!I83,'FAVELA 3D'!I83) -> 0 | J83: =SUM(ADM!J83,MARKETING!J83,COMERCIAL!J83,OPERAÇÕES!J83,'FAVELA 3D'!J83) -> 16000 | ... N83: =SUM(ADM!N83,MARKETING!N83,COMERCIAL!N83,OPERAÇÕES!N83,'FAVELA 3D'!N83) -> 0 | O83: =SUM(C83:N83) -> 18500
B84: IPTU | C84: =SUM(ADM!C84,MARKETING!C84,COMERCIAL!C84,OPERAÇÕES!C84,'FAVELA 3D'!C84) -> 0 | D84: =SUM(ADM!D84,MARKETING!D84,COMERCIAL!D84,OPERAÇÕES!D84,'FAVELA 3D'!D84) -> 0 | E84: =SUM(ADM!E84,MARKETING!E84,COMERCIAL!E84,OPERAÇÕES!E84,'FAVELA 3D'!E84) -> 0 | F84: =SUM(ADM!F84,MARKETING!F84,COMERCIAL!F84,OPERAÇÕES!F84,'FAVELA 3D'!F84) -> 1600 | G84: =SUM(ADM!G84,MARKETING!G84,COMERCIAL!G84,OPERAÇÕES!G84,'FAVELA 3D'!G84) -> 0 | H84: =SUM(ADM!H84,MARKETING!H84,COMERCIAL!H84,OPERAÇÕES!H84,'FAVELA 3D'!H84) -> 0 | I84: =SUM(ADM!I84,MARKETING!I84,COMERCIAL!I84,OPERAÇÕES!I84,'FAVELA 3D'!I84) -> 0 | J84: =SUM(ADM!J84,MARKETING!J84,COMERCIAL!J84,OPERAÇÕES!J84,'FAVELA 3D'!J84) -> 0 | ... N84: =SUM(ADM!N84,MARKETING!N84,COMERCIAL!N84,OPERAÇÕES!N84,'FAVELA 3D'!N84) -> 0 | O84: =SUM(C84:N84) -> 1600
B85: Contabilidade | C85: =SUM(ADM!C85,MARKETING!C85,COMERCIAL!C85,OPERAÇÕES!C85,'FAVELA 3D'!C85) -> 950 | D85: =SUM(ADM!D85,MARKETING!D85,COMERCIAL!D85,OPERAÇÕES!D85,'FAVELA 3D'!D85) -> 950 | E85: =SUM(ADM!E85,MARKETING!E85,COMERCIAL!E85,OPERAÇÕES!E85,'FAVELA 3D'!E85) -> 950 | F85: =SUM(ADM!F85,MARKETING!F85,COMERCIAL!F85,OPERAÇÕES!F85,'FAVELA 3D'!F85) -> 950 | G85: =SUM(ADM!G85,MARKETING!G85,COMERCIAL!G85,OPERAÇÕES!G85,'FAVELA 3D'!G85) -> 950 | H85: =SUM(ADM!H85,MARKETING!H85,COMERCIAL!H85,OPERAÇÕES!H85,'FAVELA 3D'!H85) -> 950 | I85: =SUM(ADM!I85,MARKETING!I85,COMERCIAL!I85,OPERAÇÕES!I85,'FAVELA 3D'!I85) -> 950 | J85: =SUM(ADM!J85,MARKETING!J85,COMERCIAL!J85,OPERAÇÕES!J85,'FAVELA 3D'!J85) -> 950 | ... N85: =SUM(ADM!N85,MARKETING!N85,COMERCIAL!N85,OPERAÇÕES!N85,'FAVELA 3D'!N85) -> 1450 | O85: =SUM(C85:N85) -> 12400
B86: Advogados | C86: =SUM(ADM!C86,MARKETING!C86,COMERCIAL!C86,OPERAÇÕES!C86,'FAVELA 3D'!C86) -> 2500 | D86: =SUM(ADM!D86,MARKETING!D86,COMERCIAL!D86,OPERAÇÕES!D86,'FAVELA 3D'!D86) -> 2500 | E86: =SUM(ADM!E86,MARKETING!E86,COMERCIAL!E86,OPERAÇÕES!E86,'FAVELA 3D'!E86) -> 2500 | F86: =SUM(ADM!F86,MARKETING!F86,COMERCIAL!F86,OPERAÇÕES!F86,'FAVELA 3D'!F86) -> 2500 | G86: =SUM(ADM!G86,MARKETING!G86,COMERCIAL!G86,OPERAÇÕES!G86,'FAVELA 3D'!G86) -> 2500 | H86: =SUM(ADM!H86,MARKETING!H86,COMERCIAL!H86,OPERAÇÕES!H86,'FAVELA 3D'!H86) -> 2500 | I86: =SUM(ADM!I86,MARKETING!I86,COMERCIAL!I86,OPERAÇÕES!I86,'FAVELA 3D'!I86) -> 2500 | J86: =SUM(ADM!J86,MARKETING!J86,COMERCIAL!J86,OPERAÇÕES!J86,'FAVELA 3D'!J86) -> 2500 | ... N86: =SUM(ADM!N86,MARKETING!N86,COMERCIAL!N86,OPERAÇÕES!N86,'FAVELA 3D'!N86) -> 2500 | O86: =SUM(C86:N86) -> 30000
B87: Segurança | C87: =SUM(ADM!C87,MARKETING!C87,COMERCIAL!C87,OPERAÇÕES!C87,'FAVELA 3D'!C87) -> 0 | D87: =SUM(ADM!D87,MARKETING!D87,COMERCIAL!D87,OPERAÇÕES!D87,'FAVELA 3D'!D87) -> 0 | E87: =SUM(ADM!E87,MARKETING!E87,COMERCIAL!E87,OPERAÇÕES!E87,'FAVELA 3D'!E87) -> 0 | F87: =SUM(ADM!F87,MARKETING!F87,COMERCIAL!F87,OPERAÇÕES!F87,'FAVELA 3D'!F87) -> 0 | G87: =SUM(ADM!G87,MARKETING!G87,COMERCIAL!G87,OPERAÇÕES!G87,'FAVELA 3D'!G87) -> 0 | H87: =SUM(ADM!H87,MARKETING!H87,COMERCIAL!H87,OPERAÇÕES!H87,'FAVELA 3D'!H87) -> 0 | I87: =SUM(ADM!I87,MARKETING!I87,COMERCIAL!I87,OPERAÇÕES!I87,'FAVELA 3D'!I87) -> 0 | J87: =SUM(ADM!J87,MARKETING!J87,COMERCIAL!J87,OPERAÇÕES!J87,'FAVELA 3D'!J87) -> 0 | ... N87: =SUM(ADM!N87,MARKETING!N87,COMERCIAL!N87,OPERAÇÕES!N87,'FAVELA 3D'!N87) -> 0 | O87: =SUM(C87:N87) -> 0
... B98: PRESTAÇÃO SERV. TERCEIROS | C98: =SUM(ADM!C98,MARKETING!C98,COMERCIAL!C98,OPERAÇÕES!C98,'FAVELA 3D'!C98) -> 1200 | D98: =SUM(ADM!D98,MARKETING!D98,COMERCIAL!D98,OPERAÇÕES!D98,'FAVELA 3D'!D98) -> 1200 | E98: =SUM(ADM!E98,MARKETING!E98,COMERCIAL!E98,OPERAÇÕES!E98,'FAVELA 3D'!E98) -> 1200 | F98: =SUM(ADM!F98,MARKETING!F98,COMERCIAL!F98,OPERAÇÕES!F98,'FAVELA 3D'!F98) -> 1200 | G98: =SUM(ADM!G98,MARKETING!G98,COMERCIAL!G98,OPERAÇÕES!G98,'FAVELA 3D'!G98) -> 1200 | H98: =SUM(ADM!H98,MARKETING!H98,COMERCIAL!H98,OPERAÇÕES!H98,'FAVELA 3D'!H98) -> 1800 | I98: =SUM(ADM!I98,MARKETING!I98,COMERCIAL!I98,OPERAÇÕES!I98,'FAVELA 3D'!I98) -> 1200 | J98: =SUM(ADM!J98,MARKETING!J98,COMERCIAL!J98,OPERAÇÕES!J98,'FAVELA 3D'!J98) -> 1550 | ... N98: =SUM(ADM!N98,MARKETING!N98,COMERCIAL!N98,OPERAÇÕES!N98,'FAVELA 3D'!N98) -> 1550 | O98: =SUM(C98:N98) -> 17750
B99: Despesas Financeiras / Bancos | C99: =SUM(C100:C104) -> 250 | D99: =SUM(D100:D104) -> 250 | E99: =SUM(E100:E104) -> 250 | F99: =SUM(F100:F104) -> 250 | G99: =SUM(G100:G104) -> 250 | H99: =SUM(H100:H104) -> 250 | I99: =SUM(I100:I104) -> 250 | J99: =SUM(J100:J104) -> 250 | ... N99: =SUM(N100:N104) -> 250 | O99: =SUM(C99:N99) -> 3000
B100: Juros sobre Empréstimos | C100: =SUM(ADM!C100,MARKETING!C100,COMERCIAL!C100,OPERAÇÕES!C100,'FAVELA 3D'!C100) -> 0 | D100: =SUM(ADM!D100,MARKETING!D100,COMERCIAL!D100,OPERAÇÕES!D100,'FAVELA 3D'!D100) -> 0 | E100: =SUM(ADM!E100,MARKETING!E100,COMERCIAL!E100,OPERAÇÕES!E100,'FAVELA 3D'!E100) -> 0 | F100: =SUM(ADM!F100,MARKETING!F100,COMERCIAL!F100,OPERAÇÕES!F100,'FAVELA 3D'!F100) -> 0 | G100: =SUM(ADM!G100,MARKETING!G100,COMERCIAL!G100,OPERAÇÕES!G100,'FAVELA 3D'!G100) -> 0 | H100: =SUM(ADM!H100,MARKETING!H100,COMERCIAL!H100,OPERAÇÕES!H100,'FAVELA 3D'!H100) -> 0 | I100: =SUM(ADM!I100,MARKETING!I100,COMERCIAL!I100,OPERAÇÕES!I100,'FAVELA 3D'!I100) -> 0 | J100: =SUM(ADM!J100,MARKETING!J100,COMERCIAL!J100,OPERAÇÕES!J100,'FAVELA 3D'!J100) -> 0 | ... N100: =SUM(ADM!N100,MARKETING!N100,COMERCIAL!N100,OPERAÇÕES!N100,'FAVELA 3D'!N100) -> 0 | O100: =SUM(C100:N100) -> 0
B101: Multas | C101: =SUM(ADM!C101,MARKETING!C101,COMERCIAL!C101,OPERAÇÕES!C101,'FAVELA 3D'!C101) -> 0 | D101: =SUM(ADM!D101,MARKETING!D101,COMERCIAL!D101,OPERAÇÕES!D101,'FAVELA 3D'!D101) -> 0 | E101: =SUM(ADM!E101,MARKETING!E101,COMERCIAL!E101,OPERAÇÕES!E101,'FAVELA 3D'!E101) -> 0 | F101: =SUM(ADM!F101,MARKETING!F101,COMERCIAL!F101,OPERAÇÕES!F101,'FAVELA 3D'!F101) -> 0 | G101: =SUM(ADM!G101,MARKETING!G101,COMERCIAL!G101,OPERAÇÕES!G101,'FAVELA 3D'!G101) -> 0 | H101: =SUM(ADM!H101,MARKETING!H101,COMERCIAL!H101,OPERAÇÕES!H101,'FAVELA 3D'!H101) -> 0 | I101: =SUM(ADM!I101,MARKETING!I101,COMERCIAL!I101,OPERAÇÕES!I101,'FAVELA 3D'!I101) -> 0 | J101: =SUM(ADM!J101,MARKETING!J101,COMERCIAL!J101,OPERAÇÕES!J101,'FAVELA 3D'!J101) -> 0 | ... N101: =SUM(ADM!N101,MARKETING!N101,COMERCIAL!N101,OPERAÇÕES!N101,'FAVELA 3D'!N101) -> 0 | O101: =SUM(C101:N101) -> 0
B102: Pagamento de Empréstimos | C102: =SUM(ADM!C102,MARKETING!C102,COMERCIAL!C102,OPERAÇÕES!C102,'FAVELA 3D'!C102) -> 0 | D102: =SUM(ADM!D102,MARKETING!D102,COMERCIAL!D102,OPERAÇÕES!D102,'FAVELA 3D'!D102) -> 0 | E102: =SUM(ADM!E102,MARKETING!E102,COMERCIAL!E102,OPERAÇÕES!E102,'FAVELA 3D'!E102) -> 0 | F102: =SUM(ADM!F102,MARKETING!F102,COMERCIAL!F102,OPERAÇÕES!F102,'FAVELA 3D'!F102) -> 0 | G102: =SUM(ADM!G102,MARKETING!G102,COMERCIAL!G102,OPERAÇÕES!G102,'FAVELA 3D'!G102) -> 0 | H102: =SUM(ADM!H102,MARKETING!H102,COMERCIAL!H102,OPERAÇÕES!H102,'FAVELA 3D'!H102) -> 0 | I102: =SUM(ADM!I102,MARKETING!I102,COMERCIAL!I102,OPERAÇÕES!I102,'FAVELA 3D'!I102) -> 0 | J102: =SUM(ADM!J102,MARKETING!J102,COMERCIAL!J102,OPERAÇÕES!J102,'FAVELA 3D'!J102) -> 0 | ... N102: =SUM(ADM!N102,MARKETING!N102,COMERCIAL!N102,OPERAÇÕES!N102,'FAVELA 3D'!N102) -> 0 | O102: =SUM(C102:N102) -> 0
B103: Tarifas Bancárias | C103: =SUM(ADM!C103,MARKETING!C103,COMERCIAL!C103,OPERAÇÕES!C103,'FAVELA 3D'!C103) -> 250 | D103: =SUM(ADM!D103,MARKETING!D103,COMERCIAL!D103,OPERAÇÕES!D103,'FAVELA 3D'!D103) -> 250 | E103: =SUM(ADM!E103,MARKETING!E103,COMERCIAL!E103,OPERAÇÕES!E103,'FAVELA 3D'!E103) -> 250 | F103: =SUM(ADM!F103,MARKETING!F103,COMERCIAL!F103,OPERAÇÕES!F103,'FAVELA 3D'!F103) -> 250 | G103: =SUM(ADM!G103,MARKETING!G103,COMERCIAL!G103,OPERAÇÕES!G103,'FAVELA 3D'!G103) -> 250 | H103: =SUM(ADM!H103,MARKETING!H103,COMERCIAL!H103,OPERAÇÕES!H103,'FAVELA 3D'!H103) -> 250 | I103: =SUM(ADM!I103,MARKETING!I103,COMERCIAL!I103,OPERAÇÕES!I103,'FAVELA 3D'!I103) -> 250 | J103: =SUM(ADM!J103,MARKETING!J103,COMERCIAL!J103,OPERAÇÕES!J103,'FAVELA 3D'!J103) -> 250 | ... N103: =SUM(ADM!N103,MARKETING!N103,COMERCIAL!N103,OPERAÇÕES!N103,'FAVELA 3D'!N103) -> 250 | O103: =SUM(C103:N103) -> 3000
B104: Despesas Bancárias | C104: =SUM(ADM!C104,MARKETING!C104,COMERCIAL!C104,OPERAÇÕES!C104,'FAVELA 3D'!C104) -> 0 | D104: =SUM(ADM!D104,MARKETING!D104,COMERCIAL!D104,OPERAÇÕES!D104,'FAVELA 3D'!D104) -> 0 | E104: =SUM(ADM!E104,MARKETING!E104,COMERCIAL!E104,OPERAÇÕES!E104,'FAVELA 3D'!E104) -> 0 | F104: =SUM(ADM!F104,MARKETING!F104,COMERCIAL!F104,OPERAÇÕES!F104,'FAVELA 3D'!F104) -> 0 | G104: =SUM(ADM!G104,MARKETING!G104,COMERCIAL!G104,OPERAÇÕES!G104,'FAVELA 3D'!G104) -> 0 | H104: =SUM(ADM!H104,MARKETING!H104,COMERCIAL!H104,OPERAÇÕES!H104,'FAVELA 3D'!H104) -> 0 | I104: =SUM(ADM!I104,MARKETING!I104,COMERCIAL!I104,OPERAÇÕES!I104,'FAVELA 3D'!I104) -> 0 | J104: =SUM(ADM!J104,MARKETING!J104,COMERCIAL!J104,OPERAÇÕES!J104,'FAVELA 3D'!J104) -> 0 | ... N104: =SUM(ADM!N104,MARKETING!N104,COMERCIAL!N104,OPERAÇÕES!N104,'FAVELA 3D'!N104) -> 0 | O104: =SUM(C104:N104) -> 0
B105: Impostos e Taxas | C105: =SUM(C106:C115) -> 100 | D105: =SUM(D106:D115) -> 100 | E105: =SUM(E106:E115) -> 2000 | F105: =SUM(F106:F115) -> 100 | G105: =SUM(G106:G115) -> 100 | H105: =SUM(H106:H115) -> 100 | I105: =SUM(I106:I115) -> 100 | J105: =SUM(J106:J115) -> 100 | ... N105: =SUM(N106:N115) -> 100 | O105: =SUM(C105:N105) -> 3300
B106: ICMS | C106: =SUM(ADM!C106,MARKETING!C106,COMERCIAL!C106,OPERAÇÕES!C106,'FAVELA 3D'!C106) -> 0 | D106: =SUM(ADM!D106,MARKETING!D106,COMERCIAL!D106,OPERAÇÕES!D106,'FAVELA 3D'!D106) -> 0 | E106: =SUM(ADM!E106,MARKETING!E106,COMERCIAL!E106,OPERAÇÕES!E106,'FAVELA 3D'!E106) -> 0 | F106: =SUM(ADM!F106,MARKETING!F106,COMERCIAL!F106,OPERAÇÕES!F106,'FAVELA 3D'!F106) -> 0 | G106: =SUM(ADM!G106,MARKETING!G106,COMERCIAL!G106,OPERAÇÕES!G106,'FAVELA 3D'!G106) -> 0 | H106: =SUM(ADM!H106,MARKETING!H106,COMERCIAL!H106,OPERAÇÕES!H106,'FAVELA 3D'!H106) -> 0 | I106: =SUM(ADM!I106,MARKETING!I106,COMERCIAL!I106,OPERAÇÕES!I106,'FAVELA 3D'!I106) -> 0 | J106: =SUM(ADM!J106,MARKETING!J106,COMERCIAL!J106,OPERAÇÕES!J106,'FAVELA 3D'!J106) -> 0 | ... N106: =SUM(ADM!N106,MARKETING!N106,COMERCIAL!N106,OPERAÇÕES!N106,'FAVELA 3D'!N106) -> 0 | O106: =SUM(C106:N106) -> 0
B107: IPI | C107: =SUM(ADM!C107,MARKETING!C107,COMERCIAL!C107,OPERAÇÕES!C107,'FAVELA 3D'!C107) -> 0 | D107: =SUM(ADM!D107,MARKETING!D107,COMERCIAL!D107,OPERAÇÕES!D107,'FAVELA 3D'!D107) -> 0 | E107: =SUM(ADM!E107,MARKETING!E107,COMERCIAL!E107,OPERAÇÕES!E107,'FAVELA 3D'!E107) -> 0 | F107: =SUM(ADM!F107,MARKETING!F107,COMERCIAL!F107,OPERAÇÕES!F107,'FAVELA 3D'!F107) -> 0 | G107: =SUM(ADM!G107,MARKETING!G107,COMERCIAL!G107,OPERAÇÕES!G107,'FAVELA 3D'!G107) -> 0 | H107: =SUM(ADM!H107,MARKETING!H107,COMERCIAL!H107,OPERAÇÕES!H107,'FAVELA 3D'!H107) -> 0 | I107: =SUM(ADM!I107,MARKETING!I107,COMERCIAL!I107,OPERAÇÕES!I107,'FAVELA 3D'!I107) -> 0 | J107: =SUM(ADM!J107,MARKETING!J107,COMERCIAL!J107,OPERAÇÕES!J107,'FAVELA 3D'!J107) -> 0 | ... N107: =SUM(ADM!N107,MARKETING!N107,COMERCIAL!N107,OPERAÇÕES!N107,'FAVELA 3D'!N107) -> 0 | O107: =SUM(C107:N107) -> 0
B108: PIS | C108: =SUM(ADM!C108,MARKETING!C108,COMERCIAL!C108,OPERAÇÕES!C108,'FAVELA 3D'!C108) -> 0 | D108: =SUM(ADM!D108,MARKETING!D108,COMERCIAL!D108,OPERAÇÕES!D108,'FAVELA 3D'!D108) -> 0 | E108: =SUM(ADM!E108,MARKETING!E108,COMERCIAL!E108,OPERAÇÕES!E108,'FAVELA 3D'!E108) -> 0 | F108: =SUM(ADM!F108,MARKETING!F108,COMERCIAL!F108,OPERAÇÕES!F108,'FAVELA 3D'!F108) -> 0 | G108: =SUM(ADM!G108,MARKETING!G108,COMERCIAL!G108,OPERAÇÕES!G108,'FAVELA 3D'!G108) -> 0 | H108: =SUM(ADM!H108,MARKETING!H108,COMERCIAL!H108,OPERAÇÕES!H108,'FAVELA 3D'!H108) -> 0 | I108: =SUM(ADM!I108,MARKETING!I108,COMERCIAL!I108,OPERAÇÕES!I108,'FAVELA 3D'!I108) -> 0 | J108: =SUM(ADM!J108,MARKETING!J108,COMERCIAL!J108,OPERAÇÕES!J108,'FAVELA 3D'!J108) -> 0 | ... N108: =SUM(ADM!N108,MARKETING!N108,COMERCIAL!N108,OPERAÇÕES!N108,'FAVELA 3D'!N108) -> 0 | O108: =SUM(C108:N108) -> 0
B109: COFINS | C109: =SUM(ADM!C109,MARKETING!C109,COMERCIAL!C109,OPERAÇÕES!C109,'FAVELA 3D'!C109) -> 0 | D109: =SUM(ADM!D109,MARKETING!D109,COMERCIAL!D109,OPERAÇÕES!D109,'FAVELA 3D'!D109) -> 0 | E109: =SUM(ADM!E109,MARKETING!E109,COMERCIAL!E109,OPERAÇÕES!E109,'FAVELA 3D'!E109) -> 0 | F109: =SUM(ADM!F109,MARKETING!F109,COMERCIAL!F109,OPERAÇÕES!F109,'FAVELA 3D'!F109) -> 0 | G109: =SUM(ADM!G109,MARKETING!G109,COMERCIAL!G109,OPERAÇÕES!G109,'FAVELA 3D'!G109) -> 0 | H109: =SUM(ADM!H109,MARKETING!H109,COMERCIAL!H109,OPERAÇÕES!H109,'FAVELA 3D'!H109) -> 0 | I109: =SUM(ADM!I109,MARKETING!I109,COMERCIAL!I109,OPERAÇÕES!I109,'FAVELA 3D'!I109) -> 0 | J109: =SUM(ADM!J109,MARKETING!J109,COMERCIAL!J109,OPERAÇÕES!J109,'FAVELA 3D'!J109) -> 0 | ... N109: =SUM(ADM!N109,MARKETING!N109,COMERCIAL!N109,OPERAÇÕES!N109,'FAVELA 3D'!N109) -> 0 | O109: =SUM(C109:N109) -> 0
B110: IRPJ | C110: =SUM(ADM!C110,MARKETING!C110,COMERCIAL!C110,OPERAÇÕES!C110,'FAVELA 3D'!C110) -> 0 | D110: =SUM(ADM!D110,MARKETING!D110,COMERCIAL!D110,OPERAÇÕES!D110,'FAVELA 3D'!D110) -> 0 | E110: =SUM(ADM!E110,MARKETING!E110,COMERCIAL!E110,OPERAÇÕES!E110,'FAVELA 3D'!E110) -> 0 | F110: =SUM(ADM!F110,MARKETING!F110,COMERCIAL!F110,OPERAÇÕES!F110,'FAVELA 3D'!F110) -> 0 | G110: =SUM(ADM!G110,MARKETING!G110,COMERCIAL!G110,OPERAÇÕES!G110,'FAVELA 3D'!G110) -> 0 | H110: =SUM(ADM!H110,MARKETING!H110,COMERCIAL!H110,OPERAÇÕES!H110,'FAVELA 3D'!H110) -> 0 | I110: =SUM(ADM!I110,MARKETING!I110,COMERCIAL!I110,OPERAÇÕES!I110,'FAVELA 3D'!I110) -> 0 | J110: =SUM(ADM!J110,MARKETING!J110,COMERCIAL!J110,OPERAÇÕES!J110,'FAVELA 3D'!J110) -> 0 | ... N110: =SUM(ADM!N110,MARKETING!N110,COMERCIAL!N110,OPERAÇÕES!N110,'FAVELA 3D'!N110) -> 0 | O110: =SUM(C110:N110) -> 0
B111: Contribuição Social | C111: =SUM(ADM!C111,MARKETING!C111,COMERCIAL!C111,OPERAÇÕES!C111,'FAVELA 3D'!C111) -> 0 | D111: =SUM(ADM!D111,MARKETING!D111,COMERCIAL!D111,OPERAÇÕES!D111,'FAVELA 3D'!D111) -> 0 | E111: =SUM(ADM!E111,MARKETING!E111,COMERCIAL!E111,OPERAÇÕES!E111,'FAVELA 3D'!E111) -> 0 | F111: =SUM(ADM!F111,MARKETING!F111,COMERCIAL!F111,OPERAÇÕES!F111,'FAVELA 3D'!F111) -> 0 | G111: =SUM(ADM!G111,MARKETING!G111,COMERCIAL!G111,OPERAÇÕES!G111,'FAVELA 3D'!G111) -> 0 | H111: =SUM(ADM!H111,MARKETING!H111,COMERCIAL!H111,OPERAÇÕES!H111,'FAVELA 3D'!H111) -> 0 | I111: =SUM(ADM!I111,MARKETING!I111,COMERCIAL!I111,OPERAÇÕES!I111,'FAVELA 3D'!I111) -> 0 | J111: =SUM(ADM!J111,MARKETING!J111,COMERCIAL!J111,OPERAÇÕES!J111,'FAVELA 3D'!J111) -> 0 | ... N111: =SUM(ADM!N111,MARKETING!N111,COMERCIAL!N111,OPERAÇÕES!N111,'FAVELA 3D'!N111) -> 0 | O111: =SUM(C111:N111) -> 0
B112: ISS | C112: =SUM(ADM!C112,MARKETING!C112,COMERCIAL!C112,OPERAÇÕES!C112,'FAVELA 3D'!C112) -> 0 | D112: =SUM(ADM!D112,MARKETING!D112,COMERCIAL!D112,OPERAÇÕES!D112,'FAVELA 3D'!D112) -> 0 | E112: =SUM(ADM!E112,MARKETING!E112,COMERCIAL!E112,OPERAÇÕES!E112,'FAVELA 3D'!E112) -> 0 | F112: =SUM(ADM!F112,MARKETING!F112,COMERCIAL!F112,OPERAÇÕES!F112,'FAVELA 3D'!F112) -> 0 | G112: =SUM(ADM!G112,MARKETING!G112,COMERCIAL!G112,OPERAÇÕES!G112,'FAVELA 3D'!G112) -> 0 | H112: =SUM(ADM!H112,MARKETING!H112,COMERCIAL!H112,OPERAÇÕES!H112,'FAVELA 3D'!H112) -> 0 | I112: =SUM(ADM!I112,MARKETING!I112,COMERCIAL!I112,OPERAÇÕES!I112,'FAVELA 3D'!I112) -> 0 | J112: =SUM(ADM!J112,MARKETING!J112,COMERCIAL!J112,OPERAÇÕES!J112,'FAVELA 3D'!J112) -> 0 | ... N112: =SUM(ADM!N112,MARKETING!N112,COMERCIAL!N112,OPERAÇÕES!N112,'FAVELA 3D'!N112) -> 0 | O112: =SUM(C112:N112) -> 0
B113: Simples Nacional (DAS) | C113: =SUM(ADM!C113,MARKETING!C113,COMERCIAL!C113,OPERAÇÕES!C113,'FAVELA 3D'!C113) -> 0 | D113: =SUM(ADM!D113,MARKETING!D113,COMERCIAL!D113,OPERAÇÕES!D113,'FAVELA 3D'!D113) -> 0 | E113: =SUM(ADM!E113,MARKETING!E113,COMERCIAL!E113,OPERAÇÕES!E113,'FAVELA 3D'!E113) -> 0 | F113: =SUM(ADM!F113,MARKETING!F113,COMERCIAL!F113,OPERAÇÕES!F113,'FAVELA 3D'!F113) -> 0 | G113: =SUM(ADM!G113,MARKETING!G113,COMERCIAL!G113,OPERAÇÕES!G113,'FAVELA 3D'!G113) -> 0 | H113: =SUM(ADM!H113,MARKETING!H113,COMERCIAL!H113,OPERAÇÕES!H113,'FAVELA 3D'!H113) -> 0 | I113: =SUM(ADM!I113,MARKETING!I113,COMERCIAL!I113,OPERAÇÕES!I113,'FAVELA 3D'!I113) -> 0 | J113: =SUM(ADM!J113,MARKETING!J113,COMERCIAL!J113,OPERAÇÕES!J113,'FAVELA 3D'!J113) -> 0 | ... N113: =SUM(ADM!N113,MARKETING!N113,COMERCIAL!N113,OPERAÇÕES!N113,'FAVELA 3D'!N113) -> 0 | O113: =SUM(C113:N113) -> 0
B114: IMPOSTOS/TAXAS | C114: =SUM(ADM!C114,MARKETING!C114,COMERCIAL!C114,OPERAÇÕES!C114,'FAVELA 3D'!C114) -> 100 | D114: =SUM(ADM!D114,MARKETING!D114,COMERCIAL!D114,OPERAÇÕES!D114,'FAVELA 3D'!D114) -> 100 | E114: =SUM(ADM!E114,MARKETING!E114,COMERCIAL!E114,OPERAÇÕES!E114,'FAVELA 3D'!E114) -> 2000 | F114: =SUM(ADM!F114,MARKETING!F114,COMERCIAL!F114,OPERAÇÕES!F114,'FAVELA 3D'!F114) -> 100 | G114: =SUM(ADM!G114,MARKETING!G114,COMERCIAL!G114,OPERAÇÕES!G114,'FAVELA 3D'!G114) -> 100 | H114: =SUM(ADM!H114,MARKETING!H114,COMERCIAL!H114,OPERAÇÕES!H114,'FAVELA 3D'!H114) -> 100 | I114: =SUM(ADM!I114,MARKETING!I114,COMERCIAL!I114,OPERAÇÕES!I114,'FAVELA 3D'!I114) -> 100 | J114: =SUM(ADM!J114,MARKETING!J114,COMERCIAL!J114,OPERAÇÕES!J114,'FAVELA 3D'!J114) -> 100 | ... N114: =SUM(ADM!N114,MARKETING!N114,COMERCIAL!N114,OPERAÇÕES!N114,'FAVELA 3D'!N114) -> 100 | O114: =SUM(C114:N114) -> 3300
B115: IOF | C115: =SUM(ADM!C115,MARKETING!C115,COMERCIAL!C115,OPERAÇÕES!C115,'FAVELA 3D'!C115) -> 0 | D115: =SUM(ADM!D115,MARKETING!D115,COMERCIAL!D115,OPERAÇÕES!D115,'FAVELA 3D'!D115) -> 0 | E115: =SUM(ADM!E115,MARKETING!E115,COMERCIAL!E115,OPERAÇÕES!E115,'FAVELA 3D'!E115) -> 0 | F115: =SUM(ADM!F115,MARKETING!F115,COMERCIAL!F115,OPERAÇÕES!F115,'FAVELA 3D'!F115) -> 0 | G115: =SUM(ADM!G115,MARKETING!G115,COMERCIAL!G115,OPERAÇÕES!G115,'FAVELA 3D'!G115) -> 0 | H115: =SUM(ADM!H115,MARKETING!H115,COMERCIAL!H115,OPERAÇÕES!H115,'FAVELA 3D'!H115) -> 0 | I115: =SUM(ADM!I115,MARKETING!I115,COMERCIAL!I115,OPERAÇÕES!I115,'FAVELA 3D'!I115) -> 0 | J115: =SUM(ADM!J115,MARKETING!J115,COMERCIAL!J115,OPERAÇÕES!J115,'FAVELA 3D'!J115) -> 0 | ... N115: =SUM(ADM!N115,MARKETING!N115,COMERCIAL!N115,OPERAÇÕES!N115,'FAVELA 3D'!N115) -> 0 | O115: =SUM(C115:N115) -> 0
B116: Investimento | C116: =SUM(C117:C119) -> 750 | D116: =SUM(D117:D119) -> 50250 | E116: =SUM(E117:E119) -> 750 | F116: =SUM(F117:F119) -> 750 | G116: =SUM(G117:G119) -> 750 | H116: =SUM(H117:H119) -> 750 | I116: =SUM(I117:I119) -> 750 | J116: =SUM(J117:J119) -> 750 | ... N116: =SUM(N117:N119) -> 750 | O116: =SUM(C116:N116) -> 58500
B117: Equipamentos de Informática | C117: =SUM(ADM!C117,MARKETING!C117,COMERCIAL!C117,OPERAÇÕES!C117,'FAVELA 3D'!C117) -> 150 | D117: =SUM(ADM!D117,MARKETING!D117,COMERCIAL!D117,OPERAÇÕES!D117,'FAVELA 3D'!D117) -> 750 | E117: =SUM(ADM!E117,MARKETING!E117,COMERCIAL!E117,OPERAÇÕES!E117,'FAVELA 3D'!E117) -> 150 | F117: =SUM(ADM!F117,MARKETING!F117,COMERCIAL!F117,OPERAÇÕES!F117,'FAVELA 3D'!F117) -> 150 | G117: =SUM(ADM!G117,MARKETING!G117,COMERCIAL!G117,OPERAÇÕES!G117,'FAVELA 3D'!G117) -> 150 | H117: =SUM(ADM!H117,MARKETING!H117,COMERCIAL!H117,OPERAÇÕES!H117,'FAVELA 3D'!H117) -> 150 | I117: =SUM(ADM!I117,MARKETING!I117,COMERCIAL!I117,OPERAÇÕES!I117,'FAVELA 3D'!I117) -> 150 | J117: =SUM(ADM!J117,MARKETING!J117,COMERCIAL!J117,OPERAÇÕES!J117,'FAVELA 3D'!J117) -> 150 | ... N117: =SUM(ADM!N117,MARKETING!N117,COMERCIAL!N117,OPERAÇÕES!N117,'FAVELA 3D'!N117) -> 150 | O117: =SUM(C117:N117) -> 2400
B118: Móveis e Utensílios | C118: =SUM(ADM!C118,MARKETING!C118,COMERCIAL!C118,OPERAÇÕES!C118,'FAVELA 3D'!C118) -> 200 | D118: =SUM(ADM!D118,MARKETING!D118,COMERCIAL!D118,OPERAÇÕES!D118,'FAVELA 3D'!D118) -> 11600 | E118: =SUM(ADM!E118,MARKETING!E118,COMERCIAL!E118,OPERAÇÕES!E118,'FAVELA 3D'!E118) -> 200 | F118: =SUM(ADM!F118,MARKETING!F118,COMERCIAL!F118,OPERAÇÕES!F118,'FAVELA 3D'!F118) -> 200 | G118: =SUM(ADM!G118,MARKETING!G118,COMERCIAL!G118,OPERAÇÕES!G118,'FAVELA 3D'!G118) -> 200 | H118: =SUM(ADM!H118,MARKETING!H118,COMERCIAL!H118,OPERAÇÕES!H118,'FAVELA 3D'!H118) -> 200 | I118: =SUM(ADM!I118,MARKETING!I118,COMERCIAL!I118,OPERAÇÕES!I118,'FAVELA 3D'!I118) -> 200 | J118: =SUM(ADM!J118,MARKETING!J118,COMERCIAL!J118,OPERAÇÕES!J118,'FAVELA 3D'!J118) -> 200 | ... N118: =SUM(ADM!N118,MARKETING!N118,COMERCIAL!N118,OPERAÇÕES!N118,'FAVELA 3D'!N118) -> 200 | O118: =SUM(C118:N118) -> 13800
B119: Maq./Equipamentos | C119: =SUM(ADM!C119,MARKETING!C119,COMERCIAL!C119,OPERAÇÕES!C119,'FAVELA 3D'!C119) -> 400 | D119: =SUM(ADM!D119,MARKETING!D119,COMERCIAL!D119,OPERAÇÕES!D119,'FAVELA 3D'!D119) -> 37900 | E119: =SUM(ADM!E119,MARKETING!E119,COMERCIAL!E119,OPERAÇÕES!E119,'FAVELA 3D'!E119) -> 400 | F119: =SUM(ADM!F119,MARKETING!F119,COMERCIAL!F119,OPERAÇÕES!F119,'FAVELA 3D'!F119) -> 400 | G119: =SUM(ADM!G119,MARKETING!G119,COMERCIAL!G119,OPERAÇÕES!G119,'FAVELA 3D'!G119) -> 400 | H119: =SUM(ADM!H119,MARKETING!H119,COMERCIAL!H119,OPERAÇÕES!H119,'FAVELA 3D'!H119) -> 400 | I119: =SUM(ADM!I119,MARKETING!I119,COMERCIAL!I119,OPERAÇÕES!I119,'FAVELA 3D'!I119) -> 400 | J119: =SUM(ADM!J119,MARKETING!J119,COMERCIAL!J119,OPERAÇÕES!J119,'FAVELA 3D'!J119) -> 400 | ... N119: =SUM(ADM!N119,MARKETING!N119,COMERCIAL!N119,OPERAÇÕES!N119,'FAVELA 3D'!N119) -> 400 | O119: =SUM(C119:N119) -> 42300
B120: Outras Despesas | C120: =SUM(ADM!C120,MARKETING!C120,COMERCIAL!C120,OPERAÇÕES!C120,'FAVELA 3D'!C120) -> 0 | D120: =SUM(D121:D122) -> 0 | E120: =SUM(E121:E122) -> 0 | F120: =SUM(F121:F122) -> 0 | G120: =SUM(G121:G122) -> 0 | H120: =SUM(H121:H122) -> 0 | I120: =SUM(I121:I122) -> 0 | J120: =SUM(J121:J122) -> 0 | K120: =SUM(K121:K122) -> 0 | ... N120: =SUM(N121:N122) -> 0 | O120: =SUM(C120:N120) -> 0
...

Sheet ADM
C1: INSTITUTO DE CAPACITACAO E ACAO SOCIAL O GRITO - PLANEJAMENTO 2025 - ADM
C2: =C47/O$47 -> 0.085499091 | D2: =D47/$O$47 -> 0.078884945 | E2: =E47/$O$47 -> 0.082382478 | F2: =F47/$O$47 -> 0.08338672 | G2: =G47/$O$47 -> 0.079092719 | H2: =H47/$O$47 -> 0.078884945 | I2: =I47/$O$47 -> 0.081516752 | J2: =J47/$O$47 -> 0.10719418 | K2: =K47/$O$47 -> 0.079767985 | ... N2: =N47/$O$47 -> 0.080425937
B3: CATEGORIA | C3: JANEIRO | D3: FEVEREIRO | E3: MARÇO | F3: ABRIL | G3: MAIO | H3: JUNHO | I3: JULHO | J3: AGOSTO | K3: SETEMBRO | L3: OUTUBRO | M3: NOVEMBRO | N3: DEZEMBRO | O3: TOTAL
B5: SALDO ACUMULADO | C5: =C6 -> -28880 | D5: =C5+D6 -> -53940 | E5: =D5+E6 -> -83120 | F5: =E5+F6 -> -114780 | G5: =F5+G6 -> -144060 | H5: =G5+H6 -> -173915 | I5: =H5+I6 -> -205455 | J5: =I5+J6 -> -251825 | K5: =J5+K6 -> -279395 | ... N5: =M5+N6 -> -388465
B6: SALDO MÊS | C6: =SUM(C8-C47) -> -28880 | D6: =SUM(D8-D47) -> -25060 | E6: =SUM(E8-E47) -> -29180 | F6: =SUM(F8-F47) -> -31660 | G6: =SUM(G8-G47) -> -29280 | H6: =SUM(H8-H47) -> -29855 | I6: =SUM(I8-I47) -> -31540 | J6: =SUM(J8-J47) -> -46370 | ... N6: =SUM(N8-N47) -> -35950 | O6: =SUM(C6:N6) -> -388465
B8: RECEITAS | C8: =SUM(C9,C16,C22,C28,C33,C37,C40,C43) -> 20500 | D8: =SUM(D9,D16,D22,D28,D33,D37,D40,D43) -> 20500 | E8: =SUM(E9,E16,E22,E28,E33,E37,E40,E43) -> 18400 | F8: =SUM(F9,F16,F22,F28,F33,F37,F40,F43) -> 16500 | G8: =SUM(G9,G16,G22,G28,G33,G37,G40,G43) -> 16400 | H8: =SUM(H9,H16,H22,H28,H33,H37,H40,H43) -> 15705 | I8: =SUM(I9,I16,I22,I28,I33,I37,I40,I43) -> 15540 | J8: =SUM(J9,J16,J22,J28,J33,J37,J40,J43) -> 15540 | ... N8: =SUM(N9,N16,N22,N28,N33,N37,N40,N43) -> 10500 | O8: =SUM(C8:N8) -> 181085
B9: Devoluções | C9: =SUM(C10:C15) -> 0 | D9: =SUM(D10:D15) -> 0 | E9: =SUM(E10:E15) -> 0 | F9: =SUM(F10:F15) -> 0 | G9: =SUM(G10:G15) -> 0 | H9: =SUM(H10:H15) -> 0 | I9: =SUM(I10:I15) -> 0 | J9: =SUM(J10:J15) -> 0 | ... N9: =SUM(N10:N15) -> 0 | O9: =SUM(C9:N9) -> 0
B10: Devoluções Compra Mercadoria Revenda | C10: 0 | D10: 0 | E10: 0 | F10: 0 | G10: 0 | H10: 0 | I10: 0 | J10: 0 | K10: 0 | L10: 0 | M10: 0 | N10: 0 | O10: =SUM(C10:N10) -> 0
B11: Devoluções de Compra Material Consumo | C11: 0 | D11: 0 | E11: 0 | F11: 0 | G11: 0 | H11: 0 | I11: 0 | J11: 0 | K11: 0 | L11: 0 | M11: 0 | N11: 0 | O11: =SUM(C11:N11) -> 0
B12: Devoluções de Compra de Matéria Prima | C12: 0 | D12: 0 | E12: 0 | F12: 0 | G12: 0 | H12: 0 | I12: 0 | J12: 0 | K12: 0 | L12: 0 | M12: 0 | N12: 0 | O12: =SUM(C12:N12) -> 0
B13: Devoluções de Compra de Ativo | C13: 0 | D13: 0 | E13: 0 | F13: 0 | G13: 0 | H13: 0 | I13: 0 | J13: 0 | K13: 0 | L13: 0 | M13: 0 | N13: 0 | O13: =SUM(C13:N13) -> 0
B14: Devoluções de Compra de Serviços | C14: 0 | D14: 0 | E14: 0 | F14: 0 | G14: 0 | H14: 0 | I14: 0 | J14: 0 | K14: 0 | L14: 0 | M14: 0 | N14: 0 | O14: =SUM(C14:N14) -> 0
B15: Devolução de Doações | C15: 0 | D15: 0 | E15: 0 | F15: 0 | G15: 0 | H15: 0 | I15: 0 | J15: 0 | K15: 0 | L15: 0 | M15: 0 | N15: 0 | O15: =SUM(C15:N15) -> 0
B16: Outras Entradas | C16: =SUM(C17:C21) -> 0 | D16: =SUM(D17:D21) -> 0 | E16: =SUM(E17:E21) -> 0 | F16: =SUM(F17:F21) -> 0 | G16: =SUM(G17:G21) -> 0 | H16: =SUM(H17:H21) -> 0 | I16: =SUM(I17:I21) -> 0 | J16: =SUM(J17:J21) -> 0 | ... N16: =SUM(N17:N21) -> 0 | O16: =SUM(C16:N16) -> 0
B17: Empréstimos Bancários | C17: 0 | D17: 0 | E17: 0 | F17: 0 | G17: 0 | H17: 0 | I17: 0 | J17: 0 | K17: 0 | L17: 0 | M17: 0 | N17: 0 | O17: =SUM(C17:N17) -> 0
B18: Aumento de Capital | C18: 0 | D18: 0 | E18: 0 | F18: 0 | G18: 0 | H18: 0 | I18: 0 | J18: 0 | K18: 0 | L18: 0 | M18: 0 | N18: 0 | O18: =SUM(C18:N18) -> 0
B19: Venda de Ativos | C19: 0 | D19: 0 | E19: 0 | F19: 0 | G19: 0 | H19: 0 | I19: 0 | J19: 0 | K19: 0 | L19: 0 | M19: 0 | N19: 0 | O19: =SUM(C19:N19) -> 0
B20: AJUSTE DE CAIXA | C20: 0 | D20: 0 | E20: 0 | F20: 0 | G20: 0 | H20: 0 | I20: 0 | J20: 0 | K20: 0 | L20: 0 | M20: 0 | N20: 0 | O20: =SUM(C20:N20) -> 0
B21: Prêmios de Seguros / Sinistros | C21: 0 | D21: 0 | E21: 0 | F21: 0 | G21: 0 | H21: 0 | I21: 0 | J21: 0 | K21: 0 | L21: 0 | M21: 0 | N21: 0 | O21: =SUM(C21:N21) -> 0
B22: Doações | C22: =SUM(C23:C27) -> 5500 | D22: =SUM(D23:D27) -> 5500 | E22: =SUM(E23:E27) -> 5500 | F22: =SUM(F23:F27) -> 5500 | G22: =SUM(G23:G27) -> 5500 | H22: =SUM(H23:H27) -> 5500 | I22: =SUM(I23:I27) -> 5500 | J22: =SUM(J23:J27) -> 5500 | ... N22: =SUM(N23:N27) -> 5500 | O22: =SUM(C22:N22) -> 66000
B23: Doações Recorrentes | C23: 2500 | D23: 2500 | E23: 2500 | F23: 2500 | G23: 2500 | H23: 2500 | I23: 2500 | J23: 2500 | K23: 2500 | L23: 2500 | M23: 2500 | N23: 2500 | O23: =SUM(C23:N23) -> 30000
B24: Doações Pontuais PF | C24: 0 | D24: 0 | E24: 0 | F24: 0 | G24: 0 | H24: 0 | I24: 0 | J24: 0 | K24: 0 | L24: 0 | M24: 0 | N24: 0 | O24: =SUM(C24:N24) -> 0
B25: Doações Pontuais PJ | C25: 0 | D25: 0 | E25: 0 | F25: 0 | G25: 0 | H25: 0 | I25: 0 | J25: 0 | K25: 0 | L25: 0 | M25: 0 | N25: 0 | O25: =SUM(C25:N25) -> 0
B26: Doador Anjo | C26: 3000 | D26: 3000 | E26: 3000 | F26: 3000 | G26: 3000 | H26: 3000 | I26: 3000 | J26: 3000 | K26: 3000 | L26: 3000 | M26: 3000 | N26: 3000 | O26: =SUM(C26:N26) -> 36000
B27: Patrocínios | C27: 0 | D27: 0 | E27: 0 | F27: 0 | G27: 0 | H27: 0 | I27: 0 | J27: 0 | K27: 0 | L27: 0 | M27: 0 | N27: 0 | O27: =SUM(C27:N27) -> 0
B28: Gerando Falcões | C28: =SUM(C29:C32) -> 0 | D28: =SUM(D29:D32) -> 0 | E28: =SUM(E29:E32) -> 0 | F28: =SUM(F29:F32) -> 0 | G28: =SUM(G29:G32) -> 0 | H28: =SUM(H29:H32) -> 0 | I28: =SUM(I29:I32) -> 0 | J28: =SUM(J29:J32) -> 0 | ... N28: =SUM(N29:N32) -> 0 | O28: =SUM(C28:N28) -> 0
B29: Aporte | C29: 0 | D29: 0 | E29: 0 | F29: 0 | G29: 0 | H29: 0 | I29: 0 | J29: 0 | K29: 0 | L29: 0 | M29: 0 | N29: 0 | O29: =SUM(C29:N29) -> 0
B30: Falcons Univercity | C30: 0 | D30: 0 | E30: 0 | F30: 0 | G30: 0 | H30: 0 | I30: 0 | J30: 0 | K30: 0 | L30: 0 | M30: 0 | N30: 0 | O30: =SUM(C30:N30) -> 0
B31: Regional GF | C31: 0 | D31: 0 | E31: 0 | F31: 0 | G31: 0 | H31: 0 | I31: 0 | J31: 0 | K31: 0 | L31: 0 | M31: 0 | N31: 0 | O31: =SUM(C31:N31) -> 0
B32: Favela 3D | C32: 0 | D32: 0 | E32: 0 | F32: 0 | G32: 0 | H32: 0 | I32: 0 | J32: 0 | K32: 0 | L32: 0 | M32: 0 | N32: 0 | O32: =SUM(C32:N32) -> 0
B33: Editais/Projetos | C33: =SUM(C34:C36) -> 0 | D33: =SUM(D34:D36) -> 0 | E33: =SUM(E34:E36) -> 0 | F33: =SUM(F34:F36) -> 0 | G33: =SUM(G34:G36) -> 0 | H33: =SUM(H34:H36) -> 0 | I33: =SUM(I34:I36) -> 0 | J33: =SUM(J34:J36) -> 0 | ... N33: =SUM(N34:N36) -> 0 | O33: =SUM(C33:N33) -> 0
B34: Ecogaiola | C34: 0 | D34: 0 | E34: 0 | F34: 0 | G34: 0 | H34: 0 | I34: 0 | J34: 0 | K34: 0 | L34: 0 | M34: 0 | N34: 0 | O34: =SUM(C34:N34) -> 0
B35: Prog. Hab. Polaris | C35: 0 | D35: 0 | E35: 0 | F35: 0 | G35: 0 | H35: 0 | I35: 0 | J35: 0 | K35: 0 | L35: 0 | M35: 0 | N35: 0 | O35: =SUM(C35:N35) -> 0
B36: Lei De Incentivo | C36: 0 | D36: 0 | E36: 0 | F36: 0 | G36: 0 | H36: 0 | I36: 0 | J36: 0 | K36: 0 | L36: 0 | M36: 0 | N36: 0 | O36: =SUM(C36:N36) -> 0
B37: Negócios Sociais | C37: =SUM(C38:C39) -> 0 | D37: =SUM(D38:D39) -> 0 | E37: =SUM(E38:E39) -> 0 | F37: =SUM(F38:F39) -> 0 | G37: =SUM(G38:G39) -> 0 | H37: =SUM(H38:H39) -> 0 | I37: =SUM(I38:I39) -> 0 | J37: =SUM(J38:J39) -> 0 | ... N37: =SUM(N38:N39) -> 0 | O37: =SUM(C37:N37) -> 0
B38: Vendas Outlet | C38: 0 | D38: 0 | E38: 0 | F38: 0 | G38: 0 | H38: 0 | I38: 0 | J38: 0 | K38: 0 | L38: 0 | M38: 0 | N38: 0 | O38: =SUM(C38:N38) -> 0
B39: Vendas Griffte | C39: 0 | D39: 0 | E39: 0 | F39: 0 | G39: 0 | H39: 0 | I39: 0 | J39: 0 | K39: 0 | L39: 0 | M39: 0 | N39: 0 | O39: =SUM(C39:N39) -> 0
B40: Eventos | C40: =SUM(C41:C42) -> 10000 | D40: =SUM(D41:D42) -> 10000 | E40: =SUM(E41:E42) -> 7900 | F40: =SUM(F41:F42) -> 6000 | G40: =SUM(G41:G42) -> 5900 | H40: =SUM(H41:H42) -> 5205 | I40: =SUM(I41:I42) -> 5040 | J40: =SUM(J41:J42) -> 5040 | ... N40: =SUM(N41:N42) -> 0 | O40: =SUM(C40:N40) -> 63085
B41: Clube do Grito 2024 (Cartões) | C41: 10000 | D41: 10000 | E41: 7900 | F41: 6000 | G41: 5900 | H41: 5205 | I41: 5040 | J41: 5040 | K41: =SUM(ADM!K41,MARKETING!K41,COMERCIAL!K41,OPERAÇÕES!K41) -> 0 | L41: =SUM(ADM!L41,MARKETING!L41,COMERCIAL!L41,OPERAÇÕES!L41) -> 0 | M41: =SUM(ADM!M41,MARKETING!M41,COMERCIAL!M41,OPERAÇÕES!M41) -> 0 | N41: =SUM(ADM!N41,MARKETING!N41,COMERCIAL!N41,OPERAÇÕES!N41) -> 0 | O41: =SUM(C41:N41) -> 63085
B42: Crowdfunding | C42: 0 | D42: 0 | E42: 0 | F42: 0 | G42: 0 | H42: 0 | I42: 0 | J42: 0 | K42: 0 | L42: 0 | M42: 0 | N42: 0 | O42: =SUM(C42:N42) -> 0
B43: Aplicações | C43: =SUM(C44:C46) -> 5000 | D43: =SUM(D44:D46) -> 5000 | E43: =SUM(E44:E46) -> 5000 | F43: =SUM(F44:F46) -> 5000 | G43: =SUM(G44:G46) -> 5000 | H43: =SUM(H44:H46) -> 5000 | I43: =SUM(I44:I46) -> 5000 | J43: =SUM(J44:J46) -> 5000 | ... N43: =SUM(N44:N46) -> 5000 | O43: =SUM(C43:N43) -> 60000
B44: Resgate Aplicações (Clube Grito 24) | C44: 0 | D44: 0 | E44: 0 | F44: 0 | G44: 0 | H44: 0 | I44: 0 | J44: 0 | K44: 0 | L44: 0 | M44: 0 | N44: 0 | O44: =SUM(C44:N44) -> 0
B45: Rendimentos Aplicações | C45: 5000 | D45: 5000 | E45: 5000 | F45: 5000 | G45: 5000 | H45: 5000 | I45: 5000 | J45: 5000 | K45: 5000 | L45: 5000 | M45: 5000 | N45: 5000 | O45: =SUM(C45:N45) -> 60000
O46: =SUM(C46:N46) -> 0
B47: DESPESAS | C47: =SUM(C48,C50,C53,C75,C99,C105,C116,C120,C123,C126,C130,C133) -> 49380 | D47: =SUM(D48,D50,D53,D75,D99,D105,D116,D120,D123,D126,D130,D133) -> 45560 | E47: =SUM(E48,E50,E53,E75,E99,E105,E116,E120,E123,E126,E130,E133) -> 47580 | F47: =SUM(F48,F50,F53,F75,F99,F105,F116,F120,F123,F126,F130,F133) -> 48160 | G47: =SUM(G48,G50,G53,G75,G99,G105,G116,G120,G123,G126,G130,G133) -> 45680 | H47: =SUM(H48,H50,H53,H75,H99,H105,H116,H120,H123,H126,H130,H133) -> 45560 | I47: =SUM(I48,I50,I53,I75,I99,I105,I116,I120,I123,I126,I130,I133) -> 47080 | J47: =SUM(J48,J50,J53,J75,J99,J105,J116,J120,J123,J126,J130,J133) -> 61910 | ... N47: =SUM(N48,N50,N53,N75,N99,N105,N116,N120,N123,N126,N130,N133) -> 46450 | O47: =SUM(C47:N47) -> 577550
B48: Despesas Diretas | C48: =SUM(C49) -> 0 | D48: =SUM(D49) -> 0 | E48: =SUM(E49) -> 0 | F48: =SUM(F49) -> 0 | G48: =SUM(G49) -> 0 | H48: =SUM(H49) -> 0 | I48: =SUM(I49) -> 0 | J48: =SUM(J49) -> 0 | ... N48: =SUM(N49) -> 0 | O48: =SUM(C48:N48) -> 0
B49: Compras Mercadorias Revenda | C49: 0 | D49: 0 | E49: 0 | F49: 0 | G49: 0 | H49: 0 | I49: 0 | J49: 0 | K49: 0 | L49: 0 | M49: 0 | N49: 0 | O49: =SUM(C49:N49) -> 0
B50: Marketing | C50: =SUM(C51:C52) -> 0 | D50: =SUM(D51:D52) -> 0 | E50: =SUM(E51:E52) -> 0 | F50: =SUM(F51:F52) -> 0 | G50: =SUM(G51:G52) -> 0 | H50: =SUM(H51:H52) -> 0 | I50: =SUM(I51:I52) -> 0 | J50: =SUM(J51:J52) -> 0 | ... N50: =SUM(N51:N52) -> 0 | O50: =SUM(C50:N50) -> 0
B51: Divulgação | C51: 0 | D51: 0 | E51: 0 | F51: 0 | G51: 0 | H51: 0 | I51: 0 | J51: 0 | K51: 0 | L51: 0 | M51: 0 | N51: 0 | O51: =SUM(C51:N51) -> 0
B52: Vestuários | C52: 0 | D52: 0 | E52: 0 | F52: 0 | G52: 0 | H52: 0 | I52: 0 | J52: 0 | K52: 0 | L52: 0 | M52: 0 | N52: 0 | O52: =SUM(C52:N52) -> 0
B53: Despesas com Pessoal | C53: =SUM(C54:C74) -> 33050 | D53: =SUM(D54:D74) -> 33050 | E53: =SUM(E54:E74) -> 33050 | F53: =SUM(F54:F74) -> 33050 | G53: =SUM(G54:G74) -> 33050 | H53: =SUM(H54:H74) -> 33050 | I53: =SUM(I54:I74) -> 33050 | J53: =SUM(J54:J74) -> 33050 | ... N53: =SUM(N54:N74) -> 33050 | O53: =SUM(C53:N53) -> 396600
B54: Comissões | C54: 0 | D54: 0 | E54: 0 | F54: 0 | G54: 0 | H54: 0 | I54: 0 | J54: 0 | K54: 0 | L54: 0 | M54: 0 | N54: 0 | O54: =SUM(C54:N54) -> 0
B55: Férias | C55: 0 | D55: 0 | E55: 0 | F55: 0 | G55: 0 | H55: 0 | I55: 0 | J55: 0 | K55: 0 | L55: 0 | M55: 0 | N55: 0 | O55: =SUM(C55:N55) -> 0
B56: Rescisões | C56: 0 | D56: 0 | E56: 0 | F56: 0 | G56: 0 | H56: 0 | I56: 0 | J56: 0 | K56: 0 | L56: 0 | M56: 0 | N56: 0 | O56: =SUM(C56:N56) -> 0
B57: 13º Salário | C57: 0 | D57: 0 | E57: 0 | F57: 0 | G57: 0 | H57: 0 | I57: 0 | J57: 0 | K57: 0 | L57: 0 | M57: 0 | N57: 0 | O57: =SUM(C57:N57) -> 0
B58: INSS | C58: 0 | D58: 0 | E58: 0 | F58: 0 | G58: 0 | H58: 0 | I58: 0 | J58: 0 | K58: 0 | L58: 0 | M58: 0 | N58: 0 | O58: =SUM(C58:N58) -> 0
B59: FGTS | C59: 0 | D59: 0 | E59: 0 | F59: 0 | G59: 0 | H59: 0 | I59: 0 | J59: 0 | K59: 0 | L59: 0 | M59: 0 | N59: 0 | O59: =SUM(C59:N59) -> 0
B60: IRRF | C60: 0 | D60: 0 | E60: 0 | F60: 0 | G60: 0 | H60: 0 | I60: 0 | J60: 0 | K60: 0 | L60: 0 | M60: 0 | N60: 0 | O60: =SUM(C60:N60) -> 0
B61: Exames | C61: 0 | D61: 0 | E61: 0 | F61: 0 | G61: 0 | H61: 0 | I61: 0 | J61: 0 | K61: 0 | L61: 0 | M61: 0 | N61: 0 | O61: =SUM(C61:N61) -> 0
B62: Assistência Médica | C62: 0 | D62: 0 | E62: 0 | F62: 0 | G62: 0 | H62: 0 | I62: 0 | J62: 0 | K62: 0 | L62: 0 | M62: 0 | N62: 0 | O62: =SUM(C62:N62) -> 0
B63: Vale Transporte | C63: 0 | D63: 0 | E63: 0 | F63: 0 | G63: 0 | H63: 0 | I63: 0 | J63: 0 | K63: 0 | L63: 0 | M63: 0 | N63: 0 | O63: =SUM(C63:N63) -> 0
B64: Vale Refeição | C64: 850 | D64: 850 | E64: 850 | F64: 850 | G64: 850 | H64: 850 | I64: 850 | J64: 850 | K64: 850 | L64: 850 | M64: 850 | N64: 850 | O64: =SUM(C64:N64) -> 10200
B65: Seguro de Vida | C65: 0 | D65: 0 | E65: 0 | F65: 0 | G65: 0 | H65: 0 | I65: 0 | J65: 0 | K65: 0 | L65: 0 | M65: 0 | N65: 0 | O65: =SUM(C65:N65) -> 0
... B74: Ajuda de Custo | C74: 0 | D74: 0 | E74: 0 | F74: 0 | G74: 0 | H74: 0 | I74: 0 | J74: 0 | K74: 0 | L74: 0 | M74: 0 | N74: 0 | O74: =SUM(C74:N74) -> 0
B75: Despesas Administrativas | C75: =SUM(C76:C98) -> 13530 | D75: =SUM(D76:D98) -> 10210 | E75: =SUM(E76:E98) -> 10330 | F75: =SUM(F76:F98) -> 12810 | G75: =SUM(G76:G98) -> 10330 | H75: =SUM(H76:H98) -> 10210 | I75: =SUM(I76:I98) -> 11730 | J75: =SUM(J76:J98) -> 26560 | ... N75: =SUM(N76:N98) -> 11100 | O75: =SUM(C75:N75) -> 150750
B76: Aluguel Espaços | C76: 2150 | D76: 2150 | E76: 2150 | F76: 2150 | G76: 2150 | H76: 2150 | I76: 2150 | J76: 2500 | K76: 2500 | L76: 2500 | M76: 2500 | N76: 2500 | O76: =SUM(C76:N76) -> 27550
B77: Aluguel/Locações Outros | C77: 0 | D77: 450 | E77: 450 | F77: 450 | G77: 450 | H77: 450 | I77: 450 | J77: 450 | K77: 450 | L77: 450 | M77: 450 | N77: 450 | O77: =SUM(C77:N77) -> 4950
B78: ÁGUA | C78: 350 | D78: 350 | E78: 350 | F78: 350 | G78: 350 | H78: 350 | I78: 350 | J78: 350 | K78: 350 | L78: 350 | M78: 350 | N78: 350 | O78: =SUM(C78:N78) -> 4200
B79: Energia Elétrica | C79: 1100 | D79: 1100 | E79: 1100 | F79: 1100 | G79: 1100 | H79: 1100 | I79: 1100 | J79: 1100 | K79: 1100 | L79: 1100 | M79: 1100 | N79: 1100 | O79: =SUM(C79:N79) -> 13200
B80: TELEFONIA/INTERNET | C80: 400 | D80: 400 | E80: 400 | F80: 400 | G80: 400 | H80: 400 | I80: 400 | J80: 400 | K80: 400 | L80: 400 | M80: 400 | N80: 400 | O80: =SUM(C80:N80) -> 4800
B81: Material de Escritório | C81: 400 | D81: 0 | F81: 400 | G81: 0 | H81: 0 | I81: 400 | J81: 0 | K81: 0 | L81: 400 | M81: 0 | N81: 0 | O81: =SUM(C81:N81) -> 1600
B82: Gás | C82: 120 | D82: 0 | E82: 120 | F82: 0 | G82: 120 | H82: 0 | I82: 120 | J82: 0 | K82: 120 | L82: 0 | M82: 120 | N82: 0 | O82: =SUM(C82:N82) -> 720
B83: Seguros | C83: 2500 | D83: 0 | E83: 0 | F83: 0 | G83: 0 | H83: 0 | I83: 0 | J83: 16000 | K83: 0 | L83: 0 | M83: 0 | N83: 0 | O83: =SUM(C83:N83) -> 18500
B84: IPTU | C84: 0 | D84: 0 | E84: 0 | F84: 1200 | G84: 0 | H84: 0 | I84: 0 | J84: 0 | K84: 0 | L84: 0 | M84: 0 | N84: 0 | O84: =SUM(C84:N84) -> 1200
B85: Contabilidade | C85: 500 | D85: 500 | E85: 500 | F85: 500 | G85: 500 | H85: 500 | I85: 500 | J85: 500 | K85: 500 | L85: 500 | M85: 1000 | N85: 1000 | O85: =SUM(C85:N85) -> 7000
B86: Advogados | C86: 2500 | D86: 2500 | E86: 2500 | F86: 2500 | G86: 2500 | H86: 2500 | I86: 2500 | J86: 2500 | K86: 2500 | L86: 2500 | M86: 2500 | N86: 2500 | O86: =SUM(C86:N86) -> 30000
B87: Segurança | C87: 0 | D87: 0 | E87: 0 | F87: 0 | G87: 0 | H87: 0 | I87: 0 | J87: 0 | K87: 0 | L87: 0 | M87: 0 | N87: 0 | O87: =SUM(C87:N87) -> 0
B88: Limpeza/Higiene/Copa | C88: 1000 | D88: 0 | E88: 0 | F88: 1000 | G88: 0 | H88: 0 | I88: 1000 | J88: 0 | K88: 0 | L88: 1000 | M88: 0 | N88: 0 | O88: =SUM(C88:N88) -> 4000
B89: Manutenção Equipamentos | C89: 300 | D89: 300 | E89: 300 | F89: 300 | G89: 300 | H89: 300 | I89: 300 | J89: 300 | K89: 300 | L89: 300 | M89: 300 | N89: 300 | O89: =SUM(C89:N89) -> 3600
B90: Assinaturas/Licenças | C90: 160 | D90: 160 | E90: 160 | F90: 160 | G90: 160 | H90: 160 | I90: 160 | J90: 160 | K90: 200 | L90: 200 | M90: 200 | N90: 200 | O90: =SUM(C90:N90) -> 2080
B91: Cartórios/Correios | C91: 0 | D91: 50 | E91: 50 | F91: 50 | G91: 50 | H91: 50 | I91: 50 | J91: 50 | K91: 50 | L91: 50 | M91: 50 | N91: 50 | O91: =SUM(C91:N91) -> 550
B92: Estacionamentos/Pedágios | C92: 0 | D92: 50 | E92: 50 | F92: 50 | G92: 50 | H92: 50 | I92: 50 | J92: 50 | K92: 50 | L92: 50 | M92: 50 | N92: 50 | O92: =SUM(C92:N92) -> 550
B93: TRANSPORTES/FRETES | C93: 0 | D93: 150 | E93: 150 | F93: 150 | G93: 150 | H93: 150 | I93: 150 | J93: 150 | K93: 150 | L93: 150 | M93: 150 | N93: 150 | O93: =SUM(C93:N93) -> 1650
... B98: PRESTAÇÃO SERV. TERCEIROS | C98: 1200 | D98: 1200 | E98: 1200 | F98: 1200 | G98: 1200 | H98: 1200 | I98: 1200 | J98: 1200 | K98: 1200 | L98: 1200 | M98: 1200 | N98: 1200 | O98: =SUM(C98:N98) -> 14400
B99: Despesas Financeiras / Bancos | C99: =SUM(C100:C104) -> 150 | D99: =SUM(D100:D104) -> 150 | E99: =SUM(E100:E104) -> 150 | F99: =SUM(F100:F104) -> 150 | G99: =SUM(G100:G104) -> 150 | H99: =SUM(H100:H104) -> 150 | I99: =SUM(I100:I104) -> 150 | J99: =SUM(J100:J104) -> 150 | ... N99: =SUM(N100:N104) -> 150 | O99: =SUM(C99:N99) -> 1800
B100: Juros sobre Empréstimos | C100: 0 | D100: 0 | E100: 0 | F100: 0 | G100: 0 | H100: 0 | I100: 0 | J100: 0 | K100: 0 | L100: 0 | M100: 0 | N100: 0 | O100: =SUM(C100:N100) -> 0
B101: Multas | C101: 0 | D101: 0 | E101: 0 | F101: 0 | G101: 0 | H101: 0 | I101: 0 | J101: 0 | K101: 0 | L101: 0 | M101: 0 | N101: 0 | O101: =SUM(C101:N101) -> 0
B102: Pagamento de Empréstimos | C102: 0 | D102: 0 | E102: 0 | F102: 0 | G102: 0 | H102: 0 | I102: 0 | J102: 0 | K102: 0 | L102: 0 | M102: 0 | N102: 0 | O102: =SUM(C102:N102) -> 0
B103: Tarifas Bancárias | C103: 150 | D103: 150 | E103: 150 | F103: 150 | G103: 150 | H103: 150 | I103: 150 | J103: 150 | K103: 150 | L103: 150 | M103: 150 | N103: 150 | O103: =SUM(C103:N103) -> 1800
B104: Despesas Bancárias | C104: 0 | D104: 0 | E104: 0 | F104: 0 | G104: 0 | H104: 0 | I104: 0 | J104: 0 | K104: 0 | L104: 0 | M104: 0 | N104: 0 | O104: =SUM(C104:N104) -> 0
B105: Impostos e Taxas | C105: =SUM(C106:C115) -> 100 | D105: =SUM(D106:D115) -> 100 | E105: =SUM(E106:E115) -> 2000 | F105: =SUM(F106:F115) -> 100 | G105: =SUM(G106:G115) -> 100 | H105: =SUM(H106:H115) -> 100 | I105: =SUM(I106:I115) -> 100 | J105: =SUM(J106:J115) -> 100 | ... N105: =SUM(N106:N115) -> 100 | O105: =SUM(C105:N105) -> 3300
B106: ICMS | C106: 0 | D106: 0 | E106: 0 | F106: 0 | G106: 0 | H106: 0 | I106: 0 | J106: 0 | K106: 0 | L106: 0 | M106: 0 | N106: 0 | O106: =SUM(C106:N106) -> 0
B107: IPI | C107: 0 | D107: 0 | E107: 0 | F107: 0 | G107: 0 | H107: 0 | I107: 0 | J107: 0 | K107: 0 | L107: 0 | M107: 0 | N107: 0 | O107: =SUM(C107:N107) -> 0
B108: PIS | C108: 0 | D108: 0 | E108: 0 | F108: 0 | G108: 0 | H108: 0 | I108: 0 | J108: 0 | K108: 0 | L108: 0 | M108: 0 | N108: 0 | O108: =SUM(C108:N108) -> 0
B109: COFINS | C109: 0 | D109: 0 | E109: 0 | F109: 0 | G109: 0 | H109: 0 | I109: 0 | J109: 0 | K109: 0 | L109: 0 | M109: 0 | N109: 0 | O109: =SUM(C109:N109) -> 0
B110: IRPJ | C110: 0 | D110: 0 | E110: 0 | F110: 0 | G110: 0 | H110: 0 | I110: 0 | J110: 0 | K110: 0 | L110: 0 | M110: 0 | N110: 0 | O110: =SUM(C110:N110) -> 0
B111: Contribuição Social | C111: 0 | D111: 0 | E111: 0 | F111: 0 | G111: 0 | H111: 0 | I111: 0 | J111: 0 | K111: 0 | L111: 0 | M111: 0 | N111: 0 | O111: =SUM(C111:N111) -> 0
B112: ISS | C112: 0 | D112: 0 | E112: 0 | F112: 0 | G112: 0 | H112: 0 | I112: 0 | J112: 0 | K112: 0 | L112: 0 | M112: 0 | N112: 0 | O112: =SUM(C112:N112) -> 0
B113: Simples Nacional (DAS) | C113: 0 | D113: 0 | E113: 0 | F113: 0 | G113: 0 | H113: 0 | I113: 0 | J113: 0 | K113: 0 | L113: 0 | M113: 0 | N113: 0 | O113: =SUM(C113:N113) -> 0
B114: IMPOSTOS/TAXAS | C114: 100 | D114: 100 | E114: 2000 | F114: 100 | G114: 100 | H114: 100 | I114: 100 | J114: 100 | K114: 100 | L114: 300 | M114: 100 | N114: 100 | O114: =SUM(C114:N114) -> 3300
...

Sheet VALOR SETORIZADO
B2: PEC | G2: Q. PROFISSIONAL | L2: OUTLET
B3: TIME | C3: 6450 | D3: . | E3: 12 | G3: SUPERVISOR | H3: 2500 | I3: =SUM(H3*J3) -> 30000 | J3: 12 | L3: ATENDENTE | M3: 1320 | N3: =SUM(M3*O3) -> 15840 | O3: 12
B4: LOGISTICA/TRANSP. | C4: 600 | D4: =SUM(C4*E4) -> 31200 | E4: 52 | G4: ASSIST. Q.P. | H4: 1420 | I4: =SUM(H4*J4) -> 17040 | J4: 12 | L4: GERENTE NEGOCIOS SOCIAIS | M4: 1500 | N4: =SUM(M4*O4) -> 18000 | O4: 12
B5: ALIMENTAÇÃO | C5: 680 | D5: =SUM(C5*E5) -> 35360 | E5: 52 | G5: PROFESSORES | H5: 1000 | I5: =SUM(H5*J5) -> 10000 | J5: 10 | L5: LOGISTICA | M5: 1420 | N5: =SUM(M5*O5) -> 17040 | O5: 12
B6: MANUTENÇÃO | C6: 200 | D6: =SUM(C6*E6) -> 2000 | E6: 10 | G6: MOTORISTA | H6: 1420 | I6: =SUM(H6*J6) -> 17040 | J6: 12 | L6: MANUTENÇÃO | M6: 300 | N6: =SUM(M6*O6) -> 3600 | O6: 12
B7: EVENTOS | C7: 3000 | D7: =SUM(C7*E7) -> 6000 | E7: 2 | G7: MANUTENÇÃO | H7: 200 | I7: =SUM(H7*J7) -> 2000 | J7: 10 | L7: INSUMOS | M7: 300 | N7: =SUM(M7*O7) -> 3600 | O7: 12
B8: INSUMOS | C8: 250 | D8: =SUM(C8*E8) -> 2500 | E8: 10 | G8: TRANSPORTE | H8: 1000 | I8: =SUM(H8*J8) -> 10000 | J8: 10 | L8: FRETES | M8: 500 | N8: =SUM(M8*O8) -> 6000 | O8: 12
B9: MAT. OFIC. AQUIS. | C9: 20000 | D9: =SUM(C9*E9) -> 20000 | E9: 1 | G9: MATERIAL AULA | H9: 300 | I9: =SUM(H9*J9) -> 3000 | J9: 10
B10: TREINAMENTOS | C10: 1000 | D10: =SUM(C10*E10) -> 1000 | E10: 1 | G10: MATERIAL GRÁFICOS | H10: 50 | I10: =SUM(H10*J10) -> 500 | J10: 10
D13: =SUM(D3:D12) -> 98060 | I13: =SUM(I3:I11) -> 89580 | N13: =SUM(N3:N10) -> 64080
B15: PSICOSSOCIAL | G15: MARKETING | L15: GRIFFTE
B16: PSICÓLOGO | C16: 2000 | D16: =C16*E16 -> 24000 | E16: 12 | G16: SUPERVISOR | H16: 3000 | I16: =SUM(H16*J16) -> 36000 | J16: 12 | L16: COORDENADOR | M16: 2000 | N16: =SUM(M16*O16) -> 24000 | O16: 12
B17: INSUMOS | C17: 250 | D17: =C17*E17 -> 2500 | E17: 10 | G17: ASSIST. MTK | H17: 2000 | I17: =SUM(H17*J17) -> 24000 | J17: 12 | L17: GERENTE NEGOCIOS SOCIAIS | M17: 1500 | N17: =SUM(M17*O17) -> 18000 | O17: 12
G18: ASSIST. VIDEO | H18: 1000 | I18: =SUM(H18*J18) -> 12000 | J18: 12 | L18: MANUTENÇÃO | M18: 300 | N18: =SUM(M18*O18) -> 3600 | O18: 12
G19: Eventos | H19: 5000 | I19: =SUM(H19*J19) -> 5000 | J19: 1 | L19: LOGISTICA | M19: 1420 | N19: =SUM(M19*O19) -> 17040 | O19: 12
D20: =SUM(D16:D19) -> 26500 | G20: Material Divulgação | H20: 10000 | I20: =SUM(H20*J20) -> 10000 | J20: 1 | L20: INSUMOS | M20: 300 | N20: =SUM(M20*O20) -> 300 | O20: 1
B21: OPERAÇÕES | G21: Parceiros e Visitas | H21: 1500 | I21: =SUM(H21*J21) -> 1500 | J21: 1 | L21: COSTUREIRAS | M21: 3960 | N21: =SUM(M21*O21) -> 47520 | O21: 12
B22: COORDENADOR | C22: 3500 | D22: =C22*E22 -> 42000 | E22: 12 | G22: Ferramentas Trabalho | H22: 15000 | I22: =SUM(H22*J22) -> 15000 | J22: 1
G23: CAMISAS /UNIFORMES | H23: 3000 | I23: =SUM(H23*J23) -> 3000 | J23: 1
D25: =SUM(D22:D24) -> 42000 | I25: =SUM(I16:I24) -> 106500 | N25: =SUM(N16:N24) -> 110460
L27: CASA SONHAR
B28: RECEITA | D28: % | G28: CUSTO | I28: % | L28: Assistente pedagógico | M28: 1500 | N28: =SUM(M28*O28) -> 18000 | O28: 12
B29: JANTAR | C29: - | G29: QP | H29: =I13 -> 89580 | I29: =H29/H$39 -> 0.070390219 | L29: Monitor pedagógico | M29: 1400 | N29: =SUM(M29*O29) -> 16800 | O29: 12
B30: DOAÇÕES | C30: =ADM!O22 -> 66000 | D30: =C30/C$39 -> 0.34904937 | G30: PEC | H30: =D13 -> 98060 | I30: =H30/H$39 -> 0.077053637 | L30: Profissional de apoio e limpeza | M30: 1400 | N30: =SUM(M30*O30) -> 16800 | O30: 12
B31: APORTE | C31: =ADM!O28 -> 0 | D31: =C31/C$39 -> 0 | G31: CASA SONHAR | H31: =N48 -> 250440 | I31: =H31/H$39 -> 0.19679087 | L31: Educadores Sociais - (2) | M31: 3600 | N31: =SUM(M31*O31) -> 43200 | O31: 12
B32: NEGOCIOS SOCIAIS | C32: =ADM!O37 -> 0 | D32: =C32/C$39 -> 0 | G32: PSICOSSOCIAL | H32: =D20 -> 26500 | I32: =H32/H$39 -> 0.020823184 | L32: Educador de Ballet | M32: 900 | N32: =SUM(M32*O32) -> 10800 | O32: 12
B33: EVENTOS | C33: =ADM!O40 -> 63085 | D33: =C33/C$39 -> 0.33363302 | G33: MARKETING | H33: =I25 -> 106500 | I33: =H33/H$39 -> 0.083685625 | L33: Educador de Dança Contemporânea | M33: 600 | N33: =SUM(M33*O33) -> 7200 | O33: 12
B34: APLICAÇÕES | C34: =ADM!O43 -> 60000 | D34: =C34/C$39 -> 0.31731761 | G34: ADM | H34: 485000 | I34: =H34/H$39 -> 0.38110355 | L34: Educador de Artes | M34: 960 | N34: =SUM(M34*O34) -> 11520 | O34: 12
B35: EDITAIS | C35: =ADM!O33 -> 0 | G35: OUTLET | H35: =N13 -> 64080 | I35: =H35/H$39 -> 0.050352815 | L35: Educador de Musica | M35: 960 | N35: =SUM(M35*O35) -> 11520 | O35: 12
G36: GRIFFTE | H36: =N25 -> 110460 | I36: =H36/H$39 -> 0.086797316 | L36: Educador de Capoeira | M36: 180 | N36: =SUM(M36*O36) -> 2160 | O36: 12
G37: OPERAÇÕES | H37: =D25 -> 42000 | I37: =H37/H$39 -> 0.033002782 | L37: Alimentação | M37: 3500 | N37: =SUM(M37*O37) -> 38500 | O37: 11
L38: Material pedagógico | M38: 200 | N38: =SUM(M38*O38) -> 2200 | O38: 11
C39: =SUM(C29:C38) -> 189085 | D39: =C39/C$39 -> 1 | H39: =SUM(H29:H37) -> 1272620 | I39: =H39/H$39 -> 1 | L39: Eventos | M39: 3000 | N39: =SUM(M39*O39) -> 12000 | O39: 4
L40: Excursões qtdade a definir | N40: 5000
L41: Manutenção/Reforma | N41: 25000
L42: Manutenção Equipamento | M42: 200 | N42: =SUM(M42*O42) -> 2200 | O42: 11
L43: Aluguel | M43: 1500 | N43: =SUM(M43*O43) -> 18000 | O43: 12
L44: Agua | M44: 250 | N44: =SUM(M44*O44) -> 3000 | O44: 12
L45: Luz | M45: 350 | N45: =SUM(M45*O45) -> 4200 | O45: 12
L46: Telefonia/Internet | M46: 195 | N46: =SUM(M46*O46) -> 2340 | O46: 12
N48: =SUM(N28:N46) -> 250440
A57: RECEITA POR MEIO CAPTAÇÃO | I57: CUSTO POR SETOR
A58: SETOR | C58: ESPERADO | D58: ESPERADO | E58: REAL | F58: REAL | G58: SALDO | I58: SETOR | K58: ESPERADO | L58: ESPERADO | M58: REAL | N58: REAL | O58: SALDO
A60: APORTE GF | B60: 226200 | C60: 20300 | D60: =C60/B60 -> 0.08974359 | E60: 21300 | F60: =E60/B60 -> 0.094164456 | G60: =F60-D60 -> 0.0044208665 | I60: QP | J60: =H29 -> 89580 | K60: 7918.34 | L60: =K60/J60 -> 0.088394061 | M60: 5627.16 | N60: =M60/J60 -> 0.062817147 | O60: =L60-N60 -> 0.025576914
A61: DOADOR RECORRENTE | B61: 59400 | C61: 4950 | D61: =C61/B61 -> 0.083333333 | E61: 4910.64 | F61: =E61/B61 -> 0.082670707 | G61: =F61-D61 -> -0.00066262626 | I61: PEC | J61: =H30 -> 98060 | K61: 14800.37 | L61: =K61/J61 -> 0.15093178 | M61: 13318.18 | N61: =M61/J61 -> 0.13581664 | O61: =L61-N61 -> 0.015115134
A62: DOADOR PONTUAL | B62: 73000 | C62: 6083.33 | D62: =C62/B62 -> 0.083333288 | E62: 842.61 | F62: =E62/B62 -> 0.011542603 | G62: =F62-D62 -> -0.071790685 | I62: CIDADANIA | J62: =H32 -> 26500 | K62: 11225 | L62: =K62/J62 -> 0.42358491 | M62: 6100.71 | N62: =M62/J62 -> 0.23021547 | O62: =L62-N62 -> 0.19336943
A63: OUTLET | B63: 84000 | C63: 7000 | D63: =C63/B63 -> 0.083333333 | E63: 5593.53 | F63: =E63/B63 -> 0.066589643 | G63: =F63-D63 -> -0.01674369 | I63: MARKETING | J63: =H33 -> 106500 | K63: 3982.81 | L63: =K63/J63 -> 0.037397277 | M63: 3144.6 | N63: =M63/J63 -> 0.029526761 | O63: =L63-N63 -> 0.0078705164
A64: EVENTOS | B64: 257500 | C64: 0 | D64: =C64/B64 -> 0 | E64: 0 | F64: =E64/B64 -> 0 | G64: =F64-D64 -> 0 | I64: ADM | J64: =H34 -> 485000 | K64: 19683.63 | L64: =K64/J64 -> 0.040584804 | M64: 30897.21 | N64: =M64/J64 -> 0.063705588 | O64: =L64-N64 -> -0.023120784
A65: GRIFFTE | B65: 52000 | C65: 0 | D65: =C65/B65 -> 0 | E65: 0 | F65: =E65/B65 -> 0 | G65: =F65-D65 -> 0 | I65: OUTLET | J65: =H35 -> 64080 | K65: 2879 | L65: =K65/J65 -> 0.044928215 | M65: 3341.63 | N65: =M65/J65 -> 0.052147784 | O65: =L65-N65 -> -0.0072195693
A66: PEC | B66: 12717.16 | C66: 1271.72 | D66: =C66/B66 -> 0.10000031 | E66: 0 | F66: =E66/B66 -> 0 | G66: =F66-D66 -> -0.10000031 | I66: GRIFFTE | J66: =H36 -> 110460 | K66: 1126.67 | L66: =K66/J66 -> 0.010199801 | M66: 5627.16 | N66: =M66/J66 -> 0.050942966 | O66: =L66-N66 -> -0.040743165
A67: Q.PROFISSIONAL | B67: 8580 | C67: 858 | D67: =C67/B67 -> 0.1 | E67: 0 | F67: =E67/B67 -> 0 | G67: =F67-D67 -> -0.1
A68: CIDADANIA | B68: 800 | C68: 80 | D68: =C68/B68 -> 0.1 | E68: 0 | F68: =E68/B68 -> 0 | G68: =F68-D68 -> -0.1 | K68: =SUM(K60:K66) -> 61615.82 | L68: =SUM(L60:L66) -> 0.79602084 | M68: =SUM(M60:M66) -> 68056.65 | N68: =SUM(N60:N66) -> 0.62517236 | O68: =SUM(O60:O66) -> 0.17084848
C70: =SUM(C60:C68) -> 40543.05 | D70: =SUM(D60:D68) -> 0.63974386 | E70: =SUM(E60:E68) -> 32646.78 | F70: =SUM(F60:F68) -> 0.25496741 | G70: =SUM(G60:G68) -> -0.38477645 | I70: SALDO GERAL
I71: UNIDADE | K71: ESPERADO | L71: ESPERADO | M71: REAL | N71: REAL | O71: SALDO
D73: =SUM(M68/E70) -> 2.0846359 | I73: O GRITO | J73: 72875.8 | K73: 116691.85 | L73: =SUM(J73/K73)-100% -> -0.37548509

Sheet PREVISTO X REALIZADO
C1: INSTITUTO DE CAPACITACAO E ACAO SOCIAL O GRITO - PLANEJAMENTO 2024
D2: Emitido por RICARDO em 17/11/2023 10:58
B3: CATEGORIA | C3: PREVISTO | D3: REALIZADO/ REALIZAR | E3: DIFERENÇA | F3: JUSTIFICATIVA
B4: RECEITAS | C4: 0 | D4: 0 | E4: 0
B5: Devoluções | C5: 0 | D5: 0 | E5: 0
B6: Devoluções Compra Mercadoria Revenda | C6: 0 | D6: 0 | E6: 0
B7: Devoluções de Compra Material Consumo | C7: 0 | D7: 0 | E7: 0
B8: Devoluções de Compra de Matéria Prima | C8: 0 | D8: 0 | E8: 0
B9: Devoluções de Compra de Ativo | C9: 0 | D9: 0 | E9: 0
B10: Devoluções de Compra de Serviços | C10: 0 | D10: 0 | E10: 0
B11: Devolução de Doações | C11: 0 | D11: 0 | E11: 0
B12: Outras Entradas | C12: 0 | D12: 0 | E12: 0
B13: Empréstimos Bancários | C13: 0 | D13: 0 | E13: 0
B14: Aumento de Capital | C14: 0 | D14: 0 | E14: 0
B15: Venda de Ativos | C15: 0 | D15: 0 | E15: 0
... B136: Silker | C136: 0 | D136: 0 | E136: 0

Sheet MARKETING
C1: INSTITUTO DE CAPACITACAO E ACAO SOCIAL O GRITO - PLANEJAMENTO 2025 - MARKETING
A2: Emitido por RICARDO em 17/11/2023 10:58 | C2: =C47/O$47 -> 0.023491054 | D2: =D47/$O$47 -> 0.13583671 | E2: =E47/$O$47 -> 0.062611106 | F2: =F47/$O$47 -> 0.061835458 | G2: =G47/$O$47 -> 0.032360833 | H2: =H47/$O$47 -> 0.14316769 | I2: =I47/$O$47 -> 0.14870804 | J2: =J47/$O$47 -> 0.033025674 | K2: =K47/$O$47 -> 0.032360833 | ... N2: =N47/$O$47 -> 0.18781763
B3: CATEGORIA | C3: JANEIRO | D3: FEVEREIRO | E3: MARÇO | F3: ABRIL | G3: MAIO | H3: JUNHO | I3: JULHO | J3: AGOSTO | K3: SETEMBRO | L3: OUTUBRO | M3: NOVEMBRO | N3: DEZEMBRO | O3: TOTAL
B5: SALDO ACUMULADO | C5: =C6 -> -10600 | D5: =C5+D6 -> -70394.36 | E5: =D5+E6 -> -93746.72 | F5: =E5+F6 -> -116749.08 | G5: =F5+G6 -> -126451.44 | H5: =G5+H6 -> -177153.8 | I5: =H5+I6 -> -244256.16 | J5: =I5+J6 -> -259158.52 | K5: =J5+K6 -> -273760.88 | ... N5: =M5+N6 -> -421135.6
B6: SALDO MÊS | C6: =SUM(C8-C47) -> -10600 | D6: =SUM(D8-D47) -> -59794.36 | E6: =SUM(E8-E47) -> -23352.36 | F6: =SUM(F8-F47) -> -23002.36 | G6: =SUM(G8-G47) -> -9702.36 | H6: =SUM(H8-H47) -> -50702.36 | I6: =SUM(I8-I47) -> -67102.36 | J6: =SUM(J8-J47) -> -14902.36 | ... N6: =SUM(N8-N47) -> -84750 | O6: =SUM(C6:N6) -> -421135.6
B8: RECEITAS | C8: =SUM(C9,C16,C22,C28,C33,C37,C40,C43) -> 0 | D8: =SUM(D9,D16,D22,D28,D33,D37,D40,D43) -> 1500 | E8: =SUM(E9,E16,E22,E28,E33,E37,E40,E43) -> 4900 | F8: =SUM(F9,F16,F22,F28,F33,F37,F40,F43) -> 4900 | G8: =SUM(G9,G16,G22,G28,G33,G37,G40,G43) -> 4900 | H8: =SUM(H9,H16,H22,H28,H33,H37,H40,H43) -> 13900 | I8: =SUM(I9,I16,I22,I28,I33,I37,I40,I43) -> 0 | J8: =SUM(J9,J16,J22,J28,J33,J37,J40,J43) -> 0 | ... N8: =SUM(N9,N16,N22,N28,N33,N37,N40,N43) -> 0 | O8: =SUM(C8:N8) -> 30100
B9: Devoluções | C9: =SUM(C10:C15) -> 0 | D9: =SUM(D10:D15) -> 0 | E9: =SUM(E10:E15) -> 0 | F9: =SUM(F10:F15) -> 0 | G9: =SUM(G10:G15) -> 0 | H9: =SUM(H10:H15) -> 0 | I9: =SUM(I10:I15) -> 0 | J9: =SUM(J10:J15) -> 0 | ... N9: =SUM(N10:N15) -> 0 | O9: =SUM(C9:N9) -> 0
B10: Devoluções Compra Mercadoria Revenda | C10: 0 | D10: 0 | E10: 0 | F10: 0 | G10: 0 | H10: 0 | I10: 0 | J10: 0 | K10: 0 | L10: 0 | M10: 0 | N10: 0 | O10: =SUM(C10:N10) -> 0
B11: Devoluções de Compra Material Consumo | C11: 0 | D11: 0 | E11: 0 | F11: 0 | G11: 0 | H11: 0 | I11: 0 | J11: 0 | K11: 0 | L11: 0 | M11: 0 | N11: 0 | O11: =SUM(C11:N11) -> 0
B12: Devoluções de Compra de Matéria Prima | C12: 0 | D12: 0 | E12: 0 | F12: 0 | G12: 0 | H12: 0 | I12: 0 | J12: 0 | K12: 0 | L12: 0 | M12: 0 | N12: 0 | O12: =SUM(C12:N12) -> 0
B13: Devoluções de Compra de Ativo | C13: 0 | D13: 0 | E13: 0 | F13: 0 | G13: 0 | H13: 0 | I13: 0 | J13: 0 | K13: 0 | L13: 0 | M13: 0 | N13: 0 | O13: =SUM(C13:N13) -> 0
B14: Devoluções de Compra de Serviços | C14: 0 | D14: 0 | E14: 0 | F14: 0 | G14: 0 | H14: 0 | I14: 0 | J14: 0 | K14: 0 | L14: 0 | M14: 0 | N14: 0 | O14: =SUM(C14:N14) -> 0
B15: Devolução de Doações | C15: 0 | D15: 0 | E15: 0 | F15: 0 | G15: 0 | H15: 0 | I15: 0 | J15: 0 | K15: 0 | L15: 0 | M15: 0 | N15: 0 | O15: =SUM(C15:N15) -> 0
B16: Outras Entradas | C16: =SUM(C17:C21) -> 0 | D16: =SUM(D17:D21) -> 0 | E16: =SUM(E17:E21) -> 0 | F16: =SUM(F17:F21) -> 0 | G16: =SUM(G17:G21) -> 0 | H16: =SUM(H17:H21) -> 0 | I16: =SUM(I17:I21) -> 0 | J16: =SUM(J17:J21) -> 0 | ... N16: =SUM(N17:N21) -> 0 | O16: =SUM(C16:N16) -> 0
B17: Empréstimos Bancários | C17: 0 | D17: 0 | E17: 0 | F17: 0 | G17: 0 | H17: 0 | I17: 0 | J17: 0 | K17: 0 | L17: 0 | M17: 0 | N17: 0 | O17: =SUM(C17:N17) -> 0
B18: Aumento de Capital | C18: 0 | D18: 0 | E18: 0 | F18: 0 | G18: 0 | H18: 0 | I18: 0 | J18: 0 | K18: 0 | L18: 0 | M18: 0 | N18: 0 | O18: =SUM(C18:N18) -> 0
B19: Venda de Ativos | C19: 0 | D19: 0 | E19: 0 | F19: 0 | G19: 0 | H19: 0 | I19: 0 | J19: 0 | K19: 0 | L19: 0 | M19: 0 | N19: 0 | O19: =SUM(C19:N19) -> 0
B20: AJUSTE DE CAIXA | C20: 0 | D20: 0 | E20: 0 | F20: 0 | G20: 0 | H20: 0 | I20: 0 | J20: 0 | K20: 0 | L20: 0 | M20: 0 | N20: 0 | O20: =SUM(C20:N20) -> 0
B21: Prêmios de Seguros / Sinistros | C21: 0 | D21: 0 | E21: 0 | F21: 0 | G21: 0 | H21: 0 | I21: 0 | J21: 0 | K21: 0 | L21: 0 | M21: 0 | N21: 0 | O21: =SUM(C21:N21) -> 0
B22: Doações | C22: =SUM(C23:C27) -> 0 | D22: =SUM(D23:D27) -> 1500 | E22: =SUM(E23:E27) -> 0 | F22: =SUM(F23:F27) -> 0 | G22: =SUM(G23:G27) -> 0 | H22: =SUM(H23:H27) -> 9000 | I22: =SUM(I23:I27) -> 0 | J22: =SUM(J23:J27) -> 0 | ... N22: =SUM(N23:N27) -> 0 | O22: =SUM(C22:N22) -> 10500
B23: Doações Recorrentes | C23: 0 | D23: 0 | E23: 0 | F23: 0 | G23: 0 | H23: 0 | I23: 0 | J23: 0 | K23: 0 | L23: 0 | M23: 0 | N23: 0 | O23: =SUM(C23:N23) -> 0
B24: Doações Pontuais PF | C24: 0 | D24: 1500 | E24: 0 | F24: 0 | G24: 0 | H24: 9000 | I24: 0 | J24: 0 | K24: 0 | L24: 0 | M24: 0 | N24: 0 | O24: =SUM(C24:N24) -> 10500
B25: Doações Pontuais PJ | C25: 0 | D25: 0 | E25: 0 | F25: 0 | G25: 0 | H25: 0 | I25: 0 | J25: 0 | K25: 0 | L25: 0 | M25: 0 | N25: 0 | O25: =SUM(C25:N25) -> 0
B26: Sócio Doador | C26: 0 | D26: 0 | E26: 0 | F26: 0 | G26: 0 | H26: 0 | I26: 0 | J26: 0 | K26: 0 | L26: 0 | M26: 0 | N26: 0 | O26: =SUM(C26:N26) -> 0
B27: Patrocínios | C27: 0 | D27: 0 | E27: 0 | F27: 0 | G27: 0 | H27: 0 | I27: 0 | J27: 0 | K27: 0 | L27: 0 | M27: 0 | N27: 0 | O27: =SUM(C27:N27) -> 0
B28: Gerando Falcões | C28: =SUM(C29:C32) -> 0 | D28: =SUM(D29:D32) -> 0 | E28: =SUM(E29:E32) -> 0 | F28: =SUM(F29:F32) -> 0 | G28: =SUM(G29:G32) -> 0 | H28: =SUM(H29:H32) -> 0 | I28: =SUM(I29:I32) -> 0 | J28: =SUM(J29:J32) -> 0 | ... N28: =SUM(N29:N32) -> 0 | O28: =SUM(C28:N28) -> 0
B29: Aporte | C29: 0 | D29: 0 | E29: 0 | F29: 0 | G29: 0 | H29: 0 | I29: 0 | J29: 0 | K29: 0 | L29: 0 | M29: 0 | N29: 0 | O29: =SUM(C29:N29) -> 0
B30: Falcons Univercity | C30: 0 | D30: 0 | E30: 0 | F30: 0 | G30: 0 | H30: 0 | I30: 0 | J30: 0 | K30: 0 | L30: 0 | M30: 0 | N30: 0 | O30: =SUM(C30:N30) -> 0
B31: Regional GF | C31: 0 | D31: 0 | E31: 0 | F31: 0 | G31: 0 | H31: 0 | I31: 0 | J31: 0 | K31: 0 | L31: 0 | M31: 0 | N31: 0 | O31: =SUM(C31:N31) -> 0
B32: Favela 3D | C32: 0 | D32: 0 | E32: 0 | F32: 0 | G32: 0 | H32: 0 | I32: 0 | J32: 0 | K32: 0 | L32: 0 | M32: 0 | N32: 0 | O32: =SUM(C32:N32) -> 0
B33: Editais/Projetos | C33: =SUM(C34:C36) -> 0 | D33: =SUM(D34:D36) -> 0 | E33: =SUM(E34:E36) -> 0 | F33: =SUM(F34:F36) -> 0 | G33: =SUM(G34:G36) -> 0 | H33: =SUM(H34:H36) -> 0 | I33: =SUM(I34:I36) -> 0 | J33: =SUM(J34:J36) -> 0 | ... N33: =SUM(N34:N36) -> 0 | O33: =SUM(C33:N33) -> 0
B34: Ecogaiola | C34: 0 | D34: 0 | E34: 0 | F34: 0 | G34: 0 | H34: 0 | I34: 0 | J34: 0 | K34: 0 | L34: 0 | M34: 0 | N34: 0 | O34: =SUM(C34:N34) -> 0
B35: Prog. Hab. Polaris | C35: 0 | D35: 0 | E35: 0 | F35: 0 | G35: 0 | H35: 0 | I35: 0 | J35: 0 | K35: 0 | L35: 0 | M35: 0 | N35: 0 | O35: =SUM(C35:N35) -> 0
B36: Lei De Incentivo | C36: 0 | D36: 0 | E36: 0 | F36: 0 | G36: 0 | H36: 0 | I36: 0 | J36: 0 | K36: 0 | L36: 0 | M36: 0 | N36: 0 | O36: =SUM(C36:N36) -> 0
B37: Negócios Sociais | C37: =SUM(C38:C39) -> 0 | D37: =SUM(D38:D39) -> 0 | E37: =SUM(E38:E39) -> 4900 | F37: =SUM(F38:F39) -> 4900 | G37: =SUM(G38:G39) -> 4900 | H37: =SUM(H38:H39) -> 4900 | I37: =SUM(I38:I39) -> 0 | J37: =SUM(J38:J39) -> 0 | ... N37: =SUM(N38:N39) -> 0 | O37: =SUM(C37:N37) -> 19600
B38: Vendas Outlet | C38: 0 | D38: 0 | E38: 4900 | F38: 4900 | G38: 4900 | H38: 4900 | O38: =SUM(C38:N38) -> 19600
B39: Vendas Griffte | C39: 0 | D39: 0 | E39: 0 | F39: 0 | G39: 0 | H39: 0 | O39: =SUM(C39:N39) -> 0
B40: Eventos | C40: =SUM(C41:C42) -> 0 | D40: =SUM(D41:D42) -> 0 | E40: =SUM(E41:E42) -> 0 | F40: =SUM(F41:F42) -> 0 | G40: =SUM(G41:G42) -> 0 | H40: =SUM(H41:H42) -> 0 | I40: =SUM(I41:I42) -> 0 | J40: =SUM(J41:J42) -> 0 | ... N40: =SUM(N41:N42) -> 0 | O40: =SUM(C40:N40) -> 0
B41: Clube Do Grito | C41: 0 | D41: 0 | E41: 0 | F41: 0 | G41: 0 | H41: 0 | I41: 0 | J41: 0 | K41: 0 | L41: 0 | M41: 0 | N41: 0 | O41: =SUM(C41:N41) -> 0
B42: Crowdfunding | C42: 0 | D42: 0 | E42: 0 | F42: 0 | G42: 0 | H42: 0 | I42: 0 | J42: 0 | K42: 0 | L42: 0 | M42: 0 | N42: 0 | O42: =SUM(C42:N42) -> 0
B43: Aplicações | C43: =SUM(C44:C46) -> 0 | D43: =SUM(D44:D46) -> 0 | E43: =SUM(E44:E46) -> 0 | F43: =SUM(F44:F46) -> 0 | G43: =SUM(G44:G46) -> 0 | H43: =SUM(H44:H46) -> 0 | I43: =SUM(I44:I46) -> 0 | J43: =SUM(J44:J46) -> 0 | ... N43: =SUM(N44:N46) -> 0 | O43: =SUM(C43:N43) -> 0
B44: Resgate Aplicações (Clube do Grito 2023) | C44: 0 | D44: 0 | E44: 0 | F44: 0 | G44: 0 | H44: 0 | I44: 0 | J44: 0 | K44: 0 | L44: 0 | M44: 0 | N44: 0 | O44: =SUM(C44:N44) -> 0
B45: Rendimentos Aplicações | C45: 0 | D45: 0 | E45: 0 | F45: 0 | G45: 0 | H45: 0 | I45: 0 | J45: 0 | K45: 0 | L45: 0 | M45: 0 | N45: 0 | O45: =SUM(C45:N45) -> 0
O46: =SUM(C46:N46) -> 0
B47: DESPESAS | C47: =SUM(C48,C50,C53,C75,C99,C105,C116,C120,C123,C126,C130,C133) -> 10600 | D47: =SUM(D48,D50,D53,D75,D99,D105,D116,D120,D123,D126,D130,D133) -> 61294.36 | E47: =SUM(E48,E50,E53,E75,E99,E105,E116,E120,E123,E126,E130,E133) -> 28252.36 | F47: =SUM(F48,F50,F53,F75,F99,F105,F116,F120,F123,F126,F130,F133) -> 27902.36 | G47: =SUM(G48,G50,G53,G75,G99,G105,G116,G120,G123,G126,G130,G133) -> 14602.36 | H47: =SUM(H48,H50,H53,H75,H99,H105,H116,H120,H123,H126,H130,H133) -> 64602.36 | I47: =SUM(I48,I50,I53,I75,I99,I105,I116,I120,I123,I126,I130,I133) -> 67102.36 | J47: =SUM(J48,J50,J53,J75,J99,J105,J116,J120,J123,J126,J130,J133) -> 14902.36 | ... N47: =SUM(N48,N50,N53,N75,N99,N105,N116,N120,N123,N126,N130,N133) -> 84750 | O47: =SUM(C47:N47) -> 451235.6
B48: Despesas Diretas | C48: =SUM(C49) -> 0 | D48: =SUM(D49) -> 0 | E48: =SUM(E49) -> 14650 | F48: =SUM(F49) -> 14000 | G48: =SUM(G49) -> 0 | H48: =SUM(H49) -> 0 | I48: =SUM(I49) -> 0 | J48: =SUM(J49) -> 0 | ... N48: =SUM(N49) -> 0 | O48: =SUM(C48:N48) -> 28650
B49: Compras Mercadorias Revenda | C49: 0 | D49: 0 | E49: 14650 | F49: 14000 | G49: 0 | H49: 0 | I49: 0 | J49: 0 | K49: 0 | L49: 0 | M49: 0 | N49: 0 | O49: =SUM(C49:N49) -> 28650
B50: Marketing | C50: =SUM(C51:C52) -> 0 | D50: =SUM(D51:D52) -> 20000 | E50: =SUM(E51:E52) -> 300 | F50: =SUM(F51:F52) -> 300 | G50: =SUM(G51:G52) -> 300 | H50: =SUM(H51:H52) -> 40300 | I50: =SUM(I51:I52) -> 40300 | J50: =SUM(J51:J52) -> 300 | ... N50: =SUM(N51:N52) -> 40300 | O50: =SUM(C50:N50) -> 143000
B51: Divulgação | C51: 0 | D51: 20000 | E51: 300 | F51: 300 | G51: 300 | H51: 40300 | I51: 40300 | J51: 300 | K51: 300 | L51: 300 | M51: 300 | N51: 40300 | O51: =SUM(C51:N51) -> 143000
B52: Vestuários | C52: 0 | D52: 0 | E52: 0 | F52: 0 | G52: 0 | H52: 0 | I52: 0 | J52: 0 | K52: 0 | L52: 0 | M52: 0 | N52: 0 | O52: =SUM(C52:N52) -> 0
B53: Despesas com Pessoal | C53: =SUM(C54:C74) -> 8600 | D53: =SUM(D54:D74) -> 8600 | E53: =SUM(E54:E74) -> 8600 | F53: =SUM(F54:F74) -> 8600 | G53: =SUM(G54:G74) -> 8600 | H53: =SUM(H54:H74) -> 8600 | I53: =SUM(I54:I74) -> 11100 | J53: =SUM(J54:J74) -> 8600 | ... N53: =SUM(N54:N74) -> 8600 | O53: =SUM(C53:N53) -> 105700
B54: Comissões | C54: 0 | D54: 0 | E54: 0 | F54: 0 | G54: 0 | H54: 0 | I54: 0 | J54: 0 | K54: 0 | L54: 0 | M54: 0 | N54: 0 | O54: =SUM(C54:N54) -> 0
B55: Férias | C55: 0 | D55: 0 | E55: 0 | F55: 0 | G55: 0 | H55: 0 | I55: 0 | J55: 0 | K55: 0 | L55: 0 | M55: 0 | N55: 0 | O55: =SUM(C55:N55) -> 0
B56: Rescisões | C56: 0 | D56: 0 | E56: 0 | F56: 0 | G56: 0 | H56: 0 | I56: 0 | J56: 0 | K56: 0 | L56: 0 | M56: 0 | N56: 0 | O56: =SUM(C56:N56) -> 0
B57: 13º Salário | C57: 0 | D57: 0 | E57: 0 | F57: 0 | G57: 0 | H57: 0 | I57: 0 | J57: 0 | K57: 0 | L57: 0 | M57: 0 | N57: 0 | O57: =SUM(C57:N57) -> 0
B58: INSS | C58: 0 | D58: 0 | E58: 0 | F58: 0 | G58: 0 | H58: 0 | I58: 0 | J58: 0 | K58: 0 | L58: 0 | M58: 0 | N58: 0 | O58: =SUM(C58:N58) -> 0
B59: FGTS | C59: 0 | D59: 0 | E59: 0 | F59: 0 | G59: 0 | H59: 0 | I59: 0 | J59: 0 | K59: 0 | L59: 0 | M59: 0 | N59: 0 | O59: =SUM(C59:N59) -> 0
B60: IRRF | C60: 0 | D60: 0 | E60: 0 | F60: 0 | G60: 0 | H60: 0 | I60: 0 | J60: 0 | K60: 0 | L60: 0 | M60: 0 | N60: 0 | O60: =SUM(C60:N60) -> 0
B61: Exames | C61: 0 | D61: 0 | E61: 0 | F61: 0 | G61: 0 | H61: 0 | I61: 0 | J61: 0 | K61: 0 | L61: 0 | M61: 0 | N61: 0 | O61: =SUM(C61:N61) -> 0
B62: Assistência Médica | C62: 0 | D62: 0 | E62: 0 | F62: 0 | G62: 0 | H62: 0 | I62: 0 | J62: 0 | K62: 0 | L62: 0 | M62: 0 | N62: 0 | O62: =SUM(C62:N62) -> 0
B63: Vale Transporte | C63: 0 | D63: 0 | E63: 0 | F63: 0 | G63: 0 | H63: 0 | I63: 0 | J63: 0 | K63: 0 | L63: 0 | M63: 0 | N63: 0 | O63: =SUM(C63:N63) -> 0
B64: Vale Refeição | C64: 400 | D64: 400 | E64: 400 | F64: 400 | G64: 400 | H64: 400 | I64: 400 | J64: 400 | K64: 400 | L64: 400 | M64: 400 | N64: 400 | O64: =SUM(C64:N64) -> 4800
B65: Seguro de Vida | C65: 0 | D65: 0 | E65: 0 | F65: 0 | G65: 0 | H65: 0 | I65: 0 | J65: 0 | K65: 0 | L65: 0 | M65: 0 | N65: 0 | O65: =SUM(C65:N65) -> 0
... B74: Ajuda de Custo | C74: 0 | D74: 0 | E74: 0 | F74: 0 | G74: 0 | H74: 0 | I74: 0 | J74: 0 | K74: 0 | L74: 0 | M74: 0 | N74: 0 | O74: =SUM(C74:N74) -> 0
B75: Despesas Administrativas | C75: =SUM(C76:C98) -> 1700 | D75: =SUM(D76:D98) -> 5194.36 | E75: =SUM(E76:E98) -> 3702.36 | F75: =SUM(F76:F98) -> 3702.36 | G75: =SUM(G76:G98) -> 4702.36 | H75: =SUM(H76:H98) -> 4702.36 | I75: =SUM(I76:I98) -> 4702.36 | J75: =SUM(J76:J98) -> 4702.36 | ... N75: =SUM(N76:N98) -> 50 | O75: =SUM(C75:N75) -> 45685.6
B76: Aluguel Espaços | C76: 0 | D76: 0 | E76: 0 | F76: 0 | G76: 0 | H76: 0 | I76: 0 | J76: 0 | K76: 0 | L76: 0 | M76: 0 | N76: 0 | O76: =SUM(C76:N76) -> 0
B77: Aluguel/Locações Outros | C77: 0 | D77: 0 | E77: 0 | F77: 0 | G77: 0 | H77: 0 | I77: 0 | J77: 0 | K77: 0 | L77: 0 | M77: 0 | N77: 0 | O77: =SUM(C77:N77) -> 0
B78: ÁGUA | C78: 0 | D78: 0 | E78: 0 | F78: 0 | G78: 0 | H78: 0 | I78: 0 | J78: 0 | K78: 0 | L78: 0 | M78: 0 | N78: 0 | O78: =SUM(C78:N78) -> 0
B79: Energia Elétrica | C79: 0 | D79: 0 | E79: 0 | F79: 0 | G79: 0 | H79: 0 | I79: 0 | J79: 0 | K79: 0 | L79: 0 | M79: 0 | N79: 0 | O79: =SUM(C79:N79) -> 0
B80: TELEFONIA/INTERNET | C80: 50 | D80: 50 | E80: 50 | F80: 50 | G80: 50 | H80: 50 | I80: 50 | J80: 50 | K80: 50 | L80: 50 | M80: 50 | N80: 50 | O80: =SUM(C80:N80) -> 600
B81: Material de Escritório | C81: 0 | D81: 0 | E81: 0 | F81: 0 | G81: 0 | H81: 0 | I81: 0 | J81: 0 | K81: 0 | L81: 0 | M81: 0 | N81: 0 | O81: =SUM(C81:N81) -> 0
B82: Gás | C82: 0 | D82: 0 | E82: 0 | F82: 0 | G82: 0 | H82: 0 | I82: 0 | J82: 0 | K82: 0 | L82: 0 | M82: 0 | N82: 0 | O82: =SUM(C82:N82) -> 0
B83: Seguros | C83: 0 | D83: 0 | E83: 0 | F83: 0 | G83: 0 | H83: 0 | I83: 0 | J83: 0 | K83: 0 | L83: 0 | M83: 0 | N83: 0 | O83: =SUM(C83:N83) -> 0
B84: IPTU | C84: 0 | D84: 0 | E84: 0 | F84: 0 | G84: 0 | H84: 0 | I84: 0 | J84: 0 | K84: 0 | L84: 0 | M84: 0 | N84: 0 | O84: =SUM(C84:N84) -> 0
B85: Contabilidade | C85: 0 | D85: 0 | E85: 0 | F85: 0 | G85: 0 | H85: 0 | I85: 0 | J85: 0 | K85: 0 | L85: 0 | M85: 0 | N85: 0 | O85: =SUM(C85:N85) -> 0
B86: Advogados | C86: 0 | D86: 0 | E86: 0 | F86: 0 | G86: 0 | H86: 0 | I86: 0 | J86: 0 | K86: 0 | L86: 0 | M86: 0 | N86: 0 | O86: =SUM(C86:N86) -> 0
B87: Segurança | C87: 0 | D87: 0 | E87: 0 | F87: 0 | G87: 0 | H87: 0 | I87: 0 | J87: 0 | K87: 0 | L87: 0 | M87: 0 | N87: 0 | O87: =SUM(C87:N87) -> 0
... B98: PRESTAÇÃO SERV. TERCEIROS | C98: 0 | D98: 0 | E98: 0 | F98: 0 | G98: 0 | H98: 0 | I98: 0 | J98: 0 | K98: 0 | L98: 0 | M98: 0 | N98: 0 | O98: =SUM(C98:N98) -> 0
B99: Despesas Financeiras / Bancos | C99: =SUM(C100:C104) -> 0 | D99: =SUM(D100:D104) -> 0 | E99: =SUM(E100:E104) -> 0 | F99: =SUM(F100:F104) -> 0 | G99: =SUM(G100:G104) -> 0 | H99: =SUM(H100:H104) -> 0 | I99: =SUM(I100:I104) -> 0 | J99: =SUM(J100:J104) -> 0 | ... N99: =SUM(N100:N104) -> 0 | O99: =SUM(C99:N99) -> 0
B100: Juros sobre Empréstimos | C100: 0 | D100: 0 | E100: 0 | F100: 0 | G100: 0 | H100: 0 | I100: 0 | J100: 0 | K100: 0 | L100: 0 | M100: 0 | N100: 0 | O100: =SUM(C100:N100) -> 0
B101: Multas | C101: 0 | D101: 0 | E101: 0 | F101: 0 | G101: 0 | H101: 0 | I101: 0 | J101: 0 | K101: 0 | L101: 0 | M101: 0 | N101: 0 | O101: =SUM(C101:N101) -> 0
B102: Pagamento de Empréstimos | C102: 0 | D102: 0 | E102: 0 | F102: 0 | G102: 0 | H102: 0 | I102: 0 | J102: 0 | K102: 0 | L102: 0 | M102: 0 | N102: 0 | O102: =SUM(C102:N102) -> 0
B103: Tarifas Bancárias | C103: 0 | D103: 0 | E103: 0 | F103: 0 | G103: 0 | H103: 0 | I103: 0 | J103: 0 | K103: 0 | L103: 0 | M103: 0 | N103: 0 | O103: =SUM(C103:N103) -> 0
B104: Despesas Bancárias | C104: 0 | D104: 0 | E104: 0 | F104: 0 | G104: 0 | H104: 0 | I104: 0 | J104: 0 | K104: 0 | L104: 0 | M104: 0 | N104: 0 | O104: =SUM(C104:N104) -> 0
B105: Impostos e Taxas | C105: =SUM(C106:C115) -> 0 | D105: =SUM(D106:D115) -> 0 | E105: =SUM(E106:E115) -> 0 | F105: =SUM(F106:F115) -> 0 | G105: =SUM(G106:G115) -> 0 | H105: =SUM(H106:H115) -> 0 | I105: =SUM(I106:I115) -> 0 | J105: =SUM(J106:J115) -> 0 | ... N105: =SUM(N106:N115) -> 0 | O105: =SUM(C105:N105) -> 0
B106: ICMS | C106: 0 | D106: 0 | E106: 0 | F106: 0 | G106: 0 | H106: 0 | I106: 0 | J106: 0 | K106: 0 | L106: 0 | M106: 0 | N106: 0 | O106: =SUM(C106:N106) -> 0
B107: IPI | C107: 0 | D107: 0 | E107: 0 | F107: 0 | G107: 0 | H107: 0 | I107: 0 | J107: 0 | K107: 0 | L107: 0 | M107: 0 | N107: 0 | O107: =SUM(C107:N107) -> 0
B108: PIS | C108: 0 | D108: 0 | E108: 0 | F108: 0 | G108: 0 | H108: 0 | I108: 0 | J108: 0 | K108: 0 | L108: 0 | M108: 0 | N108: 0 | O108: =SUM(C108:N108) -> 0
B109: COFINS | C109: 0 | D109: 0 | E109: 0 | F109: 0 | G109: 0 | H109: 0 | I109: 0 | J109: 0 | K109: 0 | L109: 0 | M109: 0 | N109: 0 | O109: =SUM(C109:N109) -> 0
B110: IRPJ | C110: 0 | D110: 0 | E110: 0 | F110: 0 | G110: 0 | H110: 0 | I110: 0 | J110: 0 | K110: 0 | L110: 0 | M110: 0 | N110: 0 | O110: =SUM(C110:N110) -> 0
B111: Contribuição Social | C111: 0 | D111: 0 | E111: 0 | F111: 0 | G111: 0 | H111: 0 | I111: 0 | J111: 0 | K111: 0 | L111: 0 | M111: 0 | N111: 0 | O111: =SUM(C111:N111) -> 0
B112: ISS | C112: 0 | D112: 0 | E112: 0 | F112: 0 | G112: 0 | H112: 0 | I112: 0 | J112: 0 | K112: 0 | L112: 0 | M112: 0 | N112: 0 | O112: =SUM(C112:N112) -> 0
B113: Simples Nacional (DAS) | C113: 0 | D113: 0 | E113: 0 | F113: 0 | G113: 0 | H113: 0 | I113: 0 | J113: 0 | K113: 0 | L113: 0 | M113: 0 | N113: 0 | O113: =SUM(C113:N113) -> 0
B114: IMPOSTOS/TAXAS | C114: 0 | D114: 0 | E114: 0 | F114: 0 | G114: 0 | H114: 0 | I114: 0 | J114: 0 | K114: 0 | L114: 0 | M114: 0 | N114: 0 | O114: =SUM(C114:N114) -> 0
B115: IOF | C115: 0 | D115: 0 | E115: 0 | F115: 0 | G115: 0 | H115: 0 | I115: 0 | J115: 0 | K115: 0 | L115: 0 | M115: 0 | N115: 0 | O115: =SUM(C115:N115) -> 0
B116: Investimento | C116: =SUM(C117:C119) -> 0 | D116: =SUM(D117:D119) -> 17500 | E116: =SUM(E117:E119) -> 0 | F116: =SUM(F117:F119) -> 0 | G116: =SUM(G117:G119) -> 0 | H116: =SUM(H117:H119) -> 0 | I116: =SUM(I117:I119) -> 0 | J116: =SUM(J117:J119) -> 0 | ... N116: =SUM(N117:N119) -> 0 | O116: =SUM(C116:N116) -> 17500
B117: Equipamentos de Informática | C117: 0 | D117: 0 | E117: 0 | F117: 0 | G117: 0 | H117: 0 | I117: 0 | J117: 0 | K117: 0 | L117: 0 | M117: 0 | N117: 0 | O117: =SUM(C117:N117) -> 0
B118: Móveis e Utensílios | C118: 0 | D118: 0 | E118: 0 | F118: 0 | G118: 0 | H118: 0 | I118: 0 | J118: 0 | K118: 0 | L118: 0 | M118: 0 | N118: 0 | O118: =SUM(C118:N118) -> 0
B119: Maq./Equipamentos | C119: 0 | D119: 17500 | E119: 0 | F119: 0 | G119: 0 | H119: 0 | I119: 0 | J119: 0 | K119: 0 | L119: 0 | M119: 0 | N119: 0 | O119: =SUM(C119:N119) -> 17500
B120: Outras Despesas | C120: =SUM(C121:C122) -> 0 | D120: =SUM(D121:D122) -> 0 | E120: =SUM(E121:E122) -> 0 | F120: =SUM(F121:F122) -> 0 | G120: =SUM(G121:G122) -> 0 | H120: =SUM(H121:H122) -> 0 | I120: =SUM(I121:I122) -> 0 | J120: =SUM(J121:J122) -> 0 | ... N120: =SUM(N121:N122) -> 0 | O120: =SUM(C120:N120) -> 0
...

Sheet FAVELA 3D
C1: INSTITUTO DE CAPACITACAO E ACAO SOCIAL O GRITO - PLANEJAMENTO 2025 - FAVELA 3D
A2: Emitido por RICARDO em 17/11/2023 10:58 | C2: =C47/O$47 -> 0.081926121 | D2: =D47/$O$47 -> 0.0823219 | E2: =E47/$O$47 -> 0.083377309 | F2: =F47/$O$47 -> 0.084036939 | G2: =G47/$O$47 -> 0.083377309 | H2: =H47/$O$47 -> 0.083377309 | I2: =I47/$O$47 -> 0.084036939 | J2: =J47/$O$47 -> 0.083377309 | K2: =K47/$O$47 -> 0.083377309 | ... N2: =N47/$O$47 -> 0.083377309
B3: CATEGORIA | C3: JANEIRO | D3: FEVEREIRO | E3: MARÇO | F3: ABRIL | G3: MAIO | H3: JUNHO | I3: JULHO | J3: AGOSTO | K3: SETEMBRO | L3: OUTUBRO | M3: NOVEMBRO | N3: DEZEMBRO | O3: TOTAL
B5: SALDO ACUMULADO | C5: =C6 -> -8600 | D5: =C5+D6 -> -17500 | E5: =D5+E6 -> -27200 | F5: =E5+F6 -> -37400 | G5: =F5+G6 -> -47100 | H5: =G5+H6 -> -56800 | I5: =H5+I6 -> -67000 | J5: =I5+J6 -> -76700 | K5: =J5+K6 -> -86400 | ... N5: =M5+N6 -> -116000
B6: SALDO MÊS | C6: =SUM(C8-C47) -> -8600 | D6: =SUM(D8-D47) -> -8900 | E6: =SUM(E8-E47) -> -9700 | F6: =SUM(F8-F47) -> -10200 | G6: =SUM(G8-G47) -> -9700 | H6: =SUM(H8-H47) -> -9700 | I6: =SUM(I8-I47) -> -10200 | J6: =SUM(J8-J47) -> -9700 | ... N6: =SUM(N8-N47) -> -9700 | O6: =SUM(C6:N6) -> -116000
B8: RECEITAS | C8: =SUM(C9,C16,C22,C28,C33,C37,C40,C43) -> 53500 | D8: =SUM(D9,D16,D22,D28,D33,D37,D40,D43) -> 53500 | E8: =SUM(E9,E16,E22,E28,E33,E37,E40,E43) -> 53500 | F8: =SUM(F9,F16,F22,F28,F33,F37,F40,F43) -> 53500 | G8: =SUM(G9,G16,G22,G28,G33,G37,G40,G43) -> 53500 | H8: =SUM(H9,H16,H22,H28,H33,H37,H40,H43) -> 53500 | I8: =SUM(I9,I16,I22,I28,I33,I37,I40,I43) -> 53500 | J8: =SUM(J9,J16,J22,J28,J33,J37,J40,J43) -> 53500 | ... N8: =SUM(N9,N16,N22,N28,N33,N37,N40,N43) -> 53500 | O8: =SUM(C8:N8) -> 642000
B9: Devoluções | C9: =SUM(C10:C15) -> 0 | D9: =SUM(D10:D15) -> 0 | E9: =SUM(E10:E15) -> 0 | F9: =SUM(F10:F15) -> 0 | G9: =SUM(G10:G15) -> 0 | H9: =SUM(H10:H15) -> 0 | I9: =SUM(I10:I15) -> 0 | J9: =SUM(J10:J15) -> 0 | ... N9: =SUM(N10:N15) -> 0 | O9: =SUM(C9:N9) -> 0
B10: Devoluções Compra Mercadoria Revenda | C10: 0 | D10: 0 | E10: 0 | F10: 0 | G10: 0 | H10: 0 | I10: 0 | J10: 0 | K10: 0 | L10: 0 | M10: 0 | N10: 0 | O10: =SUM(C10:N10) -> 0
B11: Devoluções de Compra Material Consumo | C11: 0 | D11: 0 | E11: 0 | F11: 0 | G11: 0 | H11: 0 | I11: 0 | J11: 0 | K11: 0 | L11: 0 | M11: 0 | N11: 0 | O11: =SUM(C11:N11) -> 0
B12: Devoluções de Compra de Matéria Prima | C12: 0 | D12: 0 | E12: 0 | F12: 0 | G12: 0 | H12: 0 | I12: 0 | J12: 0 | K12: 0 | L12: 0 | M12: 0 | N12: 0 | O12: =SUM(C12:N12) -> 0
B13: Devoluções de Compra de Ativo | C13: 0 | D13: 0 | E13: 0 | F13: 0 | G13: 0 | H13: 0 | I13: 0 | J13: 0 | K13: 0 | L13: 0 | M13: 0 | N13: 0 | O13: =SUM(C13:N13) -> 0
B14: Devoluções de Compra de Serviços | C14: 0 | D14: 0 | E14: 0 | F14: 0 | G14: 0 | H14: 0 | I14: 0 | J14: 0 | K14: 0 | L14: 0 | M14: 0 | N14: 0 | O14: =SUM(C14:N14) -> 0
B15: Devolução de Doações | C15: 0 | D15: 0 | E15: 0 | F15: 0 | G15: 0 | H15: 0 | I15: 0 | J15: 0 | K15: 0 | L15: 0 | M15: 0 | N15: 0 | O15: =SUM(C15:N15) -> 0
B16: Outras Entradas | C16: =SUM(C17:C21) -> 0 | D16: =SUM(D17:D21) -> 0 | E16: =SUM(E17:E21) -> 0 | F16: =SUM(F17:F21) -> 0 | G16: =SUM(G17:G21) -> 0 | H16: =SUM(H17:H21) -> 0 | I16: =SUM(I17:I21) -> 0 | J16: =SUM(J17:J21) -> 0 | ... N16: =SUM(N17:N21) -> 0 | O16: =SUM(C16:N16) -> 0
B17: Empréstimos Bancários | C17: 0 | D17: 0 | E17: 0 | F17: 0 | G17: 0 | H17: 0 | I17: 0 | J17: 0 | K17: 0 | L17: 0 | M17: 0 | N17: 0 | O17: =SUM(C17:N17) -> 0
B18: Aumento de Capital | C18: 0 | D18: 0 | E18: 0 | F18: 0 | G18: 0 | H18: 0 | I18: 0 | J18: 0 | K18: 0 | L18: 0 | M18: 0 | N18: 0 | O18: =SUM(C18:N18) -> 0
B19: Venda de Ativos | C19: 0 | D19: 0 | E19: 0 | F19: 0 | G19: 0 | H19: 0 | I19: 0 | J19: 0 | K19: 0 | L19: 0 | M19: 0 | N19: 0 | O19: =SUM(C19:N19) -> 0
B20: AJUSTE DE CAIXA | C20: 0 | D20: 0 | E20: 0 | F20: 0 | G20: 0 | H20: 0 | I20: 0 | J20: 0 | K20: 0 | L20: 0 | M20: 0 | N20: 0 | O20: =SUM(C20:N20) -> 0
B21: Prêmios de Seguros / Sinistros | C21: 0 | D21: 0 | E21: 0 | F21: 0 | G21: 0 | H21: 0 | I21: 0 | J21: 0 | K21: 0 | L21: 0 | M21: 0 | N21: 0 | O21: =SUM(C21:N21) -> 0
B22: Doações | C22: =SUM(C23:C27) -> 0 | D22: =SUM(D23:D27) -> 0 | E22: =SUM(E23:E27) -> 0 | F22: =SUM(F23:F27) -> 0 | G22: =SUM(G23:G27) -> 0 | H22: =SUM(H23:H27) -> 0 | I22: =SUM(I23:I27) -> 0 | J22: =SUM(J23:J27) -> 0 | ... N22: =SUM(N23:N27) -> 0 | O22: =SUM(C22:N22) -> 0
B23: Doações Recorrentes | C23: 0 | D23: 0 | E23: 0 | F23: 0 | G23: 0 | H23: 0 | I23: 0 | J23: 0 | K23: 0 | L23: 0 | M23: 0 | N23: 0 | O23: =SUM(C23:N23) -> 0
B24: Doações Pontuais PF | C24: 0 | D24: 0 | E24: 0 | F24: 0 | G24: 0 | H24: 0 | I24: 0 | J24: 0 | K24: 0 | L24: 0 | M24: 0 | N24: 0 | O24: =SUM(C24:N24) -> 0
B25: Doações Pontuais PJ | C25: 0 | D25: 0 | E25: 0 | F25: 0 | G25: 0 | H25: 0 | I25: 0 | J25: 0 | K25: 0 | L25: 0 | M25: 0 | N25: 0 | O25: =SUM(C25:N25) -> 0
B26: Sócio Doador | C26: 0 | D26: 0 | E26: 0 | F26: 0 | G26: 0 | H26: 0 | I26: 0 | J26: 0 | K26: 0 | L26: 0 | M26: 0 | N26: 0 | O26: =SUM(C26:N26) -> 0
B27: Patrocínios | C27: 0 | D27: 0 | E27: 0 | F27: 0 | G27: 0 | H27: 0 | I27: 0 | J27: 0 | K27: 0 | L27: 0 | M27: 0 | N27: 0 | O27: =SUM(C27:N27) -> 0
B28: Gerando Falcões | C28: =SUM(C29:C32) -> 53500 | D28: =SUM(D29:D32) -> 53500 | E28: =SUM(E29:E32) -> 53500 | F28: =SUM(F29:F32) -> 53500 | G28: =SUM(G29:G32) -> 53500 | H28: =SUM(H29:H32) -> 53500 | I28: =SUM(I29:I32) -> 53500 | J28: =SUM(J29:J32) -> 53500 | ... N28: =SUM(N29:N32) -> 53500 | O28: =SUM(C28:N28) -> 642000
B29: Aporte | C29: 53500 | D29: 53500 | E29: 53500 | F29: 53500 | G29: 53500 | H29: 53500 | I29: 53500 | J29: 53500 | K29: 53500 | L29: 53500 | M29: 53500 | N29: 53500 | O29: =SUM(C29:N29) -> 642000
B30: Falcons Univercity | C30: 0 | D30: 0 | E30: 0 | F30: 0 | G30: 0 | H30: 0 | I30: 0 | J30: 0 | K30: 0 | L30: 0 | M30: 0 | N30: 0 | O30: =SUM(C30:N30) -> 0
B31: Regional GF | C31: 0 | D31: 0 | E31: 0 | F31: 0 | G31: 0 | H31: 0 | I31: 0 | J31: 0 | K31: 0 | L31: 0 | M31: 0 | N31: 0 | O31: =SUM(C31:N31) -> 0
B32: Favela 3D | C32: 0 | D32: 0 | E32: 0 | F32: 0 | G32: 0 | H32: 0 | I32: 0 | J32: 0 | K32: 0 | L32: 0 | M32: 0 | N32: 0 | O32: =SUM(C32:N32) -> 0
B33: Editais/Projetos | C33: =SUM(C34:C36) -> 0 | D33: =SUM(D34:D36) -> 0 | E33: =SUM(E34:E36) -> 0 | F33: =SUM(F34:F36) -> 0 | G33: =SUM(G34:G36) -> 0 | H33: =SUM(H34:H36) -> 0 | I33: =SUM(I34:I36) -> 0 | J33: =SUM(J34:J36) -> 0 | ... N33: =SUM(N34:N36) -> 0 | O33: =SUM(C33:N33) -> 0
B34: Ecogaiola | C34: 0 | D34: 0 | E34: 0 | F34: 0 | G34: 0 | H34: 0 | I34: 0 | J34: 0 | K34: 0 | L34: 0 | M34: 0 | N34: 0 | O34: =SUM(C34:N34) -> 0
B35: Prog. Hab. Polaris | C35: 0 | D35: 0 | E35: 0 | F35: 0 | G35: 0 | H35: 0 | I35: 0 | J35: 0 | K35: 0 | L35: 0 | M35: 0 | N35: 0 | O35: =SUM(C35:N35) -> 0
B36: Lei De Incentivo | C36: 0 | D36: 0 | E36: 0 | F36: 0 | G36: 0 | H36: 0 | I36: 0 | J36: 0 | K36: 0 | L36: 0 | M36: 0 | N36: 0 | O36: =SUM(C36:N36) -> 0
B37: Negócios Sociais | C37: =SUM(C38:C39) -> 0 | D37: =SUM(D38:D39) -> 0 | E37: =SUM(E38:E39) -> 0 | F37: =SUM(F38:F39) -> 0 | G37: =SUM(G38:G39) -> 0 | H37: =SUM(H38:H39) -> 0 | I37: =SUM(I38:I39) -> 0 | J37: =SUM(J38:J39) -> 0 | ... N37: =SUM(N38:N39) -> 0 | O37: =SUM(C37:N37) -> 0
B38: Vendas Outlet | C38: 0 | D38: 0 | E38: 0 | F38: 0 | G38: 0 | H38: 0 | I38: 0 | J38: 0 | K38: 0 | L38: 0 | M38: 0 | N38: 0 | O38: =SUM(C38:N38) -> 0
B39: Vendas Griffte | C39: 0 | D39: 0 | E39: 0 | F39: 0 | G39: 0 | H39: 0 | I39: 0 | J39: 0 | K39: 0 | L39: 0 | M39: 0 | N39: 0 | O39: =SUM(C39:N39) -> 0
B40: Eventos | C40: =SUM(C41:C42) -> 0 | D40: =SUM(D41:D42) -> 0 | E40: =SUM(E41:E42) -> 0 | F40: =SUM(F41:F42) -> 0 | G40: =SUM(G41:G42) -> 0 | H40: =SUM(H41:H42) -> 0 | I40: =SUM(I41:I42) -> 0 | J40: =SUM(J41:J42) -> 0 | ... N40: =SUM(N41:N42) -> 0 | O40: =SUM(C40:N40) -> 0
B41: Clube Do Grito | C41: 0 | D41: 0 | E41: 0 | F41: 0 | G41: 0 | H41: 0 | I41: 0 | J41: 0 | K41: 0 | L41: 0 | M41: 0 | N41: 0 | O41: =SUM(C41:N41) -> 0
B42: Crowdfunding | C42: 0 | D42: 0 | E42: 0 | F42: 0 | G42: 0 | H42: 0 | I42: 0 | J42: 0 | K42: 0 | L42: 0 | M42: 0 | N42: 0 | O42: =SUM(C42:N42) -> 0
B43: Aplicações | C43: =SUM(C44:C46) -> 0 | D43: =SUM(D44:D46) -> 0 | E43: =SUM(E44:E46) -> 0 | F43: =SUM(F44:F46) -> 0 | G43: =SUM(G44:G46) -> 0 | H43: =SUM(H44:H46) -> 0 | I43: =SUM(I44:I46) -> 0 | J43: =SUM(J44:J46) -> 0 | ... N43: =SUM(N44:N46) -> 0 | O43: =SUM(C43:N43) -> 0
B44: Resgate Aplicações (Clube do Grito 2023) | C44: 0 | D44: 0 | E44: 0 | F44: 0 | G44: 0 | H44: 0 | I44: 0 | J44: 0 | K44: 0 | L44: 0 | M44: 0 | N44: 0 | O44: =SUM(C44:N44) -> 0
B45: Rendimentos Aplicações | C45: 0 | D45: 0 | E45: 0 | F45: 0 | G45: 0 | H45: 0 | I45: 0 | J45: 0 | K45: 0 | L45: 0 | M45: 0 | N45: 0 | O45: =SUM(C45:N45) -> 0
O46: =SUM(C46:N46) -> 0
B47: DESPESAS | C47: =SUM(C48,C50,C53,C75,C99,C105,C116,C120,C123,C126,C130,C133) -> 62100 | D47: =SUM(D48,D50,D53,D75,D99,D105,D116,D120,D123,D126,D130,D133) -> 62400 | E47: =SUM(E48,E50,E53,E75,E99,E105,E116,E120,E123,E126,E130,E133) -> 63200 | F47: =SUM(F48,F50,F53,F75,F99,F105,F116,F120,F123,F126,F130,F133) -> 63700 | G47: =SUM(G48,G50,G53,G75,G99,G105,G116,G120,G123,G126,G130,G133) -> 63200 | H47: =SUM(H48,H50,H53,H75,H99,H105,H116,H120,H123,H126,H130,H133) -> 63200 | I47: =SUM(I48,I50,I53,I75,I99,I105,I116,I120,I123,I126,I130,I133) -> 63700 | J47: =SUM(J48,J50,J53,J75,J99,J105,J116,J120,J123,J126,J130,J133) -> 63200 | ... N47: =SUM(N48,N50,N53,N75,N99,N105,N116,N120,N123,N126,N130,N133) -> 63200 | O47: =SUM(C47:N47) -> 758000
B48: Despesas Diretas | C48: =SUM(C49) -> 0 | D48: =SUM(D49) -> 0 | E48: =SUM(E49) -> 0 | F48: =SUM(F49) -> 0 | G48: =SUM(G49) -> 0 | H48: =SUM(H49) -> 0 | I48: =SUM(I49) -> 0 | J48: =SUM(J49) -> 0 | ... N48: =SUM(N49) -> 0 | O48: =SUM(C48:N48) -> 0
B49: Compras Mercadorias Revenda | C49: 0 | D49: 0 | E49: 0 | F49: 0 | G49: 0 | H49: 0 | I49: 0 | J49: 0 | K49: 0 | L49: 0 | M49: 0 | N49: 0 | O49: =SUM(C49:N49) -> 0
B50: Marketing | C50: =SUM(C51:C52) -> 0 | D50: =SUM(D51:D52) -> 0 | E50: =SUM(E51:E52) -> 200 | F50: =SUM(F51:F52) -> 200 | G50: =SUM(G51:G52) -> 200 | H50: =SUM(H51:H52) -> 200 | I50: =SUM(I51:I52) -> 200 | J50: =SUM(J51:J52) -> 200 | ... N50: =SUM(N51:N52) -> 200 | O50: =SUM(C50:N50) -> 2000
B51: Divulgação | C51: 0 | D51: 0 | E51: 200 | F51: 200 | G51: 200 | H51: 200 | I51: 200 | J51: 200 | K51: 200 | L51: 200 | M51: 200 | N51: 200 | O51: =SUM(C51:N51) -> 2000
B52: Vestuários | C52: 0 | D52: 0 | E52: 0 | F52: 0 | G52: 0 | H52: 0 | I52: 0 | J52: 0 | K52: 0 | L52: 0 | M52: 0 | N52: 0 | O52: =SUM(C52:N52) -> 0
B53: Despesas com Pessoal | C53: =SUM(C54:C74) -> 61750 | D53: =SUM(D54:D74) -> 61750 | E53: =SUM(E54:E74) -> 61750 | F53: =SUM(F54:F74) -> 61750 | G53: =SUM(G54:G74) -> 61750 | H53: =SUM(H54:H74) -> 61750 | I53: =SUM(I54:I74) -> 61750 | J53: =SUM(J54:J74) -> 61750 | ... N53: =SUM(N54:N74) -> 61750 | O53: =SUM(C53:N53) -> 741000
B54: Comissões | C54: 0 | D54: 0 | E54: 0 | F54: 0 | G54: 0 | H54: 0 | I54: 0 | J54: 0 | K54: 0 | L54: 0 | M54: 0 | N54: 0 | O54: =SUM(C54:N54) -> 0
B55: Férias | C55: 0 | D55: 0 | E55: 0 | F55: 0 | G55: 0 | H55: 0 | I55: 0 | J55: 0 | K55: 0 | L55: 0 | M55: 0 | N55: 0 | O55: =SUM(C55:N55) -> 0
B56: Rescisões | C56: 0 | D56: 0 | E56: 0 | F56: 0 | G56: 0 | H56: 0 | I56: 0 | J56: 0 | K56: 0 | L56: 0 | M56: 0 | N56: 0 | O56: =SUM(C56:N56) -> 0
B57: 13º Salário | C57: 0 | D57: 0 | E57: 0 | F57: 0 | G57: 0 | H57: 0 | I57: 0 | J57: 0 | K57: 0 | L57: 0 | M57: 0 | N57: 0 | O57: =SUM(C57:N57) -> 0
B58: INSS | C58: 3000 | D58: 3000 | E58: 3000 | F58: 3000 | G58: 3000 | H58: 3000 | I58: 3000 | J58: 3000 | K58: 3000 | L58: 3000 | M58: 3000 | N58: 3000 | O58: =SUM(C58:N58) -> 36000
B59: FGTS | C59: 800 | D59: 800 | E59: 800 | F59: 800 | G59: 800 | H59: 800 | I59: 800 | J59: 800 | K59: 800 | L59: 800 | M59: 800 | N59: 800 | O59: =SUM(C59:N59) -> 9600
B60: IRRF | C60: 0 | D60: 0 | E60: 0 | F60: 0 | G60: 0 | H60: 0 | I60: 0 | J60: 0 | K60: 0 | L60: 0 | M60: 0 | N60: 0 | O60: =SUM(C60:N60) -> 0
B61: Exames | C61: 0 | D61: 0 | E61: 0 | F61: 0 | G61: 0 | H61: 0 | I61: 0 | J61: 0 | K61: 0 | L61: 0 | M61: 0 | N61: 0 | O61: =SUM(C61:N61) -> 0
B62: Assistência Médica | C62: 0 | D62: 0 | E62: 0 | F62: 0 | G62: 0 | H62: 0 | I62: 0 | J62: 0 | K62: 0 | L62: 0 | M62: 0 | N62: 0 | O62: =SUM(C62:N62) -> 0
B63: Vale Transporte | C63: 1200 | D63: 1200 | E63: 1200 | F63: 1200 | G63: 1200 | H63: 1200 | I63: 1200 | J63: 1200 | K63: 1200 | L63: 1200 | M63: 1200 | N63: 1200 | O63: =SUM(C63:N63) -> 14400
B64: Vale Refeição | C64: 1200 | D64: 1200 | E64: 1200 | F64: 1200 | G64: 1200 | H64: 1200 | I64: 1200 | J64: 1200 | K64: 1200 | L64: 1200 | M64: 1200 | N64: 1200 | O64: =SUM(C64:N64) -> 14400
B65: Seguro de Vida | C65: 50 | D65: 50 | E65: 50 | F65: 50 | G65: 50 | H65: 50 | I65: 50 | J65: 50 | K65: 50 | L65: 50 | M65: 50 | N65: 50 | O65: =SUM(C65:N65) -> 600
B66: Outros Benefícios | C66: 0 | D66: 0 | E66: 0 | F66: 0 | G66: 0 | H66: 0 | I66: 0 | J66: 0 | K66: 0 | L66: 0 | M66: 0 | N66: 0 | O66: =SUM(C66:N66) -> 0 | R66: 12000
B67: Salários PJ | C67: 48000 | D67: 48000 | E67: 48000 | F67: 48000 | G67: 48000 | H67: 48000 | I67: 48000 | J67: 48000 | K67: 48000 | L67: 48000 | M67: 48000 | N67: 48000 | O67: =SUM(C67:N67) -> 576000
B68: Salários PF | C68: 7500 | D68: 7500 | E68: 7500 | F68: 7500 | G68: 7500 | H68: 7500 | I68: 7500 | J68: 7500 | K68: 7500 | L68: 7500 | M68: 7500 | N68: 7500 | O68: =SUM(C68:N68) -> 90000
B69: Encargos | C69: 0 | D69: 0 | E69: 0 | F69: 0 | G69: 0 | H69: 0 | I69: 0 | J69: 0 | K69: 0 | L69: 0 | M69: 0 | N69: 0 | O69: =SUM(C69:N69) -> 0
B70: Cursos/Treinamentos | C70: 0 | D70: 0 | E70: 0 | F70: 0 | G70: 0 | H70: 0 | I70: 0 | J70: 0 | K70: 0 | L70: 0 | M70: 0 | N70: 0 | O70: =SUM(C70:N70) -> 0
B71: Alimentação | C71: 0 | D71: 0 | E71: 0 | F71: 0 | G71: 0 | H71: 0 | I71: 0 | J71: 0 | K71: 0 | L71: 0 | M71: 0 | N71: 0 | O71: =SUM(C71:N71) -> 0
B72: Bonificações | C72: 0 | D72: 0 | E72: 0 | F72: 0 | G72: 0 | H72: 0 | I72: 0 | J72: 0 | K72: 0 | L72: 0 | M72: 0 | N72: 0 | O72: =SUM(C72:N72) -> 0
B73: Despesas Com Viagens | C73: 0 | D73: 0 | E73: 0 | F73: 0 | G73: 0 | H73: 0 | I73: 0 | J73: 0 | K73: 0 | L73: 0 | M73: 0 | N73: 0 | O73: =SUM(C73:N73) -> 0
B74: Ajuda de Custo | C74: 0 | D74: 0 | E74: 0 | F74: 0 | G74: 0 | H74: 0 | I74: 0 | J74: 0 | K74: 0 | L74: 0 | M74: 0 | N74: 0 | O74: =SUM(C74:N74) -> 0
B75: Despesas Administrativas | C75: =SUM(C76:C98) -> 350 | D75: =SUM(D76:D98) -> 650 | E75: =SUM(E76:E98) -> 1250 | F75: =SUM(F76:F98) -> 1750 | G75: =SUM(G76:G98) -> 1250 | H75: =SUM(H76:H98) -> 1250 | I75: =SUM(I76:I98) -> 1750 | J75: =SUM(J76:J98) -> 1250 | ... N75: =SUM(N76:N98) -> 1250 | O75: =SUM(C75:N75) -> 15000
B76: Aluguel Espaços | C76: 0 | D76: 300 | E76: 300 | F76: 300 | G76: 300 | H76: 300 | I76: 300 | J76: 300 | K76: 300 | L76: 300 | M76: 300 | N76: 300 | O76: =SUM(C76:N76) -> 3300
B77: Aluguel/Locações Outros | C77: 0 | D77: 0 | E77: 0 | F77: 0 | G77: 0 | H77: 0 | I77: 0 | J77: 0 | K77: 0 | L77: 0 | M77: 0 | N77: 0 | O77: =SUM(C77:N77) -> 0
B78: ÁGUA | C78: 0 | D78: 0 | E78: 0 | F78: 0 | G78: 0 | H78: 0 | I78: 0 | J78: 0 | K78: 0 | L78: 0 | M78: 0 | N78: 0 | O78: =SUM(C78:N78) -> 0
B79: Energia Elétrica | C79: 0 | D79: 0 | E79: 0 | F79: 0 | G79: 0 | H79: 0 | I79: 0 | J79: 0 | K79: 0 | L79: 0 | M79: 0 | N79: 0 | O79: =SUM(C79:N79) -> 0
B80: TELEFONIA/INTERNET | C80: 350 | D80: 350 | E80: 350 | F80: 350 | G80: 350 | H80: 350 | I80: 350 | J80: 350 | K80: 350 | L80: 350 | M80: 350 | N80: 350 | O80: =SUM(C80:N80) -> 4200
B81: Material de Escritório | C81: 0 | D81: 0 | E81: 0 | F81: 500 | G81: 0 | H81: 0 | I81: 500 | J81: 0 | K81: 0 | L81: 500 | M81: 0 | N81: 0 | O81: =SUM(C81:N81) -> 1500
B82: Gás | C82: 0 | D82: 0 | E82: 0 | F82: 0 | G82: 0 | H82: 0 | I82: 0 | J82: 0 | K82: 0 | L82: 0 | M82: 0 | N82: 0 | O82: =SUM(C82:N82) -> 0
B83: Seguros | C83: 0 | D83: 0 | E83: 0 | F83: 0 | G83: 0 | H83: 0 | I83: 0 | J83: 0 | K83: 0 | L83: 0 | M83: 0 | N83: 0 | O83: =SUM(C83:N83) -> 0
B84: IPTU | C84: 0 | D84: 0 | E84: 0 | F84: 0 | G84: 0 | H84: 0 | I84: 0 | J84: 0 | K84: 0 | L84: 0 | M84: 0 | N84: 0 | O84: =SUM(C84:N84) -> 0
B85: Contabilidade | C85: 0 | D85: 0 | E85: 0 | F85: 0 | G85: 0 | H85: 0 | I85: 0 | J85: 0 | K85: 0 | L85: 0 | M85: 0 | N85: 0 | O85: =SUM(C85:N85) -> 0
B86: Advogados | C86: 0 | D86: 0 | E86: 0 | F86: 0 | G86: 0 | H86: 0 | I86: 0 | J86: 0 | K86: 0 | L86: 0 | M86: 0 | N86: 0 | O86: =SUM(C86:N86) -> 0
B87: Segurança | C87: 0 | D87: 0 | E87: 0 | F87: 0 | G87: 0 | H87: 0 | I87: 0 | J87: 0 | K87: 0 | L87: 0 | M87: 0 | N87: 0 | O87: =SUM(C87:N87) -> 0
... B98: PRESTAÇÃO SERV. TERCEIROS | C98: 0 | D98: 0 | E98: 0 | F98: 0 | G98: 0 | H98: 0 | I98: 0 | J98: 0 | K98: 0 | L98: 0 | M98: 0 | N98: 0 | O98: =SUM(C98:N98) -> 0
B99: Despesas Financeiras / Bancos | C99: =SUM(C100:C104) -> 0 | D99: =SUM(D100:D104) -> 0 | E99: =SUM(E100:E104) -> 0 | F99: =SUM(F100:F104) -> 0 | G99: =SUM(G100:G104) -> 0 | H99: =SUM(H100:H104) -> 0 | I99: =SUM(I100:I104) -> 0 | J99: =SUM(J100:J104) -> 0 | ... N99: =SUM(N100:N104) -> 0 | O99: =SUM(C99:N99) -> 0
B100: Juros sobre Empréstimos | C100: 0 | D100: 0 | E100: 0 | F100: 0 | G100: 0 | H100: 0 | I100: 0 | J100: 0 | K100: 0 | L100: 0 | M100: 0 | N100: 0 | O100: =SUM(C100:N100) -> 0
B101: Multas | C101: 0 | D101: 0 | E101: 0 | F101: 0 | G101: 0 | H101: 0 | I101: 0 | J101: 0 | K101: 0 | L101: 0 | M101: 0 | N101: 0 | O101: =SUM(C101:N101) -> 0
B102: Pagamento de Empréstimos | C102: 0 | D102: 0 | E102: 0 | F102: 0 | G102: 0 | H102: 0 | I102: 0 | J102: 0 | K102: 0 | L102: 0 | M102: 0 | N102: 0 | O102: =SUM(C102:N102) -> 0
B103: Tarifas Bancárias | C103: 0 | D103: 0 | E103: 0 | F103: 0 | G103: 0 | H103: 0 | I103: 0 | J103: 0 | K103: 0 | L103: 0 | M103: 0 | N103: 0 | O103: =SUM(C103:N103) -> 0
B104: Despesas Bancárias | C104: 0 | D104: 0 | E104: 0 | F104: 0 | G104: 0 | H104: 0 | I104: 0 | J104: 0 | K104: 0 | L104: 0 | M104: 0 | N104: 0 | O104: =SUM(C104:N104) -> 0
B105: Impostos e Taxas | C105: =SUM(C106:C115) -> 0 | D105: =SUM(D106:D115) -> 0 | E105: =SUM(E106:E115) -> 0 | F105: =SUM(F106:F115) -> 0 | G105: =SUM(G106:G115) -> 0 | H105: =SUM(H106:H115) -> 0 | I105: =SUM(I106:I115) -> 0 | J105: =SUM(J106:J115) -> 0 | ... N105: =SUM(N106:N115) -> 0 | O105: =SUM(C105:N105) -> 0
B106: ICMS | C106: 0 | D106: 0 | E106: 0 | F106: 0 | G106: 0 | H106: 0 | I106: 0 | J106: 0 | K106: 0 | L106: 0 | M106: 0 | N106: 0 | O106: =SUM(C106:N106) -> 0
B107: IPI | C107: 0 | D107: 0 | E107: 0 | F107: 0 | G107: 0 | H107: 0 | I107: 0 | J107: 0 | K107: 0 | L107: 0 | M107: 0 | N107: 0 | O107: =SUM(C107:N107) -> 0
B108: PIS | C108: 0 | D108: 0 | E108: 0 | F108: 0 | G108: 0 | H108: 0 | I108: 0 | J108: 0 | K108: 0 | L108: 0 | M108: 0 | N108: 0 | O108: =SUM(C108:N108) -> 0
B109: COFINS | C109: 0 | D109: 0 | E109: 0 | F109: 0 | G109: 0 | H109: 0 | I109: 0 | J109: 0 | K109: 0 | L109: 0 | M109: 0 | N109: 0 | O109: =SUM(C109:N109) -> 0
B110: IRPJ | C110: 0 | D110: 0 | E110: 0 | F110: 0 | G110: 0 | H110: 0 | I110: 0 | J110: 0 | K110: 0 | L110: 0 | M110: 0 | N110: 0 | O110: =SUM(C110:N110) -> 0
B111: Contribuição Social | C111: 0 | D111: 0 | E111: 0 | F111: 0 | G111: 0 | H111: 0 | I111: 0 | J111: 0 | K111: 0 | L111: 0 | M111: 0 | N111: 0 | O111: =SUM(C111:N111) -> 0
B112: ISS | C112: 0 | D112: 0 | E112: 0 | F112: 0 | G112: 0 | H112: 0 | I112: 0 | J112: 0 | K112: 0 | L112: 0 | M112: 0 | N112: 0 | O112: =SUM(C112:N112) -> 0
...

Sheet COMERCIAL
C1: INSTITUTO DE CAPACITACAO E ACAO SOCIAL O GRITO - PLANEJAMENTO 2025 - NEGOCIOS SOCIAIS
A2: Emitido por RICARDO em 17/11/2023 10:58 | C2: =C47/O$47 -> 0.096862023 | D2: =D47/$O$47 -> 0.081779362 | E2: =E47/$O$47 -> 0.08217112 | F2: =F47/$O$47 -> 0.083346392 | G2: =G47/$O$47 -> 0.082014417 | H2: =H47/$O$47 -> 0.081975241 | I2: =I47/$O$47 -> 0.081779362 | J2: =J47/$O$47 -> 0.081779362 | K2: =K47/$O$47 -> 0.081975241 | ... N2: =N47/$O$47 -> 0.082562877
B3: CATEGORIA | C3: JANEIRO | D3: FEVEREIRO | E3: MARÇO | F3: ABRIL | G3: MAIO | H3: JUNHO | I3: JULHO | J3: AGOSTO | K3: SETEMBRO | L3: OUTUBRO | M3: NOVEMBRO | N3: DEZEMBRO | O3: TOTAL
B5: SALDO ACUMULADO | C5: =C6 -> -8225 | D5: =C5+D6 -> 400 | E5: =D5+E6 -> 8925 | F5: =E5+F6 -> 17150 | G5: =F5+G6 -> 25715 | H5: =G5+H6 -> 34290 | I5: =H5+I6 -> 42915 | J5: =I5+J6 -> 51540 | K5: =J5+K6 -> 60115 | ... N5: =M5+N6 -> 72740
B6: SALDO MÊS | C6: =SUM(C8-C47) -> -8225 | D6: =SUM(D8-D47) -> 8625 | E6: =SUM(E8-E47) -> 8525 | F6: =SUM(F8-F47) -> 8225 | G6: =SUM(G8-G47) -> 8565 | H6: =SUM(H8-H47) -> 8575 | I6: =SUM(I8-I47) -> 8625 | J6: =SUM(J8-J47) -> 8625 | ... N6: =SUM(N8-N47) -> -4575 | O6: =SUM(C6:N6) -> 72740
B8: RECEITAS | C8: =SUM(C9,C16,C22,C28,C33,C37,C40,C43) -> 16500 | D8: =SUM(D9,D16,D22,D28,D33,D37,D40,D43) -> 29500 | E8: =SUM(E9,E16,E22,E28,E33,E37,E40,E43) -> 29500 | F8: =SUM(F9,F16,F22,F28,F33,F37,F40,F43) -> 29500 | G8: =SUM(G9,G16,G22,G28,G33,G37,G40,G43) -> 29500 | H8: =SUM(H9,H16,H22,H28,H33,H37,H40,H43) -> 29500 | I8: =SUM(I9,I16,I22,I28,I33,I37,I40,I43) -> 29500 | J8: =SUM(J9,J16,J22,J28,J33,J37,J40,J43) -> 29500 | ... N8: =SUM(N9,N16,N22,N28,N33,N37,N40,N43) -> 16500 | O8: =SUM(C8:N8) -> 328000
B9: Devoluções | C9: =SUM(C10:C15) -> 0 | D9: =SUM(D10:D15) -> 0 | E9: =SUM(E10:E15) -> 0 | F9: =SUM(F10:F15) -> 0 | G9: =SUM(G10:G15) -> 0 | H9: =SUM(H10:H15) -> 0 | I9: =SUM(I10:I15) -> 0 | J9: =SUM(J10:J15) -> 0 | ... N9: =SUM(N10:N15) -> 0 | O9: =SUM(C9:N9) -> 0
B10: Devoluções Compra Mercadoria Revenda | C10: 0 | D10: 0 | E10: 0 | F10: 0 | G10: 0 | H10: 0 | I10: 0 | J10: 0 | K10: 0 | L10: 0 | M10: 0 | N10: 0 | O10: =SUM(C10:N10) -> 0
B11: Devoluções de Compra Material Consumo | C11: 0 | D11: 0 | E11: 0 | F11: 0 | G11: 0 | H11: 0 | I11: 0 | J11: 0 | K11: 0 | L11: 0 | M11: 0 | N11: 0 | O11: =SUM(C11:N11) -> 0
B12: Devoluções de Compra de Matéria Prima | C12: 0 | D12: 0 | E12: 0 | F12: 0 | G12: 0 | H12: 0 | I12: 0 | J12: 0 | K12: 0 | L12: 0 | M12: 0 | N12: 0 | O12: =SUM(C12:N12) -> 0
B13: Devoluções de Compra de Ativo | C13: 0 | D13: 0 | E13: 0 | F13: 0 | G13: 0 | H13: 0 | I13: 0 | J13: 0 | K13: 0 | L13: 0 | M13: 0 | N13: 0 | O13: =SUM(C13:N13) -> 0
B14: Devoluções de Compra de Serviços | C14: 0 | D14: 0 | E14: 0 | F14: 0 | G14: 0 | H14: 0 | I14: 0 | J14: 0 | K14: 0 | L14: 0 | M14: 0 | N14: 0 | O14: =SUM(C14:N14) -> 0
B15: Devolução de Doações | C15: 0 | D15: 0 | E15: 0 | F15: 0 | G15: 0 | H15: 0 | I15: 0 | J15: 0 | K15: 0 | L15: 0 | M15: 0 | N15: 0 | O15: =SUM(C15:N15) -> 0
B16: Outras Entradas | C16: =SUM(C17:C21) -> 0 | D16: =SUM(D17:D21) -> 0 | E16: =SUM(E17:E21) -> 0 | F16: =SUM(F17:F21) -> 0 | G16: =SUM(G17:G21) -> 0 | H16: =SUM(H17:H21) -> 0 | I16: =SUM(I17:I21) -> 0 | J16: =SUM(J17:J21) -> 0 | ... N16: =SUM(N17:N21) -> 0 | O16: =SUM(C16:N16) -> 0
B17: Empréstimos Bancários | C17: 0 | D17: 0 | E17: 0 | F17: 0 | G17: 0 | H17: 0 | I17: 0 | J17: 0 | K17: 0 | L17: 0 | M17: 0 | N17: 0 | O17: =SUM(C17:N17) -> 0
B18: Aumento de Capital | C18: 0 | D18: 0 | E18: 0 | F18: 0 | G18: 0 | H18: 0 | I18: 0 | J18: 0 | K18: 0 | L18: 0 | M18: 0 | N18: 0 | O18: =SUM(C18:N18) -> 0
B19: Venda de Ativos | C19: 0 | D19: 0 | E19: 0 | F19: 0 | G19: 0 | H19: 0 | I19: 0 | J19: 0 | K19: 0 | L19: 0 | M19: 0 | N19: 0 | O19: =SUM(C19:N19) -> 0
B20: AJUSTE DE CAIXA | C20: 0 | D20: 0 | E20: 0 | F20: 0 | G20: 0 | H20: 0 | I20: 0 | J20: 0 | K20: 0 | L20: 0 | M20: 0 | N20: 0 | O20: =SUM(C20:N20) -> 0
B21: Prêmios de Seguros / Sinistros | C21: 0 | D21: 0 | E21: 0 | F21: 0 | G21: 0 | H21: 0 | I21: 0 | J21: 0 | K21: 0 | L21: 0 | M21: 0 | N21: 0 | O21: =SUM(C21:N21) -> 0
B22: Doações | C22: =SUM(C23:C27) -> 0 | D22: =SUM(D23:D27) -> 0 | E22: =SUM(E23:E27) -> 0 | F22: =SUM(F23:F27) -> 0 | G22: =SUM(G23:G27) -> 0 | H22: =SUM(H23:H27) -> 0 | I22: =SUM(I23:I27) -> 0 | J22: =SUM(J23:J27) -> 0 | ... N22: =SUM(N23:N27) -> 0 | O22: =SUM(C22:N22) -> 0
B23: Doações Recorrentes | C23: =SUM(OUTLET!C23,GRIFFTE!C23) -> 0 | D23: =SUM(OUTLET!D23,GRIFFTE!D23) -> 0 | E23: =SUM(OUTLET!E23,GRIFFTE!E23) -> 0 | F23: =SUM(OUTLET!F23,GRIFFTE!F23) -> 0 | G23: =SUM(OUTLET!G23,GRIFFTE!G23) -> 0 | H23: =SUM(OUTLET!H23,GRIFFTE!H23) -> 0 | I23: =SUM(OUTLET!I23,GRIFFTE!I23) -> 0 | J23: =SUM(OUTLET!J23,GRIFFTE!J23) -> 0 | ... N23: =SUM(OUTLET!N23,GRIFFTE!N23) -> 0 | O23: =SUM(C23:N23) -> 0
B24: Doações Pontuais PF | C24: =SUM(OUTLET!C24,GRIFFTE!C24) -> 0 | D24: =SUM(OUTLET!D24,GRIFFTE!D24) -> 0 | E24: =SUM(OUTLET!E24,GRIFFTE!E24) -> 0 | F24: =SUM(OUTLET!F24,GRIFFTE!F24) -> 0 | G24: =SUM(OUTLET!G24,GRIFFTE!G24) -> 0 | H24: =SUM(OUTLET!H24,GRIFFTE!H24) -> 0 | I24: =SUM(OUTLET!I24,GRIFFTE!I24) -> 0 | J24: =SUM(OUTLET!J24,GRIFFTE!J24) -> 0 | ... N24: =SUM(OUTLET!N24,GRIFFTE!N24) -> 0 | O24: =SUM(C24:N24) -> 0
B25: Doações Pontuais PJ | C25: =SUM(OUTLET!C25,GRIFFTE!C25) -> 0 | D25: =SUM(OUTLET!D25,GRIFFTE!D25) -> 0 | E25: =SUM(OUTLET!E25,GRIFFTE!E25) -> 0 | F25: =SUM(OUTLET!F25,GRIFFTE!F25) -> 0 | G25: =SUM(OUTLET!G25,GRIFFTE!G25) -> 0 | H25: =SUM(OUTLET!H25,GRIFFTE!H25) -> 0 | I25: =SUM(OUTLET!I25,GRIFFTE!I25) -> 0 | J25: =SUM(OUTLET!J25,GRIFFTE!J25) -> 0 | ... N25: =SUM(OUTLET!N25,GRIFFTE!N25) -> 0 | O25: =SUM(C25:N25) -> 0
B26: Sócio Doador | C26: =SUM(OUTLET!C26,GRIFFTE!C26) -> 0 | D26: =SUM(OUTLET!D26,GRIFFTE!D26) -> 0 | E26: =SUM(OUTLET!E26,GRIFFTE!E26) -> 0 | F26: =SUM(OUTLET!F26,GRIFFTE!F26) -> 0 | G26: =SUM(OUTLET!G26,GRIFFTE!G26) -> 0 | H26: =SUM(OUTLET!H26,GRIFFTE!H26) -> 0 | I26: =SUM(OUTLET!I26,GRIFFTE!I26) -> 0 | J26: =SUM(OUTLET!J26,GRIFFTE!J26) -> 0 | ... N26: =SUM(OUTLET!N26,GRIFFTE!N26) -> 0 | O26: =SUM(C26:N26) -> 0
B27: Patrocínios | C27: =SUM(OUTLET!C27,GRIFFTE!C27) -> 0 | D27: =SUM(OUTLET!D27,GRIFFTE!D27) -> 0 | E27: =SUM(OUTLET!E27,GRIFFTE!E27) -> 0 | F27: =SUM(OUTLET!F27,GRIFFTE!F27) -> 0 | G27: =SUM(OUTLET!G27,GRIFFTE!G27) -> 0 | H27: =SUM(OUTLET!H27,GRIFFTE!H27) -> 0 | I27: =SUM(OUTLET!I27,GRIFFTE!I27) -> 0 | J27: =SUM(OUTLET!J27,GRIFFTE!J27) -> 0 | ... N27: =SUM(OUTLET!N27,GRIFFTE!N27) -> 0 | O27: =SUM(C27:N27) -> 0
B28: Gerando Falcões | C28: =SUM(C29:C32) -> 0 | D28: =SUM(D29:D32) -> 0 | E28: =SUM(E29:E32) -> 0 | F28: =SUM(F29:F32) -> 0 | G28: =SUM(G29:G32) -> 0 | H28: =SUM(H29:H32) -> 0 | I28: =SUM(I29:I32) -> 0 | J28: =SUM(J29:J32) -> 0 | ... N28: =SUM(N29:N32) -> 0 | O28: =SUM(C28:N28) -> 0
B29: Aporte | C29: =SUM(OUTLET!C29,GRIFFTE!C29) -> 0 | D29: =SUM(OUTLET!D29,GRIFFTE!D29) -> 0 | E29: =SUM(OUTLET!E29,GRIFFTE!E29) -> 0 | F29: =SUM(OUTLET!F29,GRIFFTE!F29) -> 0 | G29: =SUM(OUTLET!G29,GRIFFTE!G29) -> 0 | H29: =SUM(OUTLET!H29,GRIFFTE!H29) -> 0 | I29: =SUM(OUTLET!I29,GRIFFTE!I29) -> 0 | J29: =SUM(OUTLET!J29,GRIFFTE!J29) -> 0 | ... N29: =SUM(OUTLET!N29,GRIFFTE!N29) -> 0 | O29: =SUM(C29:N29) -> 0
B30: Falcons Univercity | C30: =SUM(OUTLET!C30,GRIFFTE!C30) -> 0 | D30: =SUM(OUTLET!D30,GRIFFTE!D30) -> 0 | E30: =SUM(OUTLET!E30,GRIFFTE!E30) -> 0 | F30: =SUM(OUTLET!F30,GRIFFTE!F30) -> 0 | G30: =SUM(OUTLET!G30,GRIFFTE!G30) -> 0 | H30: =SUM(OUTLET!H30,GRIFFTE!H30) -> 0 | I30: =SUM(OUTLET!I30,GRIFFTE!I30) -> 0 | J30: =SUM(OUTLET!J30,GRIFFTE!J30) -> 0 | ... N30: =SUM(OUTLET!N30,GRIFFTE!N30) -> 0 | O30: =SUM(C30:N30) -> 0
B31: Regional GF | C31: =SUM(OUTLET!C31,GRIFFTE!C31) -> 0 | D31: =SUM(OUTLET!D31,GRIFFTE!D31) -> 0 | E31: =SUM(OUTLET!E31,GRIFFTE!E31) -> 0 | F31: =SUM(OUTLET!F31,GRIFFTE!F31) -> 0 | G31: =SUM(OUTLET!G31,GRIFFTE!G31) -> 0 | H31: =SUM(OUTLET!H31,GRIFFTE!H31) -> 0 | I31: =SUM(OUTLET!I31,GRIFFTE!I31) -> 0 | J31: =SUM(OUTLET!J31,GRIFFTE!J31) -> 0 | ... N31: =SUM(OUTLET!N31,GRIFFTE!N31) -> 0 | O31: =SUM(C31:N31) -> 0
B32: Favela 3D | C32: =SUM(OUTLET!C32,GRIFFTE!C32) -> 0 | D32: =SUM(OUTLET!D32,GRIFFTE!D32) -> 0 | E32: =SUM(OUTLET!E32,GRIFFTE!E32) -> 0 | F32: =SUM(OUTLET!F32,GRIFFTE!F32) -> 0 | G32: =SUM(OUTLET!G32,GRIFFTE!G32) -> 0 | H32: =SUM(OUTLET!H32,GRIFFTE!H32) -> 0 | I32: =SUM(OUTLET!I32,GRIFFTE!I32) -> 0 | J32: =SUM(OUTLET!J32,GRIFFTE!J32) -> 0 | ... N32: =SUM(OUTLET!N32,GRIFFTE!N32) -> 0 | O32: =SUM(C32:N32) -> 0
B33: Editais/Projetos | C33: =SUM(C34:C36) -> 0 | D33: =SUM(D34:D36) -> 0 | E33: =SUM(E34:E36) -> 0 | F33: =SUM(F34:F36) -> 0 | G33: =SUM(G34:G36) -> 0 | H33: =SUM(H34:H36) -> 0 | I33: =SUM(I34:I36) -> 0 | J33: =SUM(J34:J36) -> 0 | ... N33: =SUM(N34:N36) -> 0 | O33: =SUM(C33:N33) -> 0
B34: Ecogaiola | C34: =SUM(OUTLET!C34,GRIFFTE!C34) -> 0 | D34: =SUM(OUTLET!D34,GRIFFTE!D34) -> 0 | E34: =SUM(OUTLET!E34,GRIFFTE!E34) -> 0 | F34: =SUM(OUTLET!F34,GRIFFTE!F34) -> 0 | G34: =SUM(OUTLET!G34,GRIFFTE!G34) -> 0 | H34: =SUM(OUTLET!H34,GRIFFTE!H34) -> 0 | I34: =SUM(OUTLET!I34,GRIFFTE!I34) -> 0 | J34: =SUM(OUTLET!J34,GRIFFTE!J34) -> 0 | ... N34: =SUM(OUTLET!N34,GRIFFTE!N34) -> 0 | O34: =SUM(C34:N34) -> 0
B35: Prog. Hab. Polaris | C35: =SUM(OUTLET!C35,GRIFFTE!C35) -> 0 | D35: =SUM(OUTLET!D35,GRIFFTE!D35) -> 0 | E35: =SUM(OUTLET!E35,GRIFFTE!E35) -> 0 | F35: =SUM(OUTLET!F35,GRIFFTE!F35) -> 0 | G35: =SUM(OUTLET!G35,GRIFFTE!G35) -> 0 | H35: =SUM(OUTLET!H35,GRIFFTE!H35) -> 0 | I35: =SUM(OUTLET!I35,GRIFFTE!I35) -> 0 | J35: =SUM(OUTLET!J35,GRIFFTE!J35) -> 0 | ... N35: =SUM(OUTLET!N35,GRIFFTE!N35) -> 0 | O35: =SUM(C35:N35) -> 0
B36: Lei De Incentivo | C36: =SUM(OUTLET!C36,GRIFFTE!C36) -> 0 | D36: =SUM(OUTLET!D36,GRIFFTE!D36) -> 0 | E36: =SUM(OUTLET!E36,GRIFFTE!E36) -> 0 | F36: =SUM(OUTLET!F36,GRIFFTE!F36) -> 0 | G36: =SUM(OUTLET!G36,GRIFFTE!G36) -> 0 | H36: =SUM(OUTLET!H36,GRIFFTE!H36) -> 0 | I36: =SUM(OUTLET!I36,GRIFFTE!I36) -> 0 | J36: =SUM(OUTLET!J36,GRIFFTE!J36) -> 0 | ... N36: =SUM(OUTLET!N36,GRIFFTE!N36) -> 0 | O36: =SUM(C36:N36) -> 0
B37: Negócios Sociais | C37: =SUM(C38:C39) -> 16500 | D37: =SUM(D38:D39) -> 29500 | E37: =SUM(E38:E39) -> 29500 | F37: =SUM(F38:F39) -> 29500 | G37: =SUM(G38:G39) -> 29500 | H37: =SUM(H38:H39) -> 29500 | I37: =SUM(I38:I39) -> 29500 | J37: =SUM(J38:J39) -> 29500 | ... N37: =SUM(N38:N39) -> 16500 | O37: =SUM(C37:N37) -> 328000
B38: Vendas Outlet | C38: =SUM(OUTLET!C38,GRIFFTE!C38) -> 16500 | D38: =SUM(OUTLET!D38,GRIFFTE!D38) -> 16500 | E38: =SUM(OUTLET!E38,GRIFFTE!E38) -> 16500 | F38: =SUM(OUTLET!F38,GRIFFTE!F38) -> 16500 | G38: =SUM(OUTLET!G38,GRIFFTE!G38) -> 16500 | H38: =SUM(OUTLET!H38,GRIFFTE!H38) -> 16500 | I38: =SUM(OUTLET!I38,GRIFFTE!I38) -> 16500 | J38: =SUM(OUTLET!J38,GRIFFTE!J38) -> 16500 | ... N38: =SUM(OUTLET!N38,GRIFFTE!N38) -> 16500 | O38: =SUM(C38:N38) -> 198000
B39: Vendas Griffte | C39: =SUM(OUTLET!C39,GRIFFTE!C39) -> 0 | D39: =SUM(OUTLET!D39,GRIFFTE!D39) -> 13000 | E39: =SUM(OUTLET!E39,GRIFFTE!E39) -> 13000 | F39: =SUM(OUTLET!F39,GRIFFTE!F39) -> 13000 | G39: =SUM(OUTLET!G39,GRIFFTE!G39) -> 13000 | H39: =SUM(OUTLET!H39,GRIFFTE!H39) -> 13000 | I39: =SUM(OUTLET!I39,GRIFFTE!I39) -> 13000 | J39: =SUM(OUTLET!J39,GRIFFTE!J39) -> 13000 | ... N39: =SUM(OUTLET!N39,GRIFFTE!N39) -> 0 | O39: =SUM(C39:N39) -> 130000
B40: Eventos | C40: =SUM(C41:C42) -> 0 | D40: =SUM(D41:D42) -> 0 | E40: =SUM(E41:E42) -> 0 | F40: =SUM(F41:F42) -> 0 | G40: =SUM(G41:G42) -> 0 | H40: =SUM(H41:H42) -> 0 | I40: =SUM(I41:I42) -> 0 | J40: =SUM(J41:J42) -> 0 | ... N40: =SUM(N41:N42) -> 0 | O40: =SUM(C40:N40) -> 0
B41: Clube Do Grito | C41: =SUM(OUTLET!C41,GRIFFTE!C41) -> 0 | D41: =SUM(OUTLET!D41,GRIFFTE!D41) -> 0 | E41: =SUM(OUTLET!E41,GRIFFTE!E41) -> 0 | F41: =SUM(OUTLET!F41,GRIFFTE!F41) -> 0 | G41: =SUM(OUTLET!G41,GRIFFTE!G41) -> 0 | H41: =SUM(OUTLET!H41,GRIFFTE!H41) -> 0 | I41: =SUM(OUTLET!I41,GRIFFTE!I41) -> 0 | J41: =SUM(OUTLET!J41,GRIFFTE!J41) -> 0 | ... N41: =SUM(OUTLET!N41,GRIFFTE!N41) -> 0 | O41: =SUM(C41:N41) -> 0
B42: Crowdfunding | C42: =SUM(OUTLET!C42,GRIFFTE!C42) -> 0 | D42: =SUM(OUTLET!D42,GRIFFTE!D42) -> 0 | E42: =SUM(OUTLET!E42,GRIFFTE!E42) -> 0 | F42: =SUM(OUTLET!F42,GRIFFTE!F42) -> 0 | G42: =SUM(OUTLET!G42,GRIFFTE!G42) -> 0 | H42: =SUM(OUTLET!H42,GRIFFTE!H42) -> 0 | I42: =SUM(OUTLET!I42,GRIFFTE!I42) -> 0 | J42: =SUM(OUTLET!J42,GRIFFTE!J42) -> 0 | ... N42: =SUM(OUTLET!N42,GRIFFTE!N42) -> 0 | O42: =SUM(C42:N42) -> 0
B43: Aplicações | C43: =SUM(C44:C46) -> 0 | D43: =SUM(D44:D46) -> 0 | E43: =SUM(E44:E46) -> 0 | F43: =SUM(F44:F46) -> 0 | G43: =SUM(G44:G46) -> 0 | H43: =SUM(H44:H46) -> 0 | I43: =SUM(I44:I46) -> 0 | J43: =SUM(J44:J46) -> 0 | ... N43: =SUM(N44:N46) -> 0 | O43: =SUM(C43:N43) -> 0
B44: Resgate Aplicações (Clube do Grito 2023) | C44: =SUM(OUTLET!C44,GRIFFTE!C44) -> 0 | D44: =SUM(OUTLET!D44,GRIFFTE!D44) -> 0 | E44: =SUM(OUTLET!E44,GRIFFTE!E44) -> 0 | F44: =SUM(OUTLET!F44,GRIFFTE!F44) -> 0 | G44: =SUM(OUTLET!G44,GRIFFTE!G44) -> 0 | H44: =SUM(OUTLET!H44,GRIFFTE!H44) -> 0 | I44: =SUM(OUTLET!I44,GRIFFTE!I44) -> 0 | J44: =SUM(OUTLET!J44,GRIFFTE!J44) -> 0 | ... N44: =SUM(OUTLET!N44,GRIFFTE!N44) -> 0 | O44: =SUM(C44:N44) -> 0
B45: Rendimentos Aplicações | C45: =SUM(OUTLET!C45,GRIFFTE!C45) -> 0 | D45: =SUM(OUTLET!D45,GRIFFTE!D45) -> 0 | E45: =SUM(OUTLET!E45,GRIFFTE!E45) -> 0 | F45: =SUM(OUTLET!F45,GRIFFTE!F45) -> 0 | G45: =SUM(OUTLET!G45,GRIFFTE!G45) -> 0 | H45: =SUM(OUTLET!H45,GRIFFTE!H45) -> 0 | I45: =SUM(OUTLET!I45,GRIFFTE!I45) -> 0 | J45: =SUM(OUTLET!J45,GRIFFTE!J45) -> 0 | ... N45: =SUM(OUTLET!N45,GRIFFTE!N45) -> 0 | O45: =SUM(C45:N45) -> 0
C46: =SUM(OUTLET!C46,GRIFFTE!C46) -> 0 | D46: =SUM(OUTLET!D46,GRIFFTE!D46) -> 0 | E46: =SUM(OUTLET!E46,GRIFFTE!E46) -> 0 | F46: =SUM(OUTLET!F46,GRIFFTE!F46) -> 0 | G46: =SUM(OUTLET!G46,GRIFFTE!G46) -> 0 | H46: =SUM(OUTLET!H46,GRIFFTE!H46) -> 0 | I46: =SUM(OUTLET!I46,GRIFFTE!I46) -> 0 | J46: =SUM(OUTLET!J46,GRIFFTE!J46) -> 0 | ... N46: =SUM(OUTLET!N46,GRIFFTE!N46) -> 0 | O46: =SUM(C46:N46) -> 0
B47: DESPESAS | C47: =SUM(C48,C50,C53,C75,C99,C105,C116,C120,C123,C126,C130,C133) -> 24725 | D47: =SUM(D48,D50,D53,D75,D99,D105,D116,D120,D123,D126,D130,D133) -> 20875 | E47: =SUM(E48,E50,E53,E75,E99,E105,E116,E120,E123,E126,E130,E133) -> 20975 | F47: =SUM(F48,F50,F53,F75,F99,F105,F116,F120,F123,F126,F130,F133) -> 21275 | G47: =SUM(G48,G50,G53,G75,G99,G105,G116,G120,G123,G126,G130,G133) -> 20935 | H47: =SUM(H48,H50,H53,H75,H99,H105,H116,H120,H123,H126,H130,H133) -> 20925 | I47: =SUM(I48,I50,I53,I75,I99,I105,I116,I120,I123,I126,I130,I133) -> 20875 | J47: =SUM(J48,J50,J53,J75,J99,J105,J116,J120,J123,J126,J130,J133) -> 20875 | ... N47: =SUM(N48,N50,N53,N75,N99,N105,N116,N120,N123,N126,N130,N133) -> 21075 | O47: =SUM(C47:N47) -> 255260
B48: Despesas Diretas | C48: =SUM(C49) -> 800 | D48: =SUM(D49) -> 800 | E48: =SUM(E49) -> 800 | F48: =SUM(F49) -> 800 | G48: =SUM(G49) -> 800 | H48: =SUM(H49) -> 800 | I48: =SUM(I49) -> 800 | J48: =SUM(J49) -> 800 | ... N48: =SUM(N49) -> 800 | O48: =SUM(C48:N48) -> 9600
B49: Compras Mercadorias Revenda | C49: =SUM(OUTLET!C49,GRIFFTE!C49) -> 800 | D49: =SUM(OUTLET!D49,GRIFFTE!D49) -> 800 | E49: =SUM(OUTLET!E49,GRIFFTE!E49) -> 800 | F49: =SUM(OUTLET!F49,GRIFFTE!F49) -> 800 | G49: =SUM(OUTLET!G49,GRIFFTE!G49) -> 800 | H49: =SUM(OUTLET!H49,GRIFFTE!H49) -> 800 | I49: =SUM(OUTLET!I49,GRIFFTE!I49) -> 800 | J49: =SUM(OUTLET!J49,GRIFFTE!J49) -> 800 | ... N49: =SUM(OUTLET!N49,GRIFFTE!N49) -> 800 | O49: =SUM(C49:N49) -> 9600
B50: Marketing | C50: =SUM(C51:C52) -> 0 | D50: =SUM(D51:D52) -> 0 | E50: =SUM(E51:E52) -> 100 | F50: =SUM(F51:F52) -> 0 | G50: =SUM(G51:G52) -> 60 | H50: =SUM(H51:H52) -> 50 | I50: =SUM(I51:I52) -> 0 | J50: =SUM(J51:J52) -> 0 | ... N50: =SUM(N51:N52) -> 200 | O50: =SUM(C50:N50) -> 510
B51: Divulgação | C51: =SUM(OUTLET!C51,GRIFFTE!C51) -> 0 | D51: =SUM(OUTLET!D51,GRIFFTE!D51) -> 0 | E51: =SUM(OUTLET!E51,GRIFFTE!E51) -> 100 | F51: =SUM(OUTLET!F51,GRIFFTE!F51) -> 0 | G51: =SUM(OUTLET!G51,GRIFFTE!G51) -> 60 | H51: =SUM(OUTLET!H51,GRIFFTE!H51) -> 50 | I51: =SUM(OUTLET!I51,GRIFFTE!I51) -> 0 | J51: =SUM(OUTLET!J51,GRIFFTE!J51) -> 0 | ... N51: =SUM(OUTLET!N51,GRIFFTE!N51) -> 200 | O51: =SUM(C51:N51) -> 510
B52: Vestuários | C52: =SUM(OUTLET!C52,GRIFFTE!C52) -> 0 | D52: =SUM(OUTLET!D52,GRIFFTE!D52) -> 0 | E52: =SUM(OUTLET!E52,GRIFFTE!E52) -> 0 | F52: =SUM(OUTLET!F52,GRIFFTE!F52) -> 0 | G52: =SUM(OUTLET!G52,GRIFFTE!G52) -> 0 | H52: =SUM(OUTLET!H52,GRIFFTE!H52) -> 0 | I52: =SUM(OUTLET!I52,GRIFFTE!I52) -> 0 | J52: =SUM(OUTLET!J52,GRIFFTE!J52) -> 0 | ... N52: =SUM(OUTLET!N52,GRIFFTE!N52) -> 0 | O52: =SUM(C52:N52) -> 0
B53: Despesas com Pessoal | C53: =SUM(C54:C74) -> 14450 | D53: =SUM(D54:D74) -> 14450 | E53: =SUM(E54:E74) -> 14450 | F53: =SUM(F54:F74) -> 14450 | G53: =SUM(G54:G74) -> 14450 | H53: =SUM(H54:H74) -> 14450 | I53: =SUM(I54:I74) -> 14450 | J53: =SUM(J54:J74) -> 14450 | ... N53: =SUM(N54:N74) -> 14450 | O53: =SUM(C53:N53) -> 173400
B54: Comissões | C54: =SUM(OUTLET!C54,GRIFFTE!C54) -> 0 | D54: =SUM(OUTLET!D54,GRIFFTE!D54) -> 0 | E54: =SUM(OUTLET!E54,GRIFFTE!E54) -> 0 | F54: =SUM(OUTLET!F54,GRIFFTE!F54) -> 0 | G54: =SUM(OUTLET!G54,GRIFFTE!G54) -> 0 | H54: =SUM(OUTLET!H54,GRIFFTE!H54) -> 0 | I54: =SUM(OUTLET!I54,GRIFFTE!I54) -> 0 | J54: =SUM(OUTLET!J54,GRIFFTE!J54) -> 0 | ... N54: =SUM(OUTLET!N54,GRIFFTE!N54) -> 0 | O54: =SUM(C54:N54) -> 0
B55: Férias | C55: =SUM(OUTLET!C55,GRIFFTE!C55) -> 0 | D55: =SUM(OUTLET!D55,GRIFFTE!D55) -> 0 | E55: =SUM(OUTLET!E55,GRIFFTE!E55) -> 0 | F55: =SUM(OUTLET!F55,GRIFFTE!F55) -> 0 | G55: =SUM(OUTLET!G55,GRIFFTE!G55) -> 0 | H55: =SUM(OUTLET!H55,GRIFFTE!H55) -> 0 | I55: =SUM(OUTLET!I55,GRIFFTE!I55) -> 0 | J55: =SUM(OUTLET!J55,GRIFFTE!J55) -> 0 | ... N55: =SUM(OUTLET!N55,GRIFFTE!N55) -> 0 | O55: =SUM(C55:N55) -> 0
B56: Rescisões | C56: =SUM(OUTLET!C56,GRIFFTE!C56) -> 0 | D56: =SUM(OUTLET!D56,GRIFFTE!D56) -> 0 | E56: =SUM(OUTLET!E56,GRIFFTE!E56) -> 0 | F56: =SUM(OUTLET!F56,GRIFFTE!F56) -> 0 | G56: =SUM(OUTLET!G56,GRIFFTE!G56) -> 0 | H56: =SUM(OUTLET!H56,GRIFFTE!H56) -> 0 | I56: =SUM(OUTLET!I56,GRIFFTE!I56) -> 0 | J56: =SUM(OUTLET!J56,GRIFFTE!J56) -> 0 | ... N56: =SUM(OUTLET!N56,GRIFFTE!N56) -> 0 | O56: =SUM(C56:N56) -> 0
B57: 13º Salário | C57: =SUM(OUTLET!C57,GRIFFTE!C57) -> 0 | D57: =SUM(OUTLET!D57,GRIFFTE!D57) -> 0 | E57: =SUM(OUTLET!E57,GRIFFTE!E57) -> 0 | F57: =SUM(OUTLET!F57,GRIFFTE!F57) -> 0 | G57: =SUM(OUTLET!G57,GRIFFTE!G57) -> 0 | H57: =SUM(OUTLET!H57,GRIFFTE!H57) -> 0 | I57: =SUM(OUTLET!I57,GRIFFTE!I57) -> 0 | J57: =SUM(OUTLET!J57,GRIFFTE!J57) -> 0 | ... N57: =SUM(OUTLET!N57,GRIFFTE!N57) -> 0 | O57: =SUM(C57:N57) -> 0
B58: INSS | C58: =SUM(OUTLET!C58,GRIFFTE!C58) -> 0 | D58: =SUM(OUTLET!D58,GRIFFTE!D58) -> 0 | E58: =SUM(OUTLET!E58,GRIFFTE!E58) -> 0 | F58: =SUM(OUTLET!F58,GRIFFTE!F58) -> 0 | G58: =SUM(OUTLET!G58,GRIFFTE!G58) -> 0 | H58: =SUM(OUTLET!H58,GRIFFTE!H58) -> 0 | I58: =SUM(OUTLET!I58,GRIFFTE!I58) -> 0 | J58: =SUM(OUTLET!J58,GRIFFTE!J58) -> 0 | ... N58: =SUM(OUTLET!N58,GRIFFTE!N58) -> 0 | O58: =SUM(C58:N58) -> 0
B59: FGTS | C59: =SUM(OUTLET!C59,GRIFFTE!C59) -> 0 | D59: =SUM(OUTLET!D59,GRIFFTE!D59) -> 0 | E59: =SUM(OUTLET!E59,GRIFFTE!E59) -> 0 | F59: =SUM(OUTLET!F59,GRIFFTE!F59) -> 0 | G59: =SUM(OUTLET!G59,GRIFFTE!G59) -> 0 | H59: =SUM(OUTLET!H59,GRIFFTE!H59) -> 0 | I59: =SUM(OUTLET!I59,GRIFFTE!I59) -> 0 | J59: =SUM(OUTLET!J59,GRIFFTE!J59) -> 0 | ... N59: =SUM(OUTLET!N59,GRIFFTE!N59) -> 0 | O59: =SUM(C59:N59) -> 0
B60: IRRF | C60: =SUM(OUTLET!C60,GRIFFTE!C60) -> 0 | D60: =SUM(OUTLET!D60,GRIFFTE!D60) -> 0 | E60: =SUM(OUTLET!E60,GRIFFTE!E60) -> 0 | F60: =SUM(OUTLET!F60,GRIFFTE!F60) -> 0 | G60: =SUM(OUTLET!G60,GRIFFTE!G60) -> 0 | H60: =SUM(OUTLET!H60,GRIFFTE!H60) -> 0 | I60: =SUM(OUTLET!I60,GRIFFTE!I60) -> 0 | J60: =SUM(OUTLET!J60,GRIFFTE!J60) -> 0 | ... N60: =SUM(OUTLET!N60,GRIFFTE!N60) -> 0 | O60: =SUM(C60:N60) -> 0
B61: Exames | C61: =SUM(OUTLET!C61,GRIFFTE!C61) -> 0 | D61: =SUM(OUTLET!D61,GRIFFTE!D61) -> 0 | E61: =SUM(OUTLET!E61,GRIFFTE!E61) -> 0 | F61: =SUM(OUTLET!F61,GRIFFTE!F61) -> 0 | G61: =SUM(OUTLET!G61,GRIFFTE!G61) -> 0 | H61: =SUM(OUTLET!H61,GRIFFTE!H61) -> 0 | I61: =SUM(OUTLET!I61,GRIFFTE!I61) -> 0 | J61: =SUM(OUTLET!J61,GRIFFTE!J61) -> 0 | ... N61: =SUM(OUTLET!N61,GRIFFTE!N61) -> 0 | O61: =SUM(C61:N61) -> 0
B62: Assistência Médica | C62: =SUM(OUTLET!C62,GRIFFTE!C62) -> 0 | D62: =SUM(OUTLET!D62,GRIFFTE!D62) -> 0 | E62: =SUM(OUTLET!E62,GRIFFTE!E62) -> 0 | F62: =SUM(OUTLET!F62,GRIFFTE!F62) -> 0 | G62: =SUM(OUTLET!G62,GRIFFTE!G62) -> 0 | H62: =SUM(OUTLET!H62,GRIFFTE!H62) -> 0 | I62: =SUM(OUTLET!I62,GRIFFTE!I62) -> 0 | J62: =SUM(OUTLET!J62,GRIFFTE!J62) -> 0 | ... N62: =SUM(OUTLET!N62,GRIFFTE!N62) -> 0 | O62: =SUM(C62:N62) -> 0
B63: Vale Transporte | C63: =SUM(OUTLET!C63,GRIFFTE!C63) -> 0 | D63: =SUM(OUTLET!D63,GRIFFTE!D63) -> 0 | E63: =SUM(OUTLET!E63,GRIFFTE!E63) -> 0 | F63: =SUM(OUTLET!F63,GRIFFTE!F63) -> 0 | G63: =SUM(OUTLET!G63,GRIFFTE!G63) -> 0 | H63: =SUM(OUTLET!H63,GRIFFTE!H63) -> 0 | I63: =SUM(OUTLET!I63,GRIFFTE!I63) -> 0 | J63: =SUM(OUTLET!J63,GRIFFTE!J63) -> 0 | ... N63: =SUM(OUTLET!N63,GRIFFTE!N63) -> 0 | O63: =SUM(C63:N63) -> 0
B64: Vale Refeição | C64: =SUM(OUTLET!C64,GRIFFTE!C64) -> 600 | D64: =SUM(OUTLET!D64,GRIFFTE!D64) -> 600 | E64: =SUM(OUTLET!E64,GRIFFTE!E64) -> 600 | F64: =SUM(OUTLET!F64,GRIFFTE!F64) -> 600 | G64: =SUM(OUTLET!G64,GRIFFTE!G64) -> 600 | H64: =SUM(OUTLET!H64,GRIFFTE!H64) -> 600 | I64: =SUM(OUTLET!I64,GRIFFTE!I64) -> 600 | J64: =SUM(OUTLET!J64,GRIFFTE!J64) -> 600 | ... N64: =SUM(OUTLET!N64,GRIFFTE!N64) -> 600 | O64: =SUM(C64:N64) -> 7200
B65: Seguro de Vida | C65: =SUM(OUTLET!C65,GRIFFTE!C65) -> 0 | D65: =SUM(OUTLET!D65,GRIFFTE!D65) -> 0 | E65: =SUM(OUTLET!E65,GRIFFTE!E65) -> 0 | F65: =SUM(OUTLET!F65,GRIFFTE!F65) -> 0 | G65: =SUM(OUTLET!G65,GRIFFTE!G65) -> 0 | H65: =SUM(OUTLET!H65,GRIFFTE!H65) -> 0 | I65: =SUM(OUTLET!I65,GRIFFTE!I65) -> 0 | J65: =SUM(OUTLET!J65,GRIFFTE!J65) -> 0 | ... N65: =SUM(OUTLET!N65,GRIFFTE!N65) -> 0 | O65: =SUM(C65:N65) -> 0
... B74: Ajuda de Custo | C74: =SUM(OUTLET!C74,GRIFFTE!C74) -> 0 | D74: =SUM(OUTLET!D74,GRIFFTE!D74) -> 0 | E74: =SUM(OUTLET!E74,GRIFFTE!E74) -> 0 | F74: =SUM(OUTLET!F74,GRIFFTE!F74) -> 0 | G74: =SUM(OUTLET!G74,GRIFFTE!G74) -> 0 | H74: =SUM(OUTLET!H74,GRIFFTE!H74) -> 0 | I74: =SUM(OUTLET!I74,GRIFFTE!I74) -> 0 | J74: =SUM(OUTLET!J74,GRIFFTE!J74) -> 0 | ... N74: =SUM(OUTLET!N74,GRIFFTE!N74) -> 0 | O74: =SUM(C74:N74) -> 0
B75: Despesas Administrativas | C75: =SUM(C76:C98) -> 9375 | D75: =SUM(D76:D98) -> 5525 | E75: =SUM(E76:E98) -> 5525 | F75: =SUM(F76:F98) -> 5925 | G75: =SUM(G76:G98) -> 5525 | H75: =SUM(H76:H98) -> 5525 | I75: =SUM(I76:I98) -> 5525 | J75: =SUM(J76:J98) -> 5525 | ... N75: =SUM(N76:N98) -> 5525 | O75: =SUM(C75:N75) -> 70550
B76: Aluguel Espaços | C76: =SUM(OUTLET!C76,GRIFFTE!C76) -> 1375 | D76: =SUM(OUTLET!D76,GRIFFTE!D76) -> 1375 | E76: =SUM(OUTLET!E76,GRIFFTE!E76) -> 1375 | F76: =SUM(OUTLET!F76,GRIFFTE!F76) -> 1375 | G76: =SUM(OUTLET!G76,GRIFFTE!G76) -> 1375 | H76: =SUM(OUTLET!H76,GRIFFTE!H76) -> 1375 | I76: =SUM(OUTLET!I76,GRIFFTE!I76) -> 1375 | J76: =SUM(OUTLET!J76,GRIFFTE!J76) -> 1375 | ... N76: =SUM(OUTLET!N76,GRIFFTE!N76) -> 1375 | O76: =SUM(C76:N76) -> 16500
B77: Aluguel/Locações Outros | C77: =SUM(OUTLET!C77,GRIFFTE!C77) -> 0 | D77: =SUM(OUTLET!D77,GRIFFTE!D77) -> 0 | E77: =SUM(OUTLET!E77,GRIFFTE!E77) -> 0 | F77: =SUM(OUTLET!F77,GRIFFTE!F77) -> 0 | G77: =SUM(OUTLET!G77,GRIFFTE!G77) -> 0 | H77: =SUM(OUTLET!H77,GRIFFTE!H77) -> 0 | I77: =SUM(OUTLET!I77,GRIFFTE!I77) -> 0 | J77: =SUM(OUTLET!J77,GRIFFTE!J77) -> 0 | ... N77: =SUM(OUTLET!N77,GRIFFTE!N77) -> 0 | O77: =SUM(C77:N77) -> 0
B78: ÁGUA | C78: =SUM(OUTLET!C78,GRIFFTE!C78) -> 250 | D78: =SUM(OUTLET!D78,GRIFFTE!D78) -> 250 | E78: =SUM(OUTLET!E78,GRIFFTE!E78) -> 250 | F78: =SUM(OUTLET!F78,GRIFFTE!F78) -> 250 | G78: =SUM(OUTLET!G78,GRIFFTE!G78) -> 250 | H78: =SUM(OUTLET!H78,GRIFFTE!H78) -> 250 | I78: =SUM(OUTLET!I78,GRIFFTE!I78) -> 250 | J78: =SUM(OUTLET!J78,GRIFFTE!J78) -> 250 | ... N78: =SUM(OUTLET!N78,GRIFFTE!N78) -> 250 | O78: =SUM(C78:N78) -> 3000
B79: Energia Elétrica | C79: =SUM(OUTLET!C79,GRIFFTE!C79) -> 750 | D79: =SUM(OUTLET!D79,GRIFFTE!D79) -> 950 | E79: =SUM(OUTLET!E79,GRIFFTE!E79) -> 950 | F79: =SUM(OUTLET!F79,GRIFFTE!F79) -> 950 | G79: =SUM(OUTLET!G79,GRIFFTE!G79) -> 950 | H79: =SUM(OUTLET!H79,GRIFFTE!H79) -> 950 | I79: =SUM(OUTLET!I79,GRIFFTE!I79) -> 950 | J79: =SUM(OUTLET!J79,GRIFFTE!J79) -> 950 | ... N79: =SUM(OUTLET!N79,GRIFFTE!N79) -> 950 | O79: =SUM(C79:N79) -> 11200
B80: TELEFONIA/INTERNET | C80: =SUM(OUTLET!C80,GRIFFTE!C80) -> 400 | D80: =SUM(OUTLET!D80,GRIFFTE!D80) -> 400 | E80: =SUM(OUTLET!E80,GRIFFTE!E80) -> 400 | F80: =SUM(OUTLET!F80,GRIFFTE!F80) -> 400 | G80: =SUM(OUTLET!G80,GRIFFTE!G80) -> 400 | H80: =SUM(OUTLET!H80,GRIFFTE!H80) -> 400 | I80: =SUM(OUTLET!I80,GRIFFTE!I80) -> 400 | J80: =SUM(OUTLET!J80,GRIFFTE!J80) -> 400 | ... N80: =SUM(OUTLET!N80,GRIFFTE!N80) -> 400 | O80: =SUM(C80:N80) -> 4800
B81: Material de Escritório | C81: =SUM(OUTLET!C81,GRIFFTE!C81) -> 200 | D81: =SUM(OUTLET!D81,GRIFFTE!D81) -> 200 | E81: =SUM(OUTLET!E81,GRIFFTE!E81) -> 200 | F81: =SUM(OUTLET!F81,GRIFFTE!F81) -> 200 | G81: =SUM(OUTLET!G81,GRIFFTE!G81) -> 200 | H81: =SUM(OUTLET!H81,GRIFFTE!H81) -> 200 | I81: =SUM(OUTLET!I81,GRIFFTE!I81) -> 200 | J81: =SUM(OUTLET!J81,GRIFFTE!J81) -> 200 | ... N81: =SUM(OUTLET!N81,GRIFFTE!N81) -> 200 | O81: =SUM(C81:N81) -> 2400
B82: Gás | C82: =SUM(OUTLET!C82,GRIFFTE!C82) -> 0 | D82: =SUM(OUTLET!D82,GRIFFTE!D82) -> 0 | E82: =SUM(OUTLET!E82,GRIFFTE!E82) -> 0 | F82: =SUM(OUTLET!F82,GRIFFTE!F82) -> 0 | G82: =SUM(OUTLET!G82,GRIFFTE!G82) -> 0 | H82: =SUM(OUTLET!H82,GRIFFTE!H82) -> 0 | I82: =SUM(OUTLET!I82,GRIFFTE!I82) -> 0 | J82: =SUM(OUTLET!J82,GRIFFTE!J82) -> 0 | ... N82: =SUM(OUTLET!N82,GRIFFTE!N82) -> 0 | O82: =SUM(C82:N82) -> 0
B83: Seguros | C83: =SUM(OUTLET!C83,GRIFFTE!C83) -> 0 | D83: =SUM(OUTLET!D83,GRIFFTE!D83) -> 0 | E83: =SUM(OUTLET!E83,GRIFFTE!E83) -> 0 | F83: =SUM(OUTLET!F83,GRIFFTE!F83) -> 0 | G83: =SUM(OUTLET!G83,GRIFFTE!G83) -> 0 | H83: =SUM(OUTLET!H83,GRIFFTE!H83) -> 0 | I83: =SUM(OUTLET!I83,GRIFFTE!I83) -> 0 | J83: =SUM(OUTLET!J83,GRIFFTE!J83) -> 0 | ... N83: =SUM(OUTLET!N83,GRIFFTE!N83) -> 0 | O83: =SUM(C83:N83) -> 0
B84: IPTU | C84: =SUM(OUTLET!C84,GRIFFTE!C84) -> 0 | D84: =SUM(OUTLET!D84,GRIFFTE!D84) -> 0 | E84: =SUM(OUTLET!E84,GRIFFTE!E84) -> 0 | F84: 400 | G84: =SUM(OUTLET!G84,GRIFFTE!G84) -> 0 | H84: =SUM(OUTLET!H84,GRIFFTE!H84) -> 0 | I84: =SUM(OUTLET!I84,GRIFFTE!I84) -> 0 | J84: =SUM(OUTLET!J84,GRIFFTE!J84) -> 0 | K84: =SUM(OUTLET!K84,GRIFFTE!K84) -> 0 | L84: =SUM(OUTLET!L84,GRIFFTE!L84) -> 0 | M84: =SUM(OUTLET!M84,GRIFFTE!M84) -> 0 | N84: =SUM(OUTLET!N84,GRIFFTE!N84) -> 0 | O84: =SUM(C84:N84) -> 400
B85: Contabilidade | C85: =SUM(OUTLET!C85,GRIFFTE!C85) -> 450 | D85: =SUM(OUTLET!D85,GRIFFTE!D85) -> 450 | E85: =SUM(OUTLET!E85,GRIFFTE!E85) -> 450 | F85: =SUM(OUTLET!F85,GRIFFTE!F85) -> 450 | G85: =SUM(OUTLET!G85,GRIFFTE!G85) -> 450 | H85: =SUM(OUTLET!H85,GRIFFTE!H85) -> 450 | I85: =SUM(OUTLET!I85,GRIFFTE!I85) -> 450 | J85: =SUM(OUTLET!J85,GRIFFTE!J85) -> 450 | ... N85: =SUM(OUTLET!N85,GRIFFTE!N85) -> 450 | O85: =SUM(C85:N85) -> 5400
B86: Advogados | C86: =SUM(OUTLET!C86,GRIFFTE!C86) -> 0 | D86: =SUM(OUTLET!D86,GRIFFTE!D86) -> 0 | E86: =SUM(OUTLET!E86,GRIFFTE!E86) -> 0 | F86: =SUM(OUTLET!F86,GRIFFTE!F86) -> 0 | G86: =SUM(OUTLET!G86,GRIFFTE!G86) -> 0 | H86: =SUM(OUTLET!H86,GRIFFTE!H86) -> 0 | I86: =SUM(OUTLET!I86,GRIFFTE!I86) -> 0 | J86: =SUM(OUTLET!J86,GRIFFTE!J86) -> 0 | ... N86: =SUM(OUTLET!N86,GRIFFTE!N86) -> 0 | O86: =SUM(C86:N86) -> 0
B87: Segurança | C87: =SUM(OUTLET!C87,GRIFFTE!C87) -> 0 | D87: =SUM(OUTLET!D87,GRIFFTE!D87) -> 0 | E87: =SUM(OUTLET!E87,GRIFFTE!E87) -> 0 | F87: =SUM(OUTLET!F87,GRIFFTE!F87) -> 0 | G87: =SUM(OUTLET!G87,GRIFFTE!G87) -> 0 | H87: =SUM(OUTLET!H87,GRIFFTE!H87) -> 0 | I87: =SUM(OUTLET!I87,GRIFFTE!I87) -> 0 | J87: =SUM(OUTLET!J87,GRIFFTE!J87) -> 0 | ... N87: =SUM(OUTLET!N87,GRIFFTE!N87) -> 0 | O87: =SUM(C87:N87) -> 0
B88: Limpeza/Higiene/Copa | C88: =SUM(OUTLET!C88,GRIFFTE!C88) -> 200 | D88: =SUM(OUTLET!D88,GRIFFTE!D88) -> 200 | E88: =SUM(OUTLET!E88,GRIFFTE!E88) -> 200 | F88: =SUM(OUTLET!F88,GRIFFTE!F88) -> 200 | G88: =SUM(OUTLET!G88,GRIFFTE!G88) -> 200 | H88: =SUM(OUTLET!H88,GRIFFTE!H88) -> 200 | I88: =SUM(OUTLET!I88,GRIFFTE!I88) -> 200 | J88: =SUM(OUTLET!J88,GRIFFTE!J88) -> 200 | ... N88: =SUM(OUTLET!N88,GRIFFTE!N88) -> 200 | O88: =SUM(C88:N88) -> 2400
B89: Manutenção Equipamentos | C89: =SUM(OUTLET!C89,GRIFFTE!C89) -> 4250 | D89: =SUM(OUTLET!D89,GRIFFTE!D89) -> 400 | E89: =SUM(OUTLET!E89,GRIFFTE!E89) -> 400 | F89: =SUM(OUTLET!F89,GRIFFTE!F89) -> 400 | G89: =SUM(OUTLET!G89,GRIFFTE!G89) -> 400 | H89: =SUM(OUTLET!H89,GRIFFTE!H89) -> 400 | I89: =SUM(OUTLET!I89,GRIFFTE!I89) -> 400 | J89: =SUM(OUTLET!J89,GRIFFTE!J89) -> 400 | ... N89: =SUM(OUTLET!N89,GRIFFTE!N89) -> 400 | O89: =SUM(C89:N89) -> 8650
B90: Assinaturas/Licenças | C90: =SUM(OUTLET!C90,GRIFFTE!C90) -> 0 | D90: =SUM(OUTLET!D90,GRIFFTE!D90) -> 0 | E90: =SUM(OUTLET!E90,GRIFFTE!E90) -> 0 | F90: =SUM(OUTLET!F90,GRIFFTE!F90) -> 0 | G90: =SUM(OUTLET!G90,GRIFFTE!G90) -> 0 | H90: =SUM(OUTLET!H90,GRIFFTE!H90) -> 0 | I90: =SUM(OUTLET!I90,GRIFFTE!I90) -> 0 | J90: =SUM(OUTLET!J90,GRIFFTE!J90) -> 0 | ... N90: =SUM(OUTLET!N90,GRIFFTE!N90) -> 0 | O90: =SUM(C90:N90) -> 0
B91: Cartórios/Correios | C91: =SUM(OUTLET!C91,GRIFFTE!C91) -> 0 | D91: =SUM(OUTLET!D91,GRIFFTE!D91) -> 0 | E91: =SUM(OUTLET!E91,GRIFFTE!E91) -> 0 | F91: =SUM(OUTLET!F91,GRIFFTE!F91) -> 0 | G91: =SUM(OUTLET!G91,GRIFFTE!G91) -> 0 | H91: =SUM(OUTLET!H91,GRIFFTE!H91) -> 0 | I91: =SUM(OUTLET!I91,GRIFFTE!I91) -> 0 | J91: =SUM(OUTLET!J91,GRIFFTE!J91) -> 0 | ... N91: =SUM(OUTLET!N91,GRIFFTE!N91) -> 0 | O91: =SUM(C91:N91) -> 0
B92: Estacionamentos/Pedágios | C92: =SUM(OUTLET!C92,GRIFFTE!C92) -> 0 | D92: =SUM(OUTLET!D92,GRIFFTE!D92) -> 0 | E92: =SUM(OUTLET!E92,GRIFFTE!E92) -> 0 | F92: =SUM(OUTLET!F92,GRIFFTE!F92) -> 0 | G92: =SUM(OUTLET!G92,GRIFFTE!G92) -> 0 | H92: =SUM(OUTLET!H92,GRIFFTE!H92) -> 0 | I92: =SUM(OUTLET!I92,GRIFFTE!I92) -> 0 | J92: =SUM(OUTLET!J92,GRIFFTE!J92) -> 0 | ... N92: =SUM(OUTLET!N92,GRIFFTE!N92) -> 0 | O92: =SUM(C92:N92) -> 0
B93: TRANSPORTES/FRETES | C93: =SUM(OUTLET!C93,GRIFFTE!C93) -> 1000 | D93: =SUM(OUTLET!D93,GRIFFTE!D93) -> 1000 | E93: =SUM(OUTLET!E93,GRIFFTE!E93) -> 1000 | F93: =SUM(OUTLET!F93,GRIFFTE!F93) -> 1000 | G93: =SUM(OUTLET!G93,GRIFFTE!G93) -> 1000 | H93: =SUM(OUTLET!H93,GRIFFTE!H93) -> 1000 | I93: =SUM(OUTLET!I93,GRIFFTE!I93) -> 1000 | J93: =SUM(OUTLET!J93,GRIFFTE!J93) -> 1000 | ... N93: =SUM(OUTLET!N93,GRIFFTE!N93) -> 1000 | O93: =SUM(C93:N93) -> 12000
B94: Manut./Reformas | C94: =SUM(OUTLET!C94,GRIFFTE!C94) -> 500 | D94: 300 | E94: 300 | F94: 300 | G94: 300 | H94: 300 | I94: 300 | J94: 300 | K94: 300 | L94: 300 | M94: 300 | N94: 300 | O94: =SUM(C94:N94) -> 3800
B95: MAT. DIDÁDICOS | C95: =SUM(OUTLET!C95,GRIFFTE!C95) -> 0 | D95: =SUM(OUTLET!D95,GRIFFTE!D95) -> 0 | E95: =SUM(OUTLET!E95,GRIFFTE!E95) -> 0 | F95: =SUM(OUTLET!F95,GRIFFTE!F95) -> 0 | G95: =SUM(OUTLET!G95,GRIFFTE!G95) -> 0 | H95: =SUM(OUTLET!H95,GRIFFTE!H95) -> 0 | I95: =SUM(OUTLET!I95,GRIFFTE!I95) -> 0 | J95: =SUM(OUTLET!J95,GRIFFTE!J95) -> 0 | ... N95: =SUM(OUTLET!N95,GRIFFTE!N95) -> 0 | O95: =SUM(C95:N95) -> 0
B96: PRÊMIOS/BRINDES | C96: =SUM(OUTLET!C96,GRIFFTE!C96) -> 0 | D96: =SUM(OUTLET!D96,GRIFFTE!D96) -> 0 | E96: =SUM(OUTLET!E96,GRIFFTE!E96) -> 0 | F96: =SUM(OUTLET!F96,GRIFFTE!F96) -> 0 | G96: =SUM(OUTLET!G96,GRIFFTE!G96) -> 0 | H96: =SUM(OUTLET!H96,GRIFFTE!H96) -> 0 | I96: =SUM(OUTLET!I96,GRIFFTE!I96) -> 0 | J96: =SUM(OUTLET!J96,GRIFFTE!J96) -> 0 | ... N96: =SUM(OUTLET!N96,GRIFFTE!N96) -> 0 | O96: =SUM(C96:N96) -> 0
B97: TAXI/APLICATIVOS | C97: =SUM(OUTLET!C97,GRIFFTE!C97) -> 0 | D97: =SUM(OUTLET!D97,GRIFFTE!D97) -> 0 | E97: =SUM(OUTLET!E97,GRIFFTE!E97) -> 0 | F97: =SUM(OUTLET!F97,GRIFFTE!F97) -> 0 | G97: =SUM(OUTLET!G97,GRIFFTE!G97) -> 0 | H97: =SUM(OUTLET!H97,GRIFFTE!H97) -> 0 | I97: =SUM(OUTLET!I97,GRIFFTE!I97) -> 0 | J97: =SUM(OUTLET!J97,GRIFFTE!J97) -> 0 | ... N97: =SUM(OUTLET!N97,GRIFFTE!N97) -> 0 | O97: =SUM(C97:N97) -> 0
B98: PRESTAÇÃO SERV. TERCEIROS | C98: =SUM(OUTLET!C98,GRIFFTE!C98) -> 0 | D98: =SUM(OUTLET!D98,GRIFFTE!D98) -> 0 | E98: =SUM(OUTLET!E98,GRIFFTE!E98) -> 0 | F98: =SUM(OUTLET!F98,GRIFFTE!F98) -> 0 | G98: =SUM(OUTLET!G98,GRIFFTE!G98) -> 0 | H98: =SUM(OUTLET!H98,GRIFFTE!H98) -> 0 | I98: =SUM(OUTLET!I98,GRIFFTE!I98) -> 0 | J98: =SUM(OUTLET!J98,GRIFFTE!J98) -> 0 | ... N98: =SUM(OUTLET!N98,GRIFFTE!N98) -> 0 | O98: =SUM(C98:N98) -> 0
B99: Despesas Financeiras / Bancos | C99: =SUM(C100:C104) -> 100 | D99: =SUM(D100:D104) -> 100 | E99: =SUM(E100:E104) -> 100 | F99: =SUM(F100:F104) -> 100 | G99: =SUM(G100:G104) -> 100 | H99: =SUM(H100:H104) -> 100 | I99: =SUM(I100:I104) -> 100 | J99: =SUM(J100:J104) -> 100 | ... N99: =SUM(N100:N104) -> 100 | O99: =SUM(C99:N99) -> 1200
B100: Juros sobre Empréstimos | C100: =SUM(OUTLET!C100,GRIFFTE!C100) -> 0 | D100: =SUM(OUTLET!D100,GRIFFTE!D100) -> 0 | E100: =SUM(OUTLET!E100,GRIFFTE!E100) -> 0 | F100: =SUM(OUTLET!F100,GRIFFTE!F100) -> 0 | G100: =SUM(OUTLET!G100,GRIFFTE!G100) -> 0 | H100: =SUM(OUTLET!H100,GRIFFTE!H100) -> 0 | I100: =SUM(OUTLET!I100,GRIFFTE!I100) -> 0 | J100: =SUM(OUTLET!J100,GRIFFTE!J100) -> 0 | ... N100: =SUM(OUTLET!N100,GRIFFTE!N100) -> 0 | O100: =SUM(C100:N100) -> 0
B101: Multas | C101: =SUM(OUTLET!C101,GRIFFTE!C101) -> 0 | D101: =SUM(OUTLET!D101,GRIFFTE!D101) -> 0 | E101: =SUM(OUTLET!E101,GRIFFTE!E101) -> 0 | F101: =SUM(OUTLET!F101,GRIFFTE!F101) -> 0 | G101: =SUM(OUTLET!G101,GRIFFTE!G101) -> 0 | H101: =SUM(OUTLET!H101,GRIFFTE!H101) -> 0 | I101: =SUM(OUTLET!I101,GRIFFTE!I101) -> 0 | J101: =SUM(OUTLET!J101,GRIFFTE!J101) -> 0 | ... N101: =SUM(OUTLET!N101,GRIFFTE!N101) -> 0 | O101: =SUM(C101:N101) -> 0
B102: Pagamento de Empréstimos | C102: =SUM(OUTLET!C102,GRIFFTE!C102) -> 0 | D102: =SUM(OUTLET!D102,GRIFFTE!D102) -> 0 | E102: =SUM(OUTLET!E102,GRIFFTE!E102) -> 0 | F102: =SUM(OUTLET!F102,GRIFFTE!F102) -> 0 | G102: =SUM(OUTLET!G102,GRIFFTE!G102) -> 0 | H102: =SUM(OUTLET!H102,GRIFFTE!H102) -> 0 | I102: =SUM(OUTLET!I102,GRIFFTE!I102) -> 0 | J102: =SUM(OUTLET!J102,GRIFFTE!J102) -> 0 | ... N102: =SUM(OUTLET!N102,GRIFFTE!N102) -> 0 | O102: =SUM(C102:N102) -> 0
B103: Tarifas Bancárias | C103: =SUM(OUTLET!C103,GRIFFTE!C103) -> 100 | D103: =SUM(OUTLET!D103,GRIFFTE!D103) -> 100 | E103: =SUM(OUTLET!E103,GRIFFTE!E103) -> 100 | F103: =SUM(OUTLET!F103,GRIFFTE!F103) -> 100 | G103: =SUM(OUTLET!G103,GRIFFTE!G103) -> 100 | H103: =SUM(OUTLET!H103,GRIFFTE!H103) -> 100 | I103: =SUM(OUTLET!I103,GRIFFTE!I103) -> 100 | J103: =SUM(OUTLET!J103,GRIFFTE!J103) -> 100 | ... N103: =SUM(OUTLET!N103,GRIFFTE!N103) -> 100 | O103: =SUM(C103:N103) -> 1200
B104: Despesas Bancárias | C104: =SUM(OUTLET!C104,GRIFFTE!C104) -> 0 | D104: =SUM(OUTLET!D104,GRIFFTE!D104) -> 0 | E104: =SUM(OUTLET!E104,GRIFFTE!E104) -> 0 | F104: =SUM(OUTLET!F104,GRIFFTE!F104) -> 0 | G104: =SUM(OUTLET!G104,GRIFFTE!G104) -> 0 | H104: =SUM(OUTLET!H104,GRIFFTE!H104) -> 0 | I104: =SUM(OUTLET!I104,GRIFFTE!I104) -> 0 | J104: =SUM(OUTLET!J104,GRIFFTE!J104) -> 0 | ... N104: =SUM(OUTLET!N104,GRIFFTE!N104) -> 0 | O104: =SUM(C104:N104) -> 0
B105: Impostos e Taxas | C105: =SUM(C106:C115) -> 0 | D105: =SUM(D106:D115) -> 0 | E105: =SUM(E106:E115) -> 0 | F105: =SUM(F106:F115) -> 0 | G105: =SUM(G106:G115) -> 0 | H105: =SUM(H106:H115) -> 0 | I105: =SUM(I106:I115) -> 0 | J105: =SUM(J106:J115) -> 0 | ... N105: =SUM(N106:N115) -> 0 | O105: =SUM(C105:N105) -> 0
B106: ICMS | C106: =SUM(OUTLET!C106,GRIFFTE!C106) -> 0 | D106: =SUM(OUTLET!D106,GRIFFTE!D106) -> 0 | E106: =SUM(OUTLET!E106,GRIFFTE!E106) -> 0 | F106: =SUM(OUTLET!F106,GRIFFTE!F106) -> 0 | G106: =SUM(OUTLET!G106,GRIFFTE!G106) -> 0 | H106: =SUM(OUTLET!H106,GRIFFTE!H106) -> 0 | I106: =SUM(OUTLET!I106,GRIFFTE!I106) -> 0 | J106: =SUM(OUTLET!J106,GRIFFTE!J106) -> 0 | ... N106: =SUM(OUTLET!N106,GRIFFTE!N106) -> 0 | O106: =SUM(C106:N106) -> 0
B107: IPI | C107: =SUM(OUTLET!C107,GRIFFTE!C107) -> 0 | D107: =SUM(OUTLET!D107,GRIFFTE!D107) -> 0 | E107: =SUM(OUTLET!E107,GRIFFTE!E107) -> 0 | F107: =SUM(OUTLET!F107,GRIFFTE!F107) -> 0 | G107: =SUM(OUTLET!G107,GRIFFTE!G107) -> 0 | H107: =SUM(OUTLET!H107,GRIFFTE!H107) -> 0 | I107: =SUM(OUTLET!I107,GRIFFTE!I107) -> 0 | J107: =SUM(OUTLET!J107,GRIFFTE!J107) -> 0 | ... N107: =SUM(OUTLET!N107,GRIFFTE!N107) -> 0 | O107: =SUM(C107:N107) -> 0
B108: PIS | C108: =SUM(OUTLET!C108,GRIFFTE!C108) -> 0 | D108: =SUM(OUTLET!D108,GRIFFTE!D108) -> 0 | E108: =SUM(OUTLET!E108,GRIFFTE!E108) -> 0 | F108: =SUM(OUTLET!F108,GRIFFTE!F108) -> 0 | G108: =SUM(OUTLET!G108,GRIFFTE!G108) -> 0 | H108: =SUM(OUTLET!H108,GRIFFTE!H108) -> 0 | I108: =SUM(OUTLET!I108,GRIFFTE!I108) -> 0 | J108: =SUM(OUTLET!J108,GRIFFTE!J108) -> 0 | ... N108: =SUM(OUTLET!N108,GRIFFTE!N108) -> 0 | O108: =SUM(C108:N108) -> 0
B109: COFINS | C109: =SUM(OUTLET!C109,GRIFFTE!C109) -> 0 | D109: =SUM(OUTLET!D109,GRIFFTE!D109) -> 0 | E109: =SUM(OUTLET!E109,GRIFFTE!E109) -> 0 | F109: =SUM(OUTLET!F109,GRIFFTE!F109) -> 0 | G109: =SUM(OUTLET!G109,GRIFFTE!G109) -> 0 | H109: =SUM(OUTLET!H109,GRIFFTE!H109) -> 0 | I109: =SUM(OUTLET!I109,GRIFFTE!I109) -> 0 | J109: =SUM(OUTLET!J109,GRIFFTE!J109) -> 0 | ... N109: =SUM(OUTLET!N109,GRIFFTE!N109) -> 0 | O109: =SUM(C109:N109) -> 0
B110: IRPJ | C110: =SUM(OUTLET!C110,GRIFFTE!C110) -> 0 | D110: =SUM(OUTLET!D110,GRIFFTE!D110) -> 0 | E110: =SUM(OUTLET!E110,GRIFFTE!E110) -> 0 | F110: =SUM(OUTLET!F110,GRIFFTE!F110) -> 0 | G110: =SUM(OUTLET!G110,GRIFFTE!G110) -> 0 | H110: =SUM(OUTLET!H110,GRIFFTE!H110) -> 0 | I110: =SUM(OUTLET!I110,GRIFFTE!I110) -> 0 | J110: =SUM(OUTLET!J110,GRIFFTE!J110) -> 0 | ... N110: =SUM(OUTLET!N110,GRIFFTE!N110) -> 0 | O110: =SUM(C110:N110) -> 0
...

Sheet OPERAÇÕES
C1: INSTITUTO DE CAPACITACAO E ACAO SOCIAL O GRITO - PLANEJAMENTO 2025 - OPERAÇÃO
A2: Emitido por RICARDO em 17/11/2023 10:58 | C2: =C47/O$47 -> 0.064550728 | D2: =D47/$O$47 -> 0.14838056 | E2: =E47/$O$47 -> 0.073727634 | F2: =F47/$O$47 -> 0.076103224 | G2: =G47/$O$47 -> 0.076637732 | H2: =H47/$O$47 -> 0.075865665 | I2: =I47/$O$47 -> 0.07723163 | J2: =J47/$O$47 -> 0.077766137 | K2: =K47/$O$47 -> 0.072480449 | ... N2: =N47/$O$47 -> 0.091390148
B3: CATEGORIA | C3: JANEIRO | D3: FEVEREIRO | E3: MARÇO | F3: ABRIL | G3: MAIO | H3: JUNHO | I3: JULHO | J3: AGOSTO | K3: SETEMBRO | L3: OUTUBRO | M3: NOVEMBRO | N3: DEZEMBRO | O3: TOTAL
B5: SALDO ACUMULADO | C5: =C6 -> 119655 | D5: =C5+D6 -> 84734 | E5: =D5+E6 -> 22663 | F5: =E5+F6 -> -41408 | G5: =F5+G6 -> -105929 | H5: =G5+H6 -> -20800 | I5: =H5+I6 -> -85821 | J5: =I5+J6 -> -151292 | K5: =J5+K6 -> -212313 | ... N5: =M5+N6 -> -428896
B6: SALDO MÊS | C6: =SUM(C8-C47) -> 119655 | D6: =SUM(D8-D47) -> -34921 | E6: =SUM(E8-E47) -> -62071 | F6: =SUM(F8-F47) -> -64071 | G6: =SUM(G8-G47) -> -64521 | H6: =SUM(H8-H47) -> 85129 | I6: =SUM(I8-I47) -> -65021 | J6: =SUM(J8-J47) -> -65471 | ... N6: =SUM(N8-N47) -> -76941 | O6: =SUM(C6:N6) -> -428896
B8: RECEITAS | C8: =SUM(C9,C16,C22,C28,C33,C37,C40,C43) -> 174000 | D8: =SUM(D9,D16,D22,D28,D33,D37,D40,D43) -> 90000 | E8: =SUM(E9,E16,E22,E28,E33,E37,E40,E43) -> 0 | F8: =SUM(F9,F16,F22,F28,F33,F37,F40,F43) -> 0 | G8: =SUM(G9,G16,G22,G28,G33,G37,G40,G43) -> 0 | H8: =SUM(H9,H16,H22,H28,H33,H37,H40,H43) -> 149000 | I8: =SUM(I9,I16,I22,I28,I33,I37,I40,I43) -> 0 | J8: =SUM(J9,J16,J22,J28,J33,J37,J40,J43) -> 0 | ... N8: =SUM(N9,N16,N22,N28,N33,N37,N40,N43) -> 0 | O8: =SUM(C8:N8) -> 413000
B9: Devoluções | C9: =SUM(C10:C15) -> 0 | D9: =SUM(D10:D15) -> 0 | E9: =SUM(E10:E15) -> 0 | F9: =SUM(F10:F15) -> 0 | G9: =SUM(G10:G15) -> 0 | H9: =SUM(H10:H15) -> 0 | I9: =SUM(I10:I15) -> 0 | J9: =SUM(J10:J15) -> 0 | ... N9: =SUM(N10:N15) -> 0 | O9: =SUM(C9:N9) -> 0
B10: Devoluções Compra Mercadoria Revenda | C10: 0 | D10: 0 | E10: 0 | F10: 0 | G10: 0 | H10: 0 | I10: 0 | J10: 0 | K10: 0 | L10: 0 | M10: 0 | N10: 0 | O10: =SUM(C10:N10) -> 0
B11: Devoluções de Compra Material Consumo | C11: 0 | D11: 0 | E11: 0 | F11: 0 | G11: 0 | H11: 0 | I11: 0 | J11: 0 | K11: 0 | L11: 0 | M11: 0 | N11: 0 | O11: =SUM(C11:N11) -> 0
B12: Devoluções de Compra de Matéria Prima | C12: 0 | D12: 0 | E12: 0 | F12: 0 | G12: 0 | H12: 0 | I12: 0 | J12: 0 | K12: 0 | L12: 0 | M12: 0 | N12: 0 | O12: =SUM(C12:N12) -> 0
B13: Devoluções de Compra de Ativo | C13: 0 | D13: 0 | E13: 0 | F13: 0 | G13: 0 | H13: 0 | I13: 0 | J13: 0 | K13: 0 | L13: 0 | M13: 0 | N13: 0 | O13: =SUM(C13:N13) -> 0
B14: Devoluções de Compra de Serviços | C14: 0 | D14: 0 | E14: 0 | F14: 0 | G14: 0 | H14: 0 | I14: 0 | J14: 0 | K14: 0 | L14: 0 | M14: 0 | N14: 0 | O14: =SUM(C14:N14) -> 0
B15: Devolução de Doações | C15: 0 | D15: 0 | E15: 0 | F15: 0 | G15: 0 | H15: 0 | I15: 0 | J15: 0 | K15: 0 | L15: 0 | M15: 0 | N15: 0 | O15: =SUM(C15:N15) -> 0
B16: Outras Entradas | C16: =SUM(C17:C21) -> 0 | D16: =SUM(D17:D21) -> 0 | E16: =SUM(E17:E21) -> 0 | F16: =SUM(F17:F21) -> 0 | G16: =SUM(G17:G21) -> 0 | H16: =SUM(H17:H21) -> 0 | I16: =SUM(I17:I21) -> 0 | J16: =SUM(J17:J21) -> 0 | ... N16: =SUM(N17:N21) -> 0 | O16: =SUM(C16:N16) -> 0
B17: Empréstimos Bancários | C17: 0 | D17: 0 | E17: 0 | F17: 0 | G17: 0 | H17: 0 | I17: 0 | J17: 0 | K17: 0 | L17: 0 | M17: 0 | N17: 0 | O17: =SUM(C17:N17) -> 0
B18: Aumento de Capital | C18: 0 | D18: 0 | E18: 0 | F18: 0 | G18: 0 | H18: 0 | I18: 0 | J18: 0 | K18: 0 | L18: 0 | M18: 0 | N18: 0 | O18: =SUM(C18:N18) -> 0
B19: Venda de Ativos | C19: 0 | D19: 0 | E19: 0 | F19: 0 | G19: 0 | H19: 0 | I19: 0 | J19: 0 | K19: 0 | L19: 0 | M19: 0 | N19: 0 | O19: =SUM(C19:N19) -> 0
B20: AJUSTE DE CAIXA | C20: 0 | D20: 0 | E20: 0 | F20: 0 | G20: 0 | H20: 0 | I20: 0 | J20: 0 | K20: 0 | L20: 0 | M20: 0 | N20: 0 | O20: =SUM(C20:N20) -> 0
B21: Prêmios de Seguros / Sinistros | C21: 0 | D21: 0 | E21: 0 | F21: 0 | G21: 0 | H21: 0 | I21: 0 | J21: 0 | K21: 0 | L21: 0 | M21: 0 | N21: 0 | O21: =SUM(C21:N21) -> 0
B22: Doações | C22: =SUM(C23:C27) -> 0 | D22: =SUM(D23:D27) -> 0 | E22: =SUM(E23:E27) -> 0 | F22: =SUM(F23:F27) -> 0 | G22: =SUM(G23:G27) -> 0 | H22: =SUM(H23:H27) -> 0 | I22: =SUM(I23:I27) -> 0 | J22: =SUM(J23:J27) -> 0 | ... N22: =SUM(N23:N27) -> 0 | O22: =SUM(C22:N22) -> 0
B23: Doações Recorrentes | C23: =SUM(EDITAIS!C23,'CASA SONHAR'!C23,'Q. PROF.'!C23,PSICOSSOCIAL!C23,PEC!C23) -> 0 | D23: =SUM(EDITAIS!D23,'CASA SONHAR'!D23,'Q. PROF.'!D23,PSICOSSOCIAL!D23,PEC!D23) -> 0 | E23: =SUM(EDITAIS!E23,'CASA SONHAR'!E23,'Q. PROF.'!E23,PSICOSSOCIAL!E23,PEC!E23) -> 0 | F23: =SUM(EDITAIS!F23,'CASA SONHAR'!F23,'Q. PROF.'!F23,PSICOSSOCIAL!F23,PEC!F23) -> 0 | G23: =SUM(EDITAIS!G23,'CASA SONHAR'!G23,'Q. PROF.'!G23,PSICOSSOCIAL!G23,PEC!G23) -> 0 | H23: =SUM(EDITAIS!H23,'CASA SONHAR'!H23,'Q. PROF.'!H23,PSICOSSOCIAL!H23,PEC!H23) -> 0 | I23: =SUM(EDITAIS!I23,'CASA SONHAR'!I23,'Q. PROF.'!I23,PSICOSSOCIAL!I23,PEC!I23) -> 0 | J23: =SUM(EDITAIS!J23,'CASA SONHAR'!J23,'Q. PROF.'!J23,PSICOSSOCIAL!J23,PEC!J23) -> 0 | ... N23: =SUM(EDITAIS!N23,'CASA SONHAR'!N23,'Q. PROF.'!N23,PSICOSSOCIAL!N23,PEC!N23) -> 0 | O23: =SUM(C23:N23) -> 0
B24: Doações Pontuais PF | C24: =SUM(EDITAIS!C24,'CASA SONHAR'!C24,'Q. PROF.'!C24,PSICOSSOCIAL!C24,PEC!C24) -> 0 | D24: =SUM(EDITAIS!D24,'CASA SONHAR'!D24,'Q. PROF.'!D24,PSICOSSOCIAL!D24,PEC!D24) -> 0 | E24: =SUM(EDITAIS!E24,'CASA SONHAR'!E24,'Q. PROF.'!E24,PSICOSSOCIAL!E24,PEC!E24) -> 0 | F24: =SUM(EDITAIS!F24,'CASA SONHAR'!F24,'Q. PROF.'!F24,PSICOSSOCIAL!F24,PEC!F24) -> 0 | G24: =SUM(EDITAIS!G24,'CASA SONHAR'!G24,'Q. PROF.'!G24,PSICOSSOCIAL!G24,PEC!G24) -> 0 | H24: =SUM(EDITAIS!H24,'CASA SONHAR'!H24,'Q. PROF.'!H24,PSICOSSOCIAL!H24,PEC!H24) -> 0 | I24: =SUM(EDITAIS!I24,'CASA SONHAR'!I24,'Q. PROF.'!I24,PSICOSSOCIAL!I24,PEC!I24) -> 0 | J24: =SUM(EDITAIS!J24,'CASA SONHAR'!J24,'Q. PROF.'!J24,PSICOSSOCIAL!J24,PEC!J24) -> 0 | ... N24: =SUM(EDITAIS!N24,'CASA SONHAR'!N24,'Q. PROF.'!N24,PSICOSSOCIAL!N24,PEC!N24) -> 0 | O24: =SUM(C24:N24) -> 0
B25: Doações Pontuais PJ | C25: =SUM(EDITAIS!C25,'CASA SONHAR'!C25,'Q. PROF.'!C25,PSICOSSOCIAL!C25,PEC!C25) -> 0 | D25: =SUM(EDITAIS!D25,'CASA SONHAR'!D25,'Q. PROF.'!D25,PSICOSSOCIAL!D25,PEC!D25) -> 0 | E25: =SUM(EDITAIS!E25,'CASA SONHAR'!E25,'Q. PROF.'!E25,PSICOSSOCIAL!E25,PEC!E25) -> 0 | F25: =SUM(EDITAIS!F25,'CASA SONHAR'!F25,'Q. PROF.'!F25,PSICOSSOCIAL!F25,PEC!F25) -> 0 | G25: =SUM(EDITAIS!G25,'CASA SONHAR'!G25,'Q. PROF.'!G25,PSICOSSOCIAL!G25,PEC!G25) -> 0 | H25: =SUM(EDITAIS!H25,'CASA SONHAR'!H25,'Q. PROF.'!H25,PSICOSSOCIAL!H25,PEC!H25) -> 0 | I25: =SUM(EDITAIS!I25,'CASA SONHAR'!I25,'Q. PROF.'!I25,PSICOSSOCIAL!I25,PEC!I25) -> 0 | J25: =SUM(EDITAIS!J25,'CASA SONHAR'!J25,'Q. PROF.'!J25,PSICOSSOCIAL!J25,PEC!J25) -> 0 | ... N25: =SUM(EDITAIS!N25,'CASA SONHAR'!N25,'Q. PROF.'!N25,PSICOSSOCIAL!N25,PEC!N25) -> 0 | O25: =SUM(C25:N25) -> 0
B26: Sócio Doador | C26: =SUM(EDITAIS!C26,'CASA SONHAR'!C26,'Q. PROF.'!C26,PSICOSSOCIAL!C26,PEC!C26) -> 0 | D26: =SUM(EDITAIS!D26,'CASA SONHAR'!D26,'Q. PROF.'!D26,PSICOSSOCIAL!D26,PEC!D26) -> 0 | E26: =SUM(EDITAIS!E26,'CASA SONHAR'!E26,'Q. PROF.'!E26,PSICOSSOCIAL!E26,PEC!E26) -> 0 | F26: =SUM(EDITAIS!F26,'CASA SONHAR'!F26,'Q. PROF.'!F26,PSICOSSOCIAL!F26,PEC!F26) -> 0 | G26: =SUM(EDITAIS!G26,'CASA SONHAR'!G26,'Q. PROF.'!G26,PSICOSSOCIAL!G26,PEC!G26) -> 0 | H26: =SUM(EDITAIS!H26,'CASA SONHAR'!H26,'Q. PROF.'!H26,PSICOSSOCIAL!H26,PEC!H26) -> 0 | I26: =SUM(EDITAIS!I26,'CASA SONHAR'!I26,'Q. PROF.'!I26,PSICOSSOCIAL!I26,PEC!I26) -> 0 | J26: =SUM(EDITAIS!J26,'CASA SONHAR'!J26,'Q. PROF.'!J26,PSICOSSOCIAL!J26,PEC!J26) -> 0 | ... N26: =SUM(EDITAIS!N26,'CASA SONHAR'!N26,'Q. PROF.'!N26,PSICOSSOCIAL!N26,PEC!N26) -> 0 | O26: =SUM(C26:N26) -> 0
B27: Patrocínios | C27: =SUM(EDITAIS!C27,'CASA SONHAR'!C27,'Q. PROF.'!C27,PSICOSSOCIAL!C27,PEC!C27) -> 0 | D27: =SUM(EDITAIS!D27,'CASA SONHAR'!D27,'Q. PROF.'!D27,PSICOSSOCIAL!D27,PEC!D27) -> 0 | E27: =SUM(EDITAIS!E27,'CASA SONHAR'!E27,'Q. PROF.'!E27,PSICOSSOCIAL!E27,PEC!E27) -> 0 | F27: =SUM(EDITAIS!F27,'CASA SONHAR'!F27,'Q. PROF.'!F27,PSICOSSOCIAL!F27,PEC!F27) -> 0 | G27: =SUM(EDITAIS!G27,'CASA SONHAR'!G27,'Q. PROF.'!G27,PSICOSSOCIAL!G27,PEC!G27) -> 0 | H27: =SUM(EDITAIS!H27,'CASA SONHAR'!H27,'Q. PROF.'!H27,PSICOSSOCIAL!H27,PEC!H27) -> 0 | I27: =SUM(EDITAIS!I27,'CASA SONHAR'!I27,'Q. PROF.'!I27,PSICOSSOCIAL!I27,PEC!I27) -> 0 | J27: =SUM(EDITAIS!J27,'CASA SONHAR'!J27,'Q. PROF.'!J27,PSICOSSOCIAL!J27,PEC!J27) -> 0 | ... N27: =SUM(EDITAIS!N27,'CASA SONHAR'!N27,'Q. PROF.'!N27,PSICOSSOCIAL!N27,PEC!N27) -> 0 | O27: =SUM(C27:N27) -> 0
B28: Gerando Falcões | C28: =SUM(C29:C32) -> 0 | D28: =SUM(D29:D32) -> 0 | E28: =SUM(E29:E32) -> 0 | F28: =SUM(F29:F32) -> 0 | G28: =SUM(G29:G32) -> 0 | H28: =SUM(H29:H32) -> 0 | I28: =SUM(I29:I32) -> 0 | J28: =SUM(J29:J32) -> 0 | ... N28: =SUM(N29:N32) -> 0 | O28: =SUM(C28:N28) -> 0
B29: Aporte | C29: =SUM(EDITAIS!C29,'CASA SONHAR'!C29,'Q. PROF.'!C29,PSICOSSOCIAL!C29,PEC!C29) -> 0 | D29: =SUM(EDITAIS!D29,'CASA SONHAR'!D29,'Q. PROF.'!D29,PSICOSSOCIAL!D29,PEC!D29) -> 0 | E29: =SUM(EDITAIS!E29,'CASA SONHAR'!E29,'Q. PROF.'!E29,PSICOSSOCIAL!E29,PEC!E29) -> 0 | F29: =SUM(EDITAIS!F29,'CASA SONHAR'!F29,'Q. PROF.'!F29,PSICOSSOCIAL!F29,PEC!F29) -> 0 | G29: =SUM(EDITAIS!G29,'CASA SONHAR'!G29,'Q. PROF.'!G29,PSICOSSOCIAL!G29,PEC!G29) -> 0 | H29: =SUM(EDITAIS!H29,'CASA SONHAR'!H29,'Q. PROF.'!H29,PSICOSSOCIAL!H29,PEC!H29) -> 0 | I29: =SUM(EDITAIS!I29,'CASA SONHAR'!I29,'Q. PROF.'!I29,PSICOSSOCIAL!I29,PEC!I29) -> 0 | J29: =SUM(EDITAIS!J29,'CASA SONHAR'!J29,'Q. PROF.'!J29,PSICOSSOCIAL!J29,PEC!J29) -> 0 | ... N29: =SUM(EDITAIS!N29,'CASA SONHAR'!N29,'Q. PROF.'!N29,PSICOSSOCIAL!N29,PEC!N29) -> 0 | O29: =SUM(C29:N29) -> 0
B30: Falcons Univercity | C30: =SUM(EDITAIS!C30,'CASA SONHAR'!C30,'Q. PROF.'!C30,PSICOSSOCIAL!C30,PEC!C30) -> 0 | D30: =SUM(EDITAIS!D30,'CASA SONHAR'!D30,'Q. PROF.'!D30,PSICOSSOCIAL!D30,PEC!D30) -> 0 | E30: =SUM(EDITAIS!E30,'CASA SONHAR'!E30,'Q. PROF.'!E30,PSICOSSOCIAL!E30,PEC!E30) -> 0 | F30: =SUM(EDITAIS!F30,'CASA SONHAR'!F30,'Q. PROF.'!F30,PSICOSSOCIAL!F30,PEC!F30) -> 0 | G30: =SUM(EDITAIS!G30,'CASA SONHAR'!G30,'Q. PROF.'!G30,PSICOSSOCIAL!G30,PEC!G30) -> 0 | H30: =SUM(EDITAIS!H30,'CASA SONHAR'!H30,'Q. PROF.'!H30,PSICOSSOCIAL!H30,PEC!H30) -> 0 | I30: =SUM(EDITAIS!I30,'CASA SONHAR'!I30,'Q. PROF.'!I30,PSICOSSOCIAL!I30,PEC!I30) -> 0 | J30: =SUM(EDITAIS!J30,'CASA SONHAR'!J30,'Q. PROF.'!J30,PSICOSSOCIAL!J30,PEC!J30) -> 0 | ... N30: =SUM(EDITAIS!N30,'CASA SONHAR'!N30,'Q. PROF.'!N30,PSICOSSOCIAL!N30,PEC!N30) -> 0 | O30: =SUM(C30:N30) -> 0
B31: Regional GF | C31: =SUM(EDITAIS!C31,'CASA SONHAR'!C31,'Q. PROF.'!C31,PSICOSSOCIAL!C31,PEC!C31) -> 0 | D31: =SUM(EDITAIS!D31,'CASA SONHAR'!D31,'Q. PROF.'!D31,PSICOSSOCIAL!D31,PEC!D31) -> 0 | E31: =SUM(EDITAIS!E31,'CASA SONHAR'!E31,'Q. PROF.'!E31,PSICOSSOCIAL!E31,PEC!E31) -> 0 | F31: =SUM(EDITAIS!F31,'CASA SONHAR'!F31,'Q. PROF.'!F31,PSICOSSOCIAL!F31,PEC!F31) -> 0 | G31: =SUM(EDITAIS!G31,'CASA SONHAR'!G31,'Q. PROF.'!G31,PSICOSSOCIAL!G31,PEC!G31) -> 0 | H31: =SUM(EDITAIS!H31,'CASA SONHAR'!H31,'Q. PROF.'!H31,PSICOSSOCIAL!H31,PEC!H31) -> 0 | I31: =SUM(EDITAIS!I31,'CASA SONHAR'!I31,'Q. PROF.'!I31,PSICOSSOCIAL!I31,PEC!I31) -> 0 | J31: =SUM(EDITAIS!J31,'CASA SONHAR'!J31,'Q. PROF.'!J31,PSICOSSOCIAL!J31,PEC!J31) -> 0 | ... N31: =SUM(EDITAIS!N31,'CASA SONHAR'!N31,'Q. PROF.'!N31,PSICOSSOCIAL!N31,PEC!N31) -> 0 | O31: =SUM(C31:N31) -> 0
B32: Favela 3D | C32: =SUM(EDITAIS!C32,'CASA SONHAR'!C32,'Q. PROF.'!C32,PSICOSSOCIAL!C32,PEC!C32) -> 0 | D32: =SUM(EDITAIS!D32,'CASA SONHAR'!D32,'Q. PROF.'!D32,PSICOSSOCIAL!D32,PEC!D32) -> 0 | E32: =SUM(EDITAIS!E32,'CASA SONHAR'!E32,'Q. PROF.'!E32,PSICOSSOCIAL!E32,PEC!E32) -> 0 | F32: =SUM(EDITAIS!F32,'CASA SONHAR'!F32,'Q. PROF.'!F32,PSICOSSOCIAL!F32,PEC!F32) -> 0 | G32: =SUM(EDITAIS!G32,'CASA SONHAR'!G32,'Q. PROF.'!G32,PSICOSSOCIAL!G32,PEC!G32) -> 0 | H32: =SUM(EDITAIS!H32,'CASA SONHAR'!H32,'Q. PROF.'!H32,PSICOSSOCIAL!H32,PEC!H32) -> 0 | I32: =SUM(EDITAIS!I32,'CASA SONHAR'!I32,'Q. PROF.'!I32,PSICOSSOCIAL!I32,PEC!I32) -> 0 | J32: =SUM(EDITAIS!J32,'CASA SONHAR'!J32,'Q. PROF.'!J32,PSICOSSOCIAL!J32,PEC!J32) -> 0 | ... N32: =SUM(EDITAIS!N32,'CASA SONHAR'!N32,'Q. PROF.'!N32,PSICOSSOCIAL!N32,PEC!N32) -> 0 | O32: =SUM(C32:N32) -> 0
B33: Editais/Projetos | C33: =SUM(C34:C36) -> 174000 | D33: =SUM(D34:D36) -> 90000 | E33: =SUM(E34:E36) -> 0 | F33: =SUM(F34:F36) -> 0 | G33: =SUM(G34:G36) -> 0 | H33: =SUM(H34:H36) -> 149000 | I33: =SUM(I34:I36) -> 0 | J33: =SUM(J34:J36) -> 0 | ... N33: =SUM(N34:N36) -> 0 | O33: =SUM(C33:N33) -> 413000
B34: Ecogaiola | C34: =SUM(EDITAIS!C34,'CASA SONHAR'!C34,'Q. PROF.'!C34,PSICOSSOCIAL!C34,PEC!C34) -> 0 | D34: =SUM(EDITAIS!D34,'CASA SONHAR'!D34,'Q. PROF.'!D34,PSICOSSOCIAL!D34,PEC!D34) -> 0 | E34: =SUM(EDITAIS!E34,'CASA SONHAR'!E34,'Q. PROF.'!E34,PSICOSSOCIAL!E34,PEC!E34) -> 0 | F34: =SUM(EDITAIS!F34,'CASA SONHAR'!F34,'Q. PROF.'!F34,PSICOSSOCIAL!F34,PEC!F34) -> 0 | G34: =SUM(EDITAIS!G34,'CASA SONHAR'!G34,'Q. PROF.'!G34,PSICOSSOCIAL!G34,PEC!G34) -> 0 | H34: =SUM(EDITAIS!H34,'CASA SONHAR'!H34,'Q. PROF.'!H34,PSICOSSOCIAL!H34,PEC!H34) -> 0 | I34: =SUM(EDITAIS!I34,'CASA SONHAR'!I34,'Q. PROF.'!I34,PSICOSSOCIAL!I34,PEC!I34) -> 0 | J34: =SUM(EDITAIS!J34,'CASA SONHAR'!J34,'Q. PROF.'!J34,PSICOSSOCIAL!J34,PEC!J34) -> 0 | ... N34: =SUM(EDITAIS!N34,'CASA SONHAR'!N34,'Q. PROF.'!N34,PSICOSSOCIAL!N34,PEC!N34) -> 0 | O34: =SUM(C34:N34) -> 0
B35: Prog. Hab. Polaris | C35: =SUM(EDITAIS!C35,'CASA SONHAR'!C35,'Q. PROF.'!C35,PSICOSSOCIAL!C35,PEC!C35) -> 0 | D35: =SUM(EDITAIS!D35,'CASA SONHAR'!D35,'Q. PROF.'!D35,PSICOSSOCIAL!D35,PEC!D35) -> 0 | E35: =SUM(EDITAIS!E35,'CASA SONHAR'!E35,'Q. PROF.'!E35,PSICOSSOCIAL!E35,PEC!E35) -> 0 | F35: =SUM(EDITAIS!F35,'CASA SONHAR'!F35,'Q. PROF.'!F35,PSICOSSOCIAL!F35,PEC!F35) -> 0 | G35: =SUM(EDITAIS!G35,'CASA SONHAR'!G35,'Q. PROF.'!G35,PSICOSSOCIAL!G35,PEC!G35) -> 0 | H35: =SUM(EDITAIS!H35,'CASA SONHAR'!H35,'Q. PROF.'!H35,PSICOSSOCIAL!H35,PEC!H35) -> 0 | I35: =SUM(EDITAIS!I35,'CASA SONHAR'!I35,'Q. PROF.'!I35,PSICOSSOCIAL!I35,PEC!I35) -> 0 | J35: =SUM(EDITAIS!J35,'CASA SONHAR'!J35,'Q. PROF.'!J35,PSICOSSOCIAL!J35,PEC!J35) -> 0 | ... N35: =SUM(EDITAIS!N35,'CASA SONHAR'!N35,'Q. PROF.'!N35,PSICOSSOCIAL!N35,PEC!N35) -> 0 | O35: =SUM(C35:N35) -> 0
B36: Lei De Incentivo | C36: =SUM(EDITAIS!C36,'CASA SONHAR'!C36,'Q. PROF.'!C36,PSICOSSOCIAL!C36,PEC!C36) -> 174000 | D36: =SUM(EDITAIS!D36,'CASA SONHAR'!D36,'Q. PROF.'!D36,PSICOSSOCIAL!D36,PEC!D36) -> 90000 | E36: =SUM(EDITAIS!E36,'CASA SONHAR'!E36,'Q. PROF.'!E36,PSICOSSOCIAL!E36,PEC!E36) -> 0 | F36: =SUM(EDITAIS!F36,'CASA SONHAR'!F36,'Q. PROF.'!F36,PSICOSSOCIAL!F36,PEC!F36) -> 0 | G36: =SUM(EDITAIS!G36,'CASA SONHAR'!G36,'Q. PROF.'!G36,PSICOSSOCIAL!G36,PEC!G36) -> 0 | H36: =SUM(EDITAIS!H36,'CASA SONHAR'!H36,'Q. PROF.'!H36,PSICOSSOCIAL!H36,PEC!H36) -> 149000 | I36: =SUM(EDITAIS!I36,'CASA SONHAR'!I36,'Q. PROF.'!I36,PSICOSSOCIAL!I36,PEC!I36) -> 0 | J36: =SUM(EDITAIS!J36,'CASA SONHAR'!J36,'Q. PROF.'!J36,PSICOSSOCIAL!J36,PEC!J36) -> 0 | ... N36: =SUM(EDITAIS!N36,'CASA SONHAR'!N36,'Q. PROF.'!N36,PSICOSSOCIAL!N36,PEC!N36) -> 0 | O36: =SUM(C36:N36) -> 413000
B37: Negócios Sociais | C37: =SUM(C38:C39) -> 0 | D37: =SUM(D38:D39) -> 0 | E37: =SUM(E38:E39) -> 0 | F37: =SUM(F38:F39) -> 0 | G37: =SUM(G38:G39) -> 0 | H37: =SUM(H38:H39) -> 0 | I37: =SUM(I38:I39) -> 0 | J37: =SUM(J38:J39) -> 0 | ... N37: =SUM(N38:N39) -> 0 | O37: =SUM(C37:N37) -> 0
B38: Vendas Outlet | C38: =SUM(EDITAIS!C38,'CASA SONHAR'!C38,'Q. PROF.'!C38,PSICOSSOCIAL!C38,PEC!C38) -> 0 | D38: =SUM(EDITAIS!D38,'CASA SONHAR'!D38,'Q. PROF.'!D38,PSICOSSOCIAL!D38,PEC!D38) -> 0 | E38: =SUM(EDITAIS!E38,'CASA SONHAR'!E38,'Q. PROF.'!E38,PSICOSSOCIAL!E38,PEC!E38) -> 0 | F38: =SUM(EDITAIS!F38,'CASA SONHAR'!F38,'Q. PROF.'!F38,PSICOSSOCIAL!F38,PEC!F38) -> 0 | G38: =SUM(EDITAIS!G38,'CASA SONHAR'!G38,'Q. PROF.'!G38,PSICOSSOCIAL!G38,PEC!G38) -> 0 | H38: =SUM(EDITAIS!H38,'CASA SONHAR'!H38,'Q. PROF.'!H38,PSICOSSOCIAL!H38,PEC!H38) -> 0 | I38: =SUM(EDITAIS!I38,'CASA SONHAR'!I38,'Q. PROF.'!I38,PSICOSSOCIAL!I38,PEC!I38) -> 0 | J38: =SUM(EDITAIS!J38,'CASA SONHAR'!J38,'Q. PROF.'!J38,PSICOSSOCIAL!J38,PEC!J38) -> 0 | ... N38: =SUM(EDITAIS!N38,'CASA SONHAR'!N38,'Q. PROF.'!N38,PSICOSSOCIAL!N38,PEC!N38) -> 0 | O38: =SUM(C38:N38) -> 0
B39: Vendas Griffte | C39: =SUM(EDITAIS!C39,'CASA SONHAR'!C39,'Q. PROF.'!C39,PSICOSSOCIAL!C39,PEC!C39) -> 0 | D39: =SUM(EDITAIS!D39,'CASA SONHAR'!D39,'Q. PROF.'!D39,PSICOSSOCIAL!D39,PEC!D39) -> 0 | E39: =SUM(EDITAIS!E39,'CASA SONHAR'!E39,'Q. PROF.'!E39,PSICOSSOCIAL!E39,PEC!E39) -> 0 | F39: =SUM(EDITAIS!F39,'CASA SONHAR'!F39,'Q. PROF.'!F39,PSICOSSOCIAL!F39,PEC!F39) -> 0 | G39: =SUM(EDITAIS!G39,'CASA SONHAR'!G39,'Q. PROF.'!G39,PSICOSSOCIAL!G39,PEC!G39) -> 0 | H39: =SUM(EDITAIS!H39,'CASA SONHAR'!H39,'Q. PROF.'!H39,PSICOSSOCIAL!H39,PEC!H39) -> 0 | I39: =SUM(EDITAIS!I39,'CASA SONHAR'!I39,'Q. PROF.'!I39,PSICOSSOCIAL!I39,PEC!I39) -> 0 | J39: =SUM(EDITAIS!J39,'CASA SONHAR'!J39,'Q. PROF.'!J39,PSICOSSOCIAL!J39,PEC!J39) -> 0 | ... N39: =SUM(EDITAIS!N39,'CASA SONHAR'!N39,'Q. PROF.'!N39,PSICOSSOCIAL!N39,PEC!N39) -> 0 | O39: =SUM(C39:N39) -> 0
B40: Eventos | C40: =SUM(C41:C42) -> 0 | D40: =SUM(D41:D42) -> 0 | E40: =SUM(E41:E42) -> 0 | F40: =SUM(F41:F42) -> 0 | G40: =SUM(G41:G42) -> 0 | H40: =SUM(H41:H42) -> 0 | I40: =SUM(I41:I42) -> 0 | J40: =SUM(J41:J42) -> 0 | ... N40: =SUM(N41:N42) -> 0 | O40: =SUM(C40:N40) -> 0
B41: Clube Do Grito | C41: =SUM(EDITAIS!C41,'CASA SONHAR'!C41,'Q. PROF.'!C41,PSICOSSOCIAL!C41,PEC!C41) -> 0 | D41: =SUM(EDITAIS!D41,'CASA SONHAR'!D41,'Q. PROF.'!D41,PSICOSSOCIAL!D41,PEC!D41) -> 0 | E41: =SUM(EDITAIS!E41,'CASA SONHAR'!E41,'Q. PROF.'!E41,PSICOSSOCIAL!E41,PEC!E41) -> 0 | F41: =SUM(EDITAIS!F41,'CASA SONHAR'!F41,'Q. PROF.'!F41,PSICOSSOCIAL!F41,PEC!F41) -> 0 | G41: =SUM(EDITAIS!G41,'CASA SONHAR'!G41,'Q. PROF.'!G41,PSICOSSOCIAL!G41,PEC!G41) -> 0 | H41: =SUM(EDITAIS!H41,'CASA SONHAR'!H41,'Q. PROF.'!H41,PSICOSSOCIAL!H41,PEC!H41) -> 0 | I41: =SUM(EDITAIS!I41,'CASA SONHAR'!I41,'Q. PROF.'!I41,PSICOSSOCIAL!I41,PEC!I41) -> 0 | J41: =SUM(EDITAIS!J41,'CASA SONHAR'!J41,'Q. PROF.'!J41,PSICOSSOCIAL!J41,PEC!J41) -> 0 | ... N41: =SUM(EDITAIS!N41,'CASA SONHAR'!N41,'Q. PROF.'!N41,PSICOSSOCIAL!N41,PEC!N41) -> 0 | O41: =SUM(C41:N41) -> 0
B42: Crowdfunding | C42: =SUM(EDITAIS!C42,'CASA SONHAR'!C42,'Q. PROF.'!C42,PSICOSSOCIAL!C42,PEC!C42) -> 0 | D42: =SUM(EDITAIS!D42,'CASA SONHAR'!D42,'Q. PROF.'!D42,PSICOSSOCIAL!D42,PEC!D42) -> 0 | E42: =SUM(EDITAIS!E42,'CASA SONHAR'!E42,'Q. PROF.'!E42,PSICOSSOCIAL!E42,PEC!E42) -> 0 | F42: =SUM(EDITAIS!F42,'CASA SONHAR'!F42,'Q. PROF.'!F42,PSICOSSOCIAL!F42,PEC!F42) -> 0 | G42: =SUM(EDITAIS!G42,'CASA SONHAR'!G42,'Q. PROF.'!G42,PSICOSSOCIAL!G42,PEC!G42) -> 0 | H42: =SUM(EDITAIS!H42,'CASA SONHAR'!H42,'Q. PROF.'!H42,PSICOSSOCIAL!H42,PEC!H42) -> 0 | I42: =SUM(EDITAIS!I42,'CASA SONHAR'!I42,'Q. PROF.'!I42,PSICOSSOCIAL!I42,PEC!I42) -> 0 | J42: =SUM(EDITAIS!J42,'CASA SONHAR'!J42,'Q. PROF.'!J42,PSICOSSOCIAL!J42,PEC!J42) -> 0 | ... N42: =SUM(EDITAIS!N42,'CASA SONHAR'!N42,'Q. PROF.'!N42,PSICOSSOCIAL!N42,PEC!N42) -> 0 | O42: =SUM(C42:N42) -> 0
B43: Aplicações | C43: =SUM(C44:C46) -> 0 | D43: =SUM(D44:D46) -> 0 | E43: =SUM(E44:E46) -> 0 | F43: =SUM(F44:F46) -> 0 | G43: =SUM(G44:G46) -> 0 | H43: =SUM(H44:H46) -> 0 | I43: =SUM(I44:I46) -> 0 | J43: =SUM(J44:J46) -> 0 | ... N43: =SUM(N44:N46) -> 0 | O43: =SUM(C43:N43) -> 0
B44: Resgate Aplicações (Clube do Grito 2023) | C44: =SUM(EDITAIS!C44,'CASA SONHAR'!C44,'Q. PROF.'!C44,PSICOSSOCIAL!C44,PEC!C44) -> 0 | D44: =SUM(EDITAIS!D44,'CASA SONHAR'!D44,'Q. PROF.'!D44,PSICOSSOCIAL!D44,PEC!D44) -> 0 | E44: =SUM(EDITAIS!E44,'CASA SONHAR'!E44,'Q. PROF.'!E44,PSICOSSOCIAL!E44,PEC!E44) -> 0 | F44: =SUM(EDITAIS!F44,'CASA SONHAR'!F44,'Q. PROF.'!F44,PSICOSSOCIAL!F44,PEC!F44) -> 0 | G44: =SUM(EDITAIS!G44,'CASA SONHAR'!G44,'Q. PROF.'!G44,PSICOSSOCIAL!G44,PEC!G44) -> 0 | H44: =SUM(EDITAIS!H44,'CASA SONHAR'!H44,'Q. PROF.'!H44,PSICOSSOCIAL!H44,PEC!H44) -> 0 | I44: =SUM(EDITAIS!I44,'CASA SONHAR'!I44,'Q. PROF.'!I44,PSICOSSOCIAL!I44,PEC!I44) -> 0 | J44: =SUM(EDITAIS!J44,'CASA SONHAR'!J44,'Q. PROF.'!J44,PSICOSSOCIAL!J44,PEC!J44) -> 0 | ... N44: =SUM(EDITAIS!N44,'CASA SONHAR'!N44,'Q. PROF.'!N44,PSICOSSOCIAL!N44,PEC!N44) -> 0 | O44: =SUM(C44:N44) -> 0
